Workbook

Sheet Lançamentos
A1: ,
A2: Data | B2: Descrição | C2: Tipo | D2: Categoria | E2: Conta | F2: Forma de pagamento | G2: Valor | I2: Obs | J2: Mês | K2: Saldo acumulado
A3: 46204 | B3: Leite | C3: Saída | D3: Vendas | E3: Caixa | F3: Dinheiro | J3: =TEXT(A3,"yyyy-mm") -> yyyy-07 | K3: =G3 -> 0
A4: 46204 | B4: Tortelli | C4: Saída | D4: Vendas | E4: Banco Principal | J4: =TEXT(A4,"yyyy-mm") -> yyyy-07 | K4: =K3 + IF(C4="Entrada", G4, -G4) -> 0
A5: 46204 | B5: Ecila | C5: Saída | D5: Matéria Prima | E5: Banco Principal | G5: 115.8 | J5: =TEXT(A5,"yyyy-mm") -> yyyy-07 | K5: =K4 + IF(C5="Entrada", G5, -G5) -> -115.8
A6: 46204 | B6: Vendas | C6: Entrada | D6: Vendas | G6: 1762 | J6: =TEXT(A6,"yyyy-mm") -> yyyy-07 | K6: =K5 + IF(C6="Entrada", G6, -G6) -> 1646.2
A7: 46204 | B7: Vendas Ifood | C7: Entrada | D7: Vendas iFood | E7: Banco Principal | G7: 82 | J7: =TEXT(A7,"yyyy-mm") -> yyyy-07 | K7: =K6 + IF(C7="Entrada", G7, -G7) -> 1728.2
A8: 46204 | B8: Motoboy | C8: Saída | D8: iFood | E8: Banco Principal | F8: Pix | G8: 9 | J8: =TEXT(A8,"yyyy-mm") -> yyyy-07 | K8: =K7 + IF(C8="Entrada", G8, -G8) -> 1719.2
A9: 46204 | B9: Faxina | C9: Saída | D9: Salário | E9: Banco Principal | F9: Pix | G9: 1100 | J9: =TEXT(A9,"yyyy-mm") -> yyyy-07 | K9: =K8 + IF(C9="Entrada", G9, -G9) -> 619.2
A10: 46204 | B10: Canteiros ( reembolsar) | C10: Saída | D10: Manutenção | E10: Banco Principal | F10: Pix | G10: 400 | J10: =TEXT(A10,"yyyy-mm") -> yyyy-07 | K10: =K9 + IF(C10="Entrada", G10, -G10) -> 219.2
A11: 46204 | B11: Tais salário ja pago mes passado de adiantamento | C11: Saída | D11: Salário | E11: Banco Principal | F11: Pix | G11: 3000 | J11: =TEXT(A11,"yyyy-mm") -> yyyy-07 | K11: =K10 + IF(C11="Entrada", G11, -G11) -> -2780.8
A12: 46205 | B12: Vendas | C12: Entrada | D12: Vendas | G12: 1659 | J12: =TEXT(A12,"yyyy-mm") -> yyyy-07 | K12: =K11 + IF(C12="Entrada", G12, -G12) -> -1121.8
A13: 46205 | B13: Vendas Ifood | C13: Entrada | D13: Vendas iFood | E13: Banco Principal | G13: 0 | J13: =TEXT(A13,"yyyy-mm") -> yyyy-07 | K13: =K12 + IF(C13="Entrada", G13, -G13) -> -1121.8
A14: 46205 | B14: Motoboy | C14: Saída | D14: iFood | E14: Banco Principal | F14: Pix | G14: 0 | J14: =TEXT(A14,"yyyy-mm") -> yyyy-07 | K14: =K13 + IF(C14="Entrada", G14, -G14) -> -1121.8
A15: 46205 | B15: Leite | C15: Saída | D15: Matéria Prima | E15: Caixa | F15: Dinheiro | G15: 240 | J15: =TEXT(A15,"yyyy-mm") -> yyyy-07 | K15: =K14 + IF(C15="Entrada", G15, -G15) -> -1361.8
A16: 46206 | B16: Vendas | C16: Entrada | D16: Vendas | G16: 3246 | J16: =TEXT(A16,"yyyy-mm") -> yyyy-07 | K16: =K15 + IF(C16="Entrada", G16, -G16) -> 1884.2
A17: 46206 | B17: Vendas Ifood | C17: Entrada | D17: Vendas iFood | E17: Banco Principal | G17: 106 | J17: =TEXT(A17,"yyyy-mm") -> yyyy-07 | K17: =K16 + IF(C17="Entrada", G17, -G17) -> 1990.2
A18: 46206 | B18: Motoboy | C18: Saída | D18: iFood | E18: Banco Principal | F18: Pix | G18: 18 | J18: =TEXT(A18,"yyyy-mm") -> yyyy-07 | K18: =K17 + IF(C18="Entrada", G18, -G18) -> 1972.2
A19: 46206 | B19: Frutas | C19: Saída | D19: Matéria Prima | E19: Banco Principal | F19: Pix | G19: 164 | J19: =TEXT(A19,"yyyy-mm") -> yyyy-07 | K19: =K18 + IF(C19="Entrada", G19, -G19) -> 1808.2
A20: 46206 | B20: Leite | C20: Saída | D20: Matéria Prima | E20: Caixa | F20: Dinheiro | G20: 376 | J20: =TEXT(A20,"yyyy-mm") -> yyyy-07 | K20: =K19 + IF(C20="Entrada", G20, -G20) -> 1432.2
A21: 46206 | B21: Folga Luany 50+100 | C21: Saída | D21: Freelancer | E21: Banco Principal | F21: Pix | G21: 150 | J21: =TEXT(A21,"yyyy-mm") -> yyyy-07 | K21: =K20 + IF(C21="Entrada", G21, -G21) -> 1282.2
A22: 46207 | B22: Vendas | C22: Entrada | D22: Vendas | G22: 5206 | J22: =TEXT(A22,"yyyy-mm") -> yyyy-07 | K22: =K21 + IF(C22="Entrada", G22, -G22) -> 6488.2
A23: 46207 | B23: Vebdas Ifood | C23: Entrada | D23: Vendas iFood | E23: Banco Principal | G23: 150 | J23: =TEXT(A23,"yyyy-mm") -> yyyy-07 | K23: =K22 + IF(C23="Entrada", G23, -G23) -> 6638.2
A24: 46207 | B24: Motoboy | C24: Saída | D24: iFood | E24: Banco Principal | F24: Pix | G24: 35 | J24: =TEXT(A24,"yyyy-mm") -> yyyy-07 | K24: =K23 + IF(C24="Entrada", G24, -G24) -> 6603.2
A25: 46207 | B25: Freelancer | C25: Saída | D25: Freelancer | E25: Caixa | F25: Dinheiro | G25: 150 | J25: =TEXT(A25,"yyyy-mm") -> yyyy-07 | K25: =K24 + IF(C25="Entrada", G25, -G25) -> 6453.2
A26: 46208 | B26: Vendas | C26: Entrada | D26: Vendas | G26: 4084 | J26: =TEXT(A26,"yyyy-mm") -> yyyy-07 | K26: =K25 + IF(C26="Entrada", G26, -G26) -> 10537.2
A27: 46208 | B27: Vendas Ifood | C27: Entrada | D27: Vendas iFood | E27: Banco Principal | G27: 394 | J27: =TEXT(A27,"yyyy-mm") -> yyyy-07 | K27: =K26 + IF(C27="Entrada", G27, -G27) -> 10931.2
A28: 46208 | B28: Motoby | C28: Saída | D28: iFood | E28: Banco Principal | F28: Pix | G28: 35 | J28: =TEXT(A28,"yyyy-mm") -> yyyy-07 | K28: =K27 + IF(C28="Entrada", G28, -G28) -> 10896.2
A29: 46208 | B29: Freelancer | C29: Saída | D29: Freelancer | E29: Caixa | F29: Dinheiro | G29: 150 | J29: =TEXT(A29,"yyyy-mm") -> yyyy-07 | K29: =K28 + IF(C29="Entrada", G29, -G29) -> 10746.2
A30: 46209 | B30: Vendas | C30: Entrada | D30: Vendas | G30: 1513 | J30: =TEXT(A30,"yyyy-mm") -> yyyy-07 | K30: =K29 + IF(C30="Entrada", G30, -G30) -> 12259.2
A31: 46209 | B31: Vendas Ifood | C31: Entrada | D31: Vendas iFood | E31: Banco Principal | G31: 151 | J31: =TEXT(A31,"yyyy-mm") -> yyyy-07 | K31: =K30 + IF(C31="Entrada", G31, -G31) -> 12410.2
A32: 46209 | B32: Motoboy | C32: Saída | D32: iFood | E32: Banco Principal | F32: Pix | G32: 18 | J32: =TEXT(A32,"yyyy-mm") -> yyyy-07 | K32: =K31 + IF(C32="Entrada", G32, -G32) -> 12392.2
A33: 46207 | B33: Extra Nathalia (já tinha pago, mandei pra conta Tais) | C33: Saída | D33: Freelancer | E33: Banco Principal | F33: Pix | G33: 300 | J33: =TEXT(A33,"yyyy-mm") -> yyyy-07 | K33: =K32 + IF(C33="Entrada", G33, -G33) -> 12092.2
A34: 46208 | B34: Croissant | C34: Saída | D34: Matéria Prima | E34: Banco Principal | F34: Pix | G34: 225 | J34: =TEXT(A34,"yyyy-mm") -> yyyy-07 | K34: =K33 + IF(C34="Entrada", G34, -G34) -> 11867.2
A35: 46209 | B35: Aluguel | C35: Saída | D35: CustoFixo | E35: Banco Principal | G35: 8918.64 | J35: =TEXT(A35,"yyyy-mm") -> yyyy-07 | K35: =K34 + IF(C35="Entrada", G35, -G35) -> 2948.56
A36: 46209 | B36: Iptu | C36: Saída | D36: CustoFixo | E36: Banco Principal | F36: Pix | G36: 94.9 | J36: =TEXT(A36,"yyyy-mm") -> yyyy-07 | K36: =K35 + IF(C36="Entrada", G36, -G36) -> 2853.66
A37: 46209 | B37: Alarme | C37: Saída | D37: CustoFixo | E37: Banco Principal | G37: 100 | J37: =TEXT(A37,"yyyy-mm") -> yyyy-07 | K37: =K36 + IF(C37="Entrada", G37, -G37) -> 2753.66
A38: 46209 | B38: Polar | C38: Saída | D38: Matéria Prima | E38: Banco Principal | G38: 177.86 | J38: =TEXT(A38,"yyyy-mm") -> yyyy-07 | K38: =K37 + IF(C38="Entrada", G38, -G38) -> 2575.8
A39: 46209 | B39: Polar | C39: Saída | D39: Matéria Prima | E39: Banco Principal | G39: 321.07 | J39: =TEXT(A39,"yyyy-mm") -> yyyy-07 | K39: =K38 + IF(C39="Entrada", G39, -G39) -> 2254.73
A40: 46210 | B40: Riber | C40: Saída | D40: Matéria Prima | E40: Banco Principal | G40: 529.5 | J40: =TEXT(A40,"yyyy-mm") -> yyyy-07 | K40: =K39 + IF(C40="Entrada", G40, -G40) -> 1725.23
A41: 46210 | B41: Vendas | C41: Entrada | D41: Vendas | G41: 1628 | J41: =TEXT(A41,"yyyy-mm") -> yyyy-07 | K41: =K40 + IF(C41="Entrada", G41, -G41) -> 3353.23
A42: 46210 | B42: Vendas iFood | C42: Entrada | D42: Vendas iFood | E42: Banco Principal | G42: 76 | J42: =TEXT(A42,"yyyy-mm") -> yyyy-07 | K42: =K41 + IF(C42="Entrada", G42, -G42) -> 3429.23
A43: 46210 | B43: Motoboy | C43: Saída | D43: iFood | E43: Banco Principal | F43: Pix | G43: 24 | J43: =TEXT(A43,"yyyy-mm") -> yyyy-07 | K43: =K42 + IF(C43="Entrada", G43, -G43) -> 3405.23
A44: 46210 | B44: Salarios + cubas | C44: Saída | D44: Salário | E44: Banco Principal | F44: Pix | G44: 4858.41 | J44: =TEXT(A44,"yyyy-mm") -> yyyy-07 | K44: =K43 + IF(C44="Entrada", G44, -G44) -> -1453.18
A45: 46211 | B45: Cartão | C45: Saída | D45: Cartao de Credito | E45: Banco Principal | G45: 1899.95 | J45: =TEXT(A45,"yyyy-mm") -> yyyy-07 | K45: =K44 + IF(C45="Entrada", G45, -G45) -> -3353.13
A46: 46211 | B46: Tráfego pago | C46: Saída | D46: Marketing | E46: Banco Principal | G46: 1000 | J46: =TEXT(A46,"yyyy-mm") -> yyyy-07 | K46: =K45 + IF(C46="Entrada", G46, -G46) -> -4353.13
A47: 46211 | B47: Água | C47: Saída | D47: Matéria Prima | E47: Banco Principal | F47: Pix | G47: 212 | J47: =TEXT(A47,"yyyy-mm") -> yyyy-07 | K47: =K46 + IF(C47="Entrada", G47, -G47) -> -4565.13
A48: 46211 | B48: Vendas | C48: Entrada | D48: Vendas | G48: 1206 | J48: =TEXT(A48,"yyyy-mm") -> yyyy-07 | K48: =K47 + IF(C48="Entrada", G48, -G48) -> -3359.13
A49: 46211 | B49: Vendas iFood | C49: Entrada | D49: Vendas iFood | E49: Banco Principal | G49: 150 | J49: =TEXT(A49,"yyyy-mm") -> yyyy-07 | K49: =K48 + IF(C49="Entrada", G49, -G49) -> -3209.13
A50: 46211 | B50: Motoboy | C50: Saída | D50: iFood | E50: Banco Principal | F50: Pix | G50: 36 | J50: =TEXT(A50,"yyyy-mm") -> yyyy-07 | K50: =K49 + IF(C50="Entrada", G50, -G50) -> -3245.13
A51: 46211 | B51: Pacoquita e goiabada | C51: Saída | D51: Matéria Prima | E51: Banco Principal | F51: Pix | G51: 79.2 | J51: =TEXT(A51,"yyyy-mm") -> yyyy-07 | K51: =K50 + IF(C51="Entrada", G51, -G51) -> -3324.33
A52: 46211 | B52: Adiantamento Tais | C52: Saída | D52: Salário | E52: Banco Principal | F52: Pix | G52: 500 | J52: =TEXT(A52,"yyyy-mm") -> yyyy-07 | K52: =K51 + IF(C52="Entrada", G52, -G52) -> -3824.33
A53: 46212 | B53: Vendas | C53: Entrada | D53: Vendas | G53: 2918 | J53: =TEXT(A53,"yyyy-mm") -> yyyy-07 | K53: =K52 + IF(C53="Entrada", G53, -G53) -> -906.33
A54: 46212 | B54: Vendas iFood | C54: Entrada | D54: Vendas iFood | E54: Banco Principal | G54: 100 | J54: =TEXT(A54,"yyyy-mm") -> yyyy-07 | K54: =K53 + IF(C54="Entrada", G54, -G54) -> -806.33
A55: 46212 | B55: Motoboy | C55: Saída | D55: iFood | E55: Banco Principal | F55: Pix | G55: 18 | J55: =TEXT(A55,"yyyy-mm") -> yyyy-07 | K55: =K54 + IF(C55="Entrada", G55, -G55) -> -824.33
A56: 46212 | B56: Kitanda maracujá | C56: Saída | D56: Matéria Prima | E56: Banco Principal | F56: Pix | G56: 116 | J56: =TEXT(A56,"yyyy-mm") -> yyyy-07 | K56: =K55 + IF(C56="Entrada", G56, -G56) -> -940.33
A57: 46212 | B57: Kitanda abacaxi | C57: Saída | D57: Matéria Prima | E57: Banco Principal | F57: Pix | G57: 52.55 | J57: =TEXT(A57,"yyyy-mm") -> yyyy-07 | K57: =K56 + IF(C57="Entrada", G57, -G57) -> -992.88
A58: 46213 | B58: Vendas | C58: Entrada | D58: Vendas | G58: 5033 | J58: =TEXT(A58,"yyyy-mm") -> yyyy-07 | K58: =K57 + IF(C58="Entrada", G58, -G58) -> 4040.12
A59: 46213 | B59: Vendas iFood | C59: Entrada | D59: Vendas iFood | E59: Banco Principal | G59: 0 | J59: =TEXT(A59,"yyyy-mm") -> yyyy-07 | K59: =K58 + IF(C59="Entrada", G59, -G59) -> 4040.12
A60: 46213 | B60: Motoboy | C60: Saída | D60: iFood | E60: Banco Principal | F60: Pix | G60: 0 | J60: =TEXT(A60,"yyyy-mm") -> yyyy-07 | K60: =K59 + IF(C60="Entrada", G60, -G60) -> 4040.12
A61: 46213 | B61: Leite | C61: Saída | D61: Matéria Prima | E61: Caixa | F61: Dinheiro | G61: 423 | J61: =TEXT(A61,"yyyy-mm") -> yyyy-07 | K61: =K60 + IF(C61="Entrada", G61, -G61) -> 3617.12
A62: 46213 | B62: Adiantamento Tais | C62: Saída | D62: Salário | E62: Banco Principal | F62: Pix | G62: 2000 | J62: =TEXT(A62,"yyyy-mm") -> yyyy-07 | K62: =K61 + IF(C62="Entrada", G62, -G62) -> 1617.12
A63: 46213 | B63: Boleto Unigra | C63: Saída | D63: Matéria Prima | E63: Banco Principal | G63: 1085.93 | J63: =TEXT(A63,"yyyy-mm") -> yyyy-07 | K63: =K62 + IF(C63="Entrada", G63, -G63) -> 531.19
A64: 46213 | B64: Marketing | C64: Saída | D64: Marketing | E64: Banco Principal | G64: 450 | J64: =TEXT(A64,"yyyy-mm") -> yyyy-07 | K64: =K63 + IF(C64="Entrada", G64, -G64) -> 81.19
A65: 46213 | B65: Royalt | C65: Saída | D65: Royalt | E65: Banco Principal | G65: 4757.25 | J65: =TEXT(A65,"yyyy-mm") -> yyyy-07 | K65: =K64 + IF(C65="Entrada", G65, -G65) -> -4676.06
A66: 46213 | B66: Seguro de vida | C66: Saída | D66: Salário | E66: Banco Principal | G66: 48 | J66: =TEXT(A66,"yyyy-mm") -> yyyy-07 | K66: =K65 + IF(C66="Entrada", G66, -G66) -> -4724.06
A67: 46213 | B67: Plano de saúde | C67: Saída | D67: Salário | E67: Banco Principal | G67: 163.6 | J67: =TEXT(A67,"yyyy-mm") -> yyyy-07 | K67: =K66 + IF(C67="Entrada", G67, -G67) -> -4887.66
A68: 46214 | B68: Vendas | C68: Entrada | D68: Vendas | G68: 7495 | J68: =TEXT(A68,"yyyy-mm") -> yyyy-07 | K68: =K67 + IF(C68="Entrada", G68, -G68) -> 2607.34
A69: 46214 | B69: Vendas Ifood | C69: Entrada | D69: Vendas iFood | E69: Banco Principal | G69: 217 | J69: =TEXT(A69,"yyyy-mm") -> yyyy-07 | K69: =K68 + IF(C69="Entrada", G69, -G69) -> 2824.34
A70: 46214 | B70: Motoboy | C70: Saída | D70: iFood | E70: Banco Principal | F70: Pix | G70: 35 | J70: =TEXT(A70,"yyyy-mm") -> yyyy-07 | K70: =K69 + IF(C70="Entrada", G70, -G70) -> 2789.34
A71: 46214 | B71: Freelancer | C71: Saída | D71: Freelancer | E71: Caixa | F71: Dinheiro | G71: 150 | J71: =TEXT(A71,"yyyy-mm") -> yyyy-07 | K71: =K70 + IF(C71="Entrada", G71, -G71) -> 2639.34
A72: 46214 | B72: Bolo Aniversariante | C72: Saída | D72: Manutenção | E72: Banco Principal | F72: Pix | G72: 66.5 | J72: =TEXT(A72,"yyyy-mm") -> yyyy-07 | K72: =K71 + IF(C72="Entrada", G72, -G72) -> 2572.84
A73: 46215 | B73: VEndas | C73: Entrada | D73: Vendas | G73: 5865 | J73: =TEXT(A73,"yyyy-mm") -> yyyy-07 | K73: =K72 + IF(C73="Entrada", G73, -G73) -> 8437.84
A74: 46215 | B74: Vendas Ifood | C74: Entrada | D74: Vendas iFood | E74: Banco Principal | G74: 284 | J74: =TEXT(A74,"yyyy-mm") -> yyyy-07 | K74: =K73 + IF(C74="Entrada", G74, -G74) -> 8721.84
A75: 46215 | B75: Motoboy | C75: Saída | D75: iFood | E75: Banco Principal | F75: Pix | G75: 36 | J75: =TEXT(A75,"yyyy-mm") -> yyyy-07 | K75: =K74 + IF(C75="Entrada", G75, -G75) -> 8685.84
A76: 46215 | B76: Freelancer | C76: Saída | D76: Freelancer | E76: Caixa | F76: Dinheiro | G76: 150 | J76: =TEXT(A76,"yyyy-mm") -> yyyy-07 | K76: =K75 + IF(C76="Entrada", G76, -G76) -> 8535.84
A77: 46215 | B77: Leite | C77: Saída | D77: Matéria Prima | E77: Caixa | F77: Dinheiro | G77: 100 | J77: =TEXT(A77,"yyyy-mm") -> yyyy-07 | K77: =K76 + IF(C77="Entrada", G77, -G77) -> 8435.84
A78: 46216 | B78: Vendas | C78: Entrada | D78: Vendas | G78: 2041 | J78: =TEXT(A78,"yyyy-mm") -> yyyy-07 | K78: =K77 + IF(C78="Entrada", G78, -G78) -> 10476.84
A79: 46216 | B79: Vendas Ifood | C79: Entrada | D79: Vendas iFood | E79: Banco Principal | G79: 0 | J79: =TEXT(A79,"yyyy-mm") -> yyyy-07 | K79: =K78 + IF(C79="Entrada", G79, -G79) -> 10476.84
A80: 46216 | B80: Motoboy | C80: Saída | D80: iFood | E80: Banco Principal | F80: Pix | G80: 0 | J80: =TEXT(A80,"yyyy-mm") -> yyyy-07 | K80: =K79 + IF(C80="Entrada", G80, -G80) -> 10476.84
A81: 46216 | B81: Boleto Polar | C81: Saída | D81: Matéria Prima | E81: Banco Principal | G81: 211.23 | J81: =TEXT(A81,"yyyy-mm") -> yyyy-07 | K81: =K80 + IF(C81="Entrada", G81, -G81) -> 10265.61
A82: 46216 | B82: Creme de Leite | C82: Saída | D82: Matéria Prima | E82: Banco Principal | F82: Pix | G82: 458.38 | J82: =TEXT(A82,"yyyy-mm") -> yyyy-07 | K82: =K81 + IF(C82="Entrada", G82, -G82) -> 9807.23
A83: 46217 | B83: Boleto Riber | C83: Saída | D83: Matéria Prima | E83: Banco Principal | G83: 852.89 | J83: =TEXT(A83,"yyyy-mm") -> yyyy-07 | K83: =K82 + IF(C83="Entrada", G83, -G83) -> 8954.34
A84: 46217 | B84: Boleto Diniz | C84: Saída | D84: Matéria Prima | E84: Banco Principal | G84: 217.35 | J84: =TEXT(A84,"yyyy-mm") -> yyyy-07 | K84: =K83 + IF(C84="Entrada", G84, -G84) -> 8736.99
A85: 46217 | B85: Boleto Diniz | C85: Saída | D85: Matéria Prima | E85: Banco Principal | G85: 379.7 | J85: =TEXT(A85,"yyyy-mm") -> yyyy-07 | K85: =K84 + IF(C85="Entrada", G85, -G85) -> 8357.29
A86: 46217 | B86: Vendas | C86: Entrada | D86: Vendas | G86: 1605 | J86: =TEXT(A86,"yyyy-mm") -> yyyy-07 | K86: =K85 + IF(C86="Entrada", G86, -G86) -> 9962.29
A87: 46217 | B87: Vendas Ifood | C87: Entrada | D87: Vendas iFood | E87: Banco Principal | G87: 0 | J87: =TEXT(A87,"yyyy-mm") -> yyyy-07 | K87: =K86 + IF(C87="Entrada", G87, -G87) -> 9962.29
A88: 46217 | B88: Motoboy | C88: Saída | D88: iFood | E88: Banco Principal | F88: Pix | G88: 0 | J88: =TEXT(A88,"yyyy-mm") -> yyyy-07 | K88: =K87 + IF(C88="Entrada", G88, -G88) -> 9962.29
A89: 46216 | B89: Extras Nathalia | C89: Saída | D89: Freelancer | E89: Banco Principal | F89: Pix | G89: 720 | J89: =TEXT(A89,"yyyy-mm") -> yyyy-07 | K89: =K88 + IF(C89="Entrada", G89, -G89) -> 9242.29
A90: 46216 | B90: Adiantamento Tais | C90: Saída | E90: Banco Principal | F90: Pix | G90: 1650 | J90: =TEXT(A90,"yyyy-mm") -> yyyy-07 | K90: =K89 + IF(C90="Entrada", G90, -G90) -> 7592.29
A91: 46216 | B91: Castanha de caju a vista | C91: Saída | D91: Matéria Prima | E91: Banco Principal | F91: Pix | G91: 941.33 | J91: =TEXT(A91,"yyyy-mm") -> yyyy-07 | K91: =K90 + IF(C91="Entrada", G91, -G91) -> 6650.96
A92: 46216 | B92: Thales restante coisas q comprei de jf | C92: Saída | D92: Matéria Prima | E92: Banco Principal | F92: Pix | G92: 1000 | J92: =TEXT(A92,"yyyy-mm") -> yyyy-07 | K92: =K91 + IF(C92="Entrada", G92, -G92) -> 5650.96
A93: 46216 | B93: Potinho pra calda | C93: Saída | D93: Mat Consumo | E93: Banco Principal | F93: Pix | G93: 172.15 | J93: =TEXT(A93,"yyyy-mm") -> yyyy-07 | K93: =K92 + IF(C93="Entrada", G93, -G93) -> 5478.81
A94: 46218 | B94: Vendas | C94: Entrada | D94: Vendas | G94: 1726 | J94: =TEXT(A94,"yyyy-mm") -> yyyy-07 | K94: =K93 + IF(C94="Entrada", G94, -G94) -> 7204.81
A95: 46218 | B95: Vendas Ifood | C95: Entrada | D95: Vendas iFood | E95: Banco Principal | G95: 57 | J95: =TEXT(A95,"yyyy-mm") -> yyyy-07 | K95: =K94 + IF(C95="Entrada", G95, -G95) -> 7261.81
A96: 46218 | B96: Motoboy | C96: Saída | D96: iFood | E96: Banco Principal | F96: Pix | G96: 9 | J96: =TEXT(A96,"yyyy-mm") -> yyyy-07 | K96: =K95 + IF(C96="Entrada", G96, -G96) -> 7252.81
A97: 46218 | B97: Contabilidade | C97: Saída | D97: Contabilidade | E97: Banco Principal | G97: 800 | J97: =TEXT(A97,"yyyy-mm") -> yyyy-07 | K97: =K96 + IF(C97="Entrada", G97, -G97) -> 6452.81
A98: 46218 | B98: DAE | C98: Saída | D98: Impostos | E98: Banco Principal | G98: 1629.92 | J98: =TEXT(A98,"yyyy-mm") -> yyyy-07 | K98: =K97 + IF(C98="Entrada", G98, -G98) -> 4822.89
A99: 46218 | B99: Leite | C99: Saída | D99: Matéria Prima | E99: Caixa | F99: Dinheiro | G99: 100 | J99: =TEXT(A99,"yyyy-mm") -> yyyy-07 | K99: =K98 + IF(C99="Entrada", G99, -G99) -> 4722.89
A100: 46218 | B100: Alisson | C100: Saída | D100: Salário | E100: Caixa | F100: Dinheiro | G100: 90 | J100: =TEXT(A100,"yyyy-mm") -> yyyy-07 | K100: =K99 + IF(C100="Entrada", G100, -G100) -> 4632.89
...

Sheet Detalhado
A1: Visão geral
A3: Entradas | B3: =SUMIF(Lançamentos!C:C,"Entrada",Lançamentos!G:G) -> 76707
A4: Saídas | B4: =SUMIF(Lançamentos!C:C,"Saída",Lançamentos!G:G) -> 61836.2
A5: Saldo | B5: =B3-B4 -> 14870.8
A7: Mês | B7: Entradas no mês | C7: Saídas no mês | D7: Saldo no mês | E7: NOVEMBRO
A8: 2025-11 | B8: 133749.59 | C8: 99338.32 | D8: 34411.27
A9: Vendas | B9: 128337.2
A10: Vendas - IFood | B10: 5470.79
A11: Salario | C11: 20849.99
A12: Custo FIxo | C12: 10960.75
A13: Impostos | C13: 13106.57
A14: Materia Prima | C14: 32119.4
A15: Frete | C15: 736.52
A16: Cartão de Crédito | C16: 4478.19
A17: Mat Consumo | C17: 4744.17
A18: iFood - Moto | C18: 880
A19: Contabilidade | C19: 730
A20: Demissão | C20: 3260.25
A21: Royalt | C21: 7726.31
A22: Papelaria | C22: 3.5
... A24: Marketing | C24: 2000
A25: TOTAL | B25: 133807.99 | C25: 102839.15
A27: Mês | B27: Entradas no mês | C27: Saídas no mês | D27: Saldo no mês | E27: DEZEMBRO
A28: 2025-12 | B28: 178658.54 | C28: 118968.96 | D28: 59689.58
A29: Vendas | B29: 150151.29
A30: Vendas - IFood | B30: 4338.8
A31: Salario | C31: 26328.02
A32: Custo FIxo | C32: 15407.56
A33: Impostos | C33: 14160.93
A34: Materia Prima | C34: 47686.14
A35: Frete | C35: 0
A36: Cartão de Crédito | C36: 3898.85
A37: Mat Consumo | C37: 387.65
A38: iFood - Moto | C38: 724
A39: Contabilidade | C39: 1166.74
A40: Demissão | C40: 0
A41: Royalt | C41: 8013.92
A42: Papelaria | C42: 0
... A45: Marketing | C45: 2650
A46: TOTAL | B46: =SUM(B29:B45) -> 154490.09 | C46: =SUM(C29:C45) -> 134699.81
A48: Mês | B48: Entradas no mês | C48: Saídas no mês | D48: Saldo no mês | E48: JANEIRO
A49: 46023 | B49: =SUMIFS(Lançamentos!G:G,Lançamentos!C:C,"Entrada",Lançamentos!J:J,A49) -> 0 | C49: =SUMIFS(Lançamentos!G:G,Lançamentos!C:C,"Saída",Lançamentos!J:J,A49) -> 0 | D49: =B49-C49 -> 0
A50: Vendas | B50: =171115.5-5836 -> 165279.5
A51: Vendas - IFood | B51: =4818.6-387.11 -> 4431.49
A52: Salario | C52: 18632.36
A53: Custo FIxo | C53: 15132.1
A54: Impostos | C54: 19998.87
A55: Materia Prima | C55: 46256.52
A56: Frete | C56: 523.18
A57: Cartão de Crédito | C57: 5371.8
A58: Mat Consumo | C58: 5378.68
A59: iFood - Moto | C59: =785-54 -> 731
A60: Contabilidade | C60: 45
A61: Demissão | C61: 554.46
A62: Royalt | C62: 9629.05
A63: Papelaria | C63: 0
A64: Tortelli | C64: 13185
A65: Freelancer | C65: =2242-390 -> 1852
A66: Marketing | C66: 2150
A67: Celso | C67: 13554.32
A68: TOTAL | B68: =SUM(B50:B66) -> 169710.99 | C68: =SUM(C50:C67) -> 152994.34
A70: Mês | B70: Entradas no mês | C70: Saídas no mês | D70: Saldo no mês | E70: FEVEREIRO
A71: 46054 | B71: 122551.38 | C71: 102298.93 | D71: 20252.45
A72: Vendas | B72: 127109.6
A73: Vendas - IFood | B73: 5097.08
A74: Salario | C74: 15298.47
A75: Custo FIxo | C75: 13355
A76: Impostos | C76: 5859.01
A77: Materia Prima | C77: 50433.54
A78: Frete | C78: 0
A79: Cartão de Crédito | C79: 6212.37
A80: Mat Consumo | C80: 1758.4
A81: iFood - Moto | C81: 920
A82: Contabilidade | C82: 777
A83: Demissão | C83: 0
A84: Royalt | C84: 10172.6
A85: Papelaria | C85: 33
... A90: Celso | C90: 0
A91: TOTAL | B91: 132206.68 | C91: 125541.89
A93: Mês | B93: Entradas no mês | C93: Saídas no mês | D93: Saldo no mês | E93: MARÇO
A94: 46082 | B94: =SUMIFS(Lançamentos!G:G,Lançamentos!C:C,"Entrada",Lançamentos!J:J,A94) -> 0 | C94: =SUMIFS(Lançamentos!G:G,Lançamentos!C:C,"Saída",Lançamentos!J:J,A94) -> 0 | D94: =B94-C94 -> 0
A95: Vendas | B95: 108054.3
A96: Vendas - IFood | B96: 6374.1
A97: Salario | C97: 20384.82
A98: Custo FIxo | C98: 16349.61
A99: Impostos | C99: 21144.75
A100: Materia Prima | C100: 32719.78
A101: Frete | C101: 1050.89
A102: Cartão de Crédito | C102: 2862.64
A103: Mat Consumo | C103: 1399.51
A104: iFood - Moto | C104: 1026
A105: Contabilidade | C105: 972
A106: Demissão | C106: 0
A107: Royalt | C107: 7563.28
A108: Papelaria | C108: 0
... A113: Celso | C113: 0
A114: TOTAL | B114: =SUM(B95:B112) -> 114428.4 | C114: =SUM(C95:C113) -> 120942.28
A116: Mês | B116: Entradas no mês | C116: Saídas no mês | D116: Saldo no mês | E116: ABRIL
A117: 46082 | B117: 0 | C117: 0 | D117: 0
A118: Vendas | B118: 127830
...

Sheet Estoque
A1: Categoria | B1: Item | C1: Qt | E1: Categoria | F1: Item | G1: Qt | I1: Categoria | J1: Item | K1: Qt | M1: Categoria | N1: Item | O1: Qt | P1: Obs
A2: Produção | B2: Acucar mascavo | C2: 1.5
A3: Produção | B3: Açúcar invertido | C3: 3 | E3: Prod Atendimento | F3: Agua c/ gás | I3: Supermercado | J3: Açúcar confeiteiro | K3: 4 | M3: Embalagens | N3: Copo G | O3: 3 | P3: fechados
A4: Produção | B4: Amarena | C4: 0 | E4: Prod Atendimento | F4: Água sem gás | I4: Supermercado | J4: Açúcar cristal | K4: 7 | M4: Embalagens | N4: Copo G | O4: 1 | P4: em uso
A5: Produção | B5: Amêndoa | C5: 1 | E5: Prod Atendimento | F5: Café | G5: 15 | I5: Supermercado | J5: Açúcar refinado | K5: 21 | M5: Embalagens | N5: Copo M | O5: 2 | P5: fechados
A6: Produção | B6: Avelã grao | C6: 1 | E6: Prod Atendimento | F6: Canudo | G6: 1 pacote | I6: Supermercado | J6: Creme de leite caixinha | K6: 19 | M6: Embalagens | N6: Copo M | O6: 1 | P6: em uso
A7: Produção | B7: Base 6 | C7: 5 | E7: Prod Atendimento | F7: Desmoldante | G7: 2 | I7: Supermercado | J7: Leite de coco | K7: 35 | M7: Embalagens | N7: Copo P | O7: 3 | P7: fechados
A8: Produção | B8: Base fruta Milk free | C8: 3 | E8: Prod Atendimento | F8: Gás sifão | G8: 3 | I8: Supermercado | J8: Óleo | K8: 11 | M8: Embalagens | N8: Copo P | O8: 1 | P8: em uso
A9: Produção | B9: Base G creme | C9: 49 | E9: Prod Atendimento | F9: Guardanapo | G9: 4 | I9: Supermercado | J9: Sal | K9: 3 | M9: Embalagens | N9: Delivery 0,5 litro | O9: 1 | P9: caixa em uso
A10: Produção | B10: Base G fruta | C10: 26 | E10: Prod Atendimento | F10: Guardanapo | G10: 1 em uso | I10: Supermercado | J10: Farinha de trigo | K10: 1 | M10: Embalagens | N10: Delivery 0,5 litro | O10: 0 | P10: fechada
A11: Produção | B11: Bombom Mescla | C11: 0
A12: Produção | B12: Bombom Pasta | C12: 0
A13: Produção | B13: Baunilha Franch | C13: 1 | E13: Prod Atendimento | F13: Nutella | G13: 3 | M13: Embalagens | N13: Delivery 0,80 ml | O13: 1 | P13: caixa em uso
A14: Produção | B14: Brunela Caramelo | C14: 0
A15: Produção | B15: Cacau Vermelho | C15: 1
A16: Produção | B16: Blend | C16: 9 | E16: Prod Atendimento | F16: Paçoquita | G16: 1 | M16: Embalagens | N16: Delivery 1 litro | O16: 1 | P16: caixa em uso
A17: Produção | B17: Canela | C17: 1 | E17: Prod Atendimento | F17: Pazinha degustação | M17: Embalagens | N17: Delivery 1 litro | O17: 1 | P17: fechada
A18: Produção | B18: Caramelo Salgado pó | C18: 0 | E18: Prod Atendimento | F18: Pazinha degustação | M18: Embalagens | N18: Delivery 180 ml | O18: 1 | P18: caixa em uso
A19: Produção | B19: Caramelo salgado crispy | C19: 0 | E19: Prod Atendimento | F19: Pazinha gelato | M19: Embalagens | N19: Delivery 300 ml | O19: 1 | P19: caixa em uso
A20: Produção | B20: Castanha de caju | C20: 1 | E20: Prod Atendimento | F20: Pazinha gelato | M20: Embalagens | N20: Sacola maior | O20: 8
A21: Produção | B21: Choc branco | C21: 1 | E21: Prod Atendimento | F21: Creme Chantilly | M21: Embalagens | N21: Sacola menor | O21: 6
A22: Produção | B22: Choc 70% | C22: 1
A23: Produção | B23: Choc 70% Nero | C23: 1 | M23: Embalagens
A24: Produção | B24: Choc meio amargo | C24: 1
A25: Produção | B25: Creme cheesecake | C25: 0
A26: Produção | B26: Crock Dubai | C26: 0
A27: Produção | B27: Creme Noce | C27: 3
A28: Produção | B28: Coco
A29: Produção | B29: Creme pistache diamante | C29: 1
A30: Produção | B30: Doce de leite | C30: 8
A31: Produção | B31: Fecula | C31: 1.5
A32: Produção | B32: Fibra Plus | C32: 3
A33: Produção | B33: Fikissimo | C33: 0
A34: Produção | B34: Fior di Arancia | C34: 1
A35: Produção | B35: Fio di bosco | C35: 3
A36: Produção | B36: Fio di maracujá | C36: 0
A37: Produção | B37: Gianduia | C37: 2
A38: Produção | B38: Glucose | C38: 2
A39: Produção | B39: La Cubaneira | C39: 2
A40: Produção | B40: Iogumix | C40: 2
... A50: Produção | B50: Pasta Café | C50: 0
A51: Produção | B51: Pasta amendoim | C51: 3 | D51: *
A52: Produção | B52: Pasta Pipoca | C52: 1
A53: Produção | B53: Pasta avelã | C53: 1.5
A54: Produção | B54: Pasta Kitkat | C54: 2
A55: Produção | B55: Pasta fragola | C55: 0
A56: Produção | B56: Pasta pistache verde | C56: 1
A57: Produção | B57: Pistache grão | C57: 1
A58: Produção | B58: Quarquimix | C58: 1
A59: Produção | B59: Quella/Brunella | C59: 9
A60: Produção | B60: Stracciatella branca | C60: 2
A61: Produção | B61: Stracciatella latissimo | C61: 1
A62: Produção | B62: Sonho de Valsa | C62: 1
A63: Produção | B63: Stracciatella Meio amargo | C63: 2
A64: Produção | B64: Trufa branca | C64: 4

Sheet Cartão Crédito
A1: Cartão Crédito
A3: Data | B3: Valor | C3: Descrição | E3: Total Nov
A4: 46024 | B4: 33.23 | C4: Gancho para corda | E4: =SUM(B4:B61) -> 6889.94
A5: 46025 | B5: 73.69 | C5: Abc (acucar fino + oleo)
A6: 46024 | B6: 114.12 | C6: Abc (saco de lixo)
A7: 46028 | B7: 16 | C7: Pilha
A8: 46028 | B8: 2.9 | C8: Papelaria- Clipe
A9: 46028 | B9: 39.54 | C9: Bodevan
A10: 46028 | B10: 131.13 | C10: Abc
A11: 46028 | B11: 319.54 | C11: Shop ( delivery e tapetinho)
A12: 45664 | B12: 103.15 | C12: Abc
A13: 46030 | B13: 243.48 | C13: Abc
A14: 46357 | B14: 99.27 | C14: Abc
A15: 46034 | B15: 99.34 | C15: Abc
A16: 46035 | B16: 330.64 | C16: Abc
... A30: 46050 | B30: 120.41 | C30: Abc
A32: 46052 | B32: 48.76 | C32: Copinhos na shop | D32: Cartão novo nubank.
A33: 46052 | B33: 91.53 | C33: Abc
A34: 46055 | B34: 328.49 | C34: Abc
A35: 46058 | C35: Tiarinhas carnaval
A36: 46058 | B36: 90.65 | C36: Copinhos shop
A37: 46058 | B37: 12.98 | C37: Bandaid
A38: 46059 | B38: 184.42 | C38: Caixas p bolachinhas e cascões
A39: 46062 | B39: 76.5 | C39: Lâmpadas varal deck
A40: 46063 | B40: 229.81 | C40: Abc
A41: 46064 | B41: 54.9 | C41: Pinga Doces Da Vovo
A42: 46064 | B42: 47 | C42: Amendoim
A43: 46065 | B43: 30 | C43: Trem pro carnaval
A44: 46065 | B44: 58.6 | C44: Ferramenta p cascata
A45: 46065 | B45: 44 | C45: Enfeite carnaval
A46: 46069 | B46: 285.75 | C46: Bodevan (papel toalha e higienico)
A47: 46069 | C47: Amendoim
A48: 46069 | B48: 171.16 | C48: Leite
A49: 46073 | B49: 45.9 | C49: Caixinha funcionários
A50: 46073 | B50: 60.23 | C50: Pote delivery shop
A51: 46074 | B51: 29.9 | C51: Abc, desintupidor
A52: 46075 | B52: 219.45 | C52: abc, compras
A53: 46076 | B53: 329.42 | C53: Fonte led
A54: 46076 | B54: 166.5 | C54: Papelaria
A55: 46079 | B55: 201.84 | C55: Abc
A56: 46079 | B56: 81.86 | C56: Tapete pra Cuba
A57: 46086 | B57: 115.03 | C57: Abc
A58: 46086 | B58: 41.76 | C58: Shop, copinho 2 sabores delivery
A59: 46090 | B59: 138.25 | C59: Abc
... A68: 46101 | B68: 75.86 | C68: abc
A69: 46105 | C69: coelhinhos decor | D69: 2x
A70: 46107 | B70: 68.37 | C70: carrosel cafe
A71: 46108 | C71: Pão de queijo café reunião
A72: 46109 | C72: Papelaria quadrinhos
A73: 46111 | B73: 145.56 | C73: Carrossel
A74: 46111 | B74: 134.3 | C74: Abc
A75: 46111 | B75: 125.15 | C75: Abc
A76: 46118 | B76: 126.72 | C76: Máquina de lavar shop
A77: 46119 | B77: 172.75 | C77: papelaria
A78: 46121 | B78: 50 | C78: mel
A79: 46121 | B79: 31.96 | C79: bolacha
A80: 46121 | B80: 7.02 | C80: bolacha
A81: 46125 | B81: 126.99 | C81: Copinhos 80 ml shop
A82: 46125 | B82: 419.74 | C82: Abc
A83: 46127 | C83: granulado
A84: 46128 | B84: 49.96 | C84: Manteiga abc
A85: 46133 | B85: 293.4 | C85: Leite
A86: 46134 | B86: 345.19 | C86: Abc
A87: 46135 | B87: 55.8 | C87: Luva Cascao
A88: 46135 | B88: 17 | C88: lavadora
A89: 46140 | B89: 20 | C89: Pote para Pacoquita
A90: 46140 | B90: 17.5 | C90: Paçoca carrossel
A91: 46142 | B91: 55 | C91: Paçoca e suspiro
B92: MAIO | C92: 2026
A93: 46146 | B93: 96.9 | C93: Bobina Fiscal Mercado Livre
A94: 46146 | B94: 253.4 | C94: Abc - IFOOD
A95: 46147 | B95: 338.75 | C95: Bodevan
A96: 46147 | B96: 49.86 | C96: farmacia (luva + bandaid)
A97: 46148 | B97: 24 | C97: copia chave
A98: 46150 | C98: padaria san remo
A99: 46154 | B99: 260.78 | C99: ABC - IFOOD
A100: 46155 | B100: 51.96 | C100: biscoito para tiramisu
A101: 46161 | B101: 83 | C101: balanca, garrafa de cafe e leiteira
A102: 46162 | B102: 249.95 | C102: ABC - IFOOD
A103: 46168 | B103: 17.5 | C103: Fita dupla face
A104: 46172 | B104: 50 | C104: Porta detergente
C105: cupom ifood
A106: 46175 | B106: 10.35 | C106: Bodevan
A107: 46176 | B107: 187.34 | C107: Abc
A108: 46176 | B108: 2 | C108: Geleia Me Lambuzei
A109: 46178 | B109: 25 | C109: Pé de moleque
A110: 46181 | B110: 88 | C110: doce de abobora
A111: 46181 | B111: 10.36 | C111: Detergente
A112: 46181 | B112: 13.8 | C112: Bodevan coleirinhas
A113: 46182 | B113: 179.73 | C113: Abc
A114: 46183 | B114: 25.9 | C114: abc detergente
A115: 46184 | B115: 13 | C115: cola no chines | D115: As coisas do croiassant, 53,50
A116: 46188 | B116: 122.78 | C116: abc
A117: 46198 | C117: carrossel
A118: 46198 | B118: 30.66 | C118: abc
A119: 46198 | B119: 274.66 | C119: mercado livre, nibs de cacau
A120: 46199 | B120: 103.3 | C120: Abc
A121: 46202 | B121: 62.9 | C121: Pote 80ml shopp
A122: 46203 | B122: 99.26 | C122: Bodevan
A123: 46204 | B123: 215.11 | C123: Abc | D123: JULHO
...

Sheet Boletos Futuros
B1: Março | F1: Abril | J1: Maio | N1: Junho | R1: Julho | V1: Agosto | Z1: Setembro | AD1: Outubro | AH1: Novembro | AL1: Dezembro | AP1: Janeiro_2027
B2: Data | C2: Descrição | D2: Valor | F2: Data | G2: Descrição | H2: Valor | J2: Data | K2: Descrição | L2: Valor | N2: Data | O2: Descrição | P2: Valor | R2: Data | S2: Descrição | T2: Valor | V2: Data | W2: Descrição | X2: Valor | Z2: Data | AA2: Descrição | AB2: Valor | AD2: Data | AE2: Descrição | AF2: Valor | AH2: Data | AI2: Descrição | AJ2: Valor | AL2: Data | AM2: Descrição | AN2: Valor | AP2: Data | AQ2: Descrição | AR2: Valor
B3: 5 | C3: Alarme | D3: 100 | F3: 2 | G3: Diniz | H3: 484.05 | J3: 5 | K3: Riber | L3: 1029.4 | N3: 2 | O3: Riber | P3: 477.68 | R3: 6 | S3: Polar | T3: 177.86 | V3: 4 | W3: Mec 3 | X3: 1561.18 | Z3: 30 | AA3: Tortelli | AB3: 13185 | AD3: 31 | AE3: Tortelli | AF3: 13185 | AH3: 30 | AI3: Tortelli | AJ3: 8185
B4: 9 | C4: Mec 3 | D4: 1736.83 | F4: 7 | G4: Guardanapos | H4: 537 | J4: 5 | K4: Riber | L4: 156.7 | N4: 2 | O4: Diniz | P4: 182.54 | R4: 6 | S4: Polar | T4: 321.07 | V4: 18 | W4: Mec 3 | X4: 1561.64
B5: 10 | C5: Diniz | D5: 400.39 | F5: 7 | G5: Riber | H5: 1074 | J5: 5 | K5: Riber | L5: 564.36 | N5: 3 | O5: Ecila | P5: 115.8 | R5: 1 | S5: Ecila | T5: 115.8 | V5: 3 | W5: Polar | X5: 211.23
B6: 10 | C6: Diniz | D6: 400.39 | F6: 7 | G6: Riber | H6: 1708.78 | J6: 7 | K6: Diniz | L6: 600.69 | N6: 6 | O6: Guardanapos | P6: 571.9 | R6: 14 | S6: Diniz | T6: 217.35 | V6: 31 | W6: Tortelli | X6: 13185
B7: 10 | C7: Frete mec 3 | D7: 432.89 | F7: 7 | G7: Diniz | H7: 399.72 | J7: 11 | K7: Unigra | L7: 1022.53 | N7: 8 | O7: MEC 3 | P7: 1486.49 | R7: 14 | S7: Diniz | T7: 379.7 | V7: 4 | W7: Diniz | X7: 831.47
B8: 15 | C8: Boleto odontológico | D8: 202.8 | F8: 8 | G8: Ecila | H8: 755 | J8: 11 | K8: MEC 3 | L8: 1734.28 | N8: 8 | O8: Polar | P8: 772.73 | R8: 7 | S8: Riber | T8: 529.5
B9: 17 | C9: Unigra | D9: 883.32 | F9: 11 | G9: Unigra | H9: 1022.5 | J9: 11 | K9: Polar | L9: 211.23 | N9: 8 | O9: Polar | P9: 444.67 | R9: 21 | S9: Mec 3 | T9: 1561.18
B10: 17 | C10: Riber | D10: 2521.74 | F10: 13 | G10: Castanha | H10: 850.5 | J10: 11 | K10: Polar | L10: 66.73 | N10: 9 | O10: Diniz | P10: 182.55 | R10: 14 | S10: Riber | T10: 852.89
B11: 18 | C11: Ecila | D11: 650 | F11: 13 | G11: Unigra | H11: 5052.07 | J11: 12 | K11: Riber | L11: 156.7 | N11: 9 | O11: Riber | P11: 578 | R11: 22 | S11: Ecila | T11: 738.6
B12: 18 | C12: Morango | D12: 278 | F12: 14 | G12: Riber | H12: 1708.19 | J12: 12 | K12: Riber | L12: 564.37 | N12: 9 | O12: Riber | P12: 1084.28 | R12: 25 | S12: Ecad | T12: 112.62
B13: 20 | C13: ICMS | D13: 1769.9 | F13: 15 | G13: Diniz | H13: 255.67 | J13: 12 | K13: Diniz | L13: 1977.87 | N13: 10 | O13: 1/3 unigra | P13: 1085.93 | R13: 22 | S13: Diniz | T13: 904.82
B14: 21 | C14: Pregel | D14: 329.39 | F14: 20 | G14: Pregel | H14: 329.39 | J14: 14 | K14: Andaluz | L14: 1132.95 | N14: 15 | O14: Diniz | P14: 231.55 | R14: 31 | S14: Tortelli | T14: 13185
B15: 20 | C15: DARF | D15: 724.51 | F15: 20 | G15: Riber | H15: 278.93 | J15: 14 | K15: Frutas | L15: 254.8 | N15: 16 | O15: Riber | P15: 578 | R15: 21 | S15: Riber | T15: 486.52
B16: 23 | C16: Mec 3 | D16: 1737.35 | F16: 21 | G16: Riber | H16: 1708.19 | J16: 14 | K16: Diniz(Thales) | L16: 697.1 | N16: 16 | O16: Riber | P16: 1084.28
B17: 25 | C17: Mec 3 | D17: 1139.44 | F17: 25 | G17: Polar | H17: 422.46 | J17: 18 | K17: Riber | L17: 1812.07 | N17: 16 | O17: Polar | P17: 136.51
F18: 25 | G18: Polar | H18: 1545.5 | J18: 20 | K18: Ecila (+ Thales) | L18: 115.8 | N18: 20 | O18: Guardanapos | P18: 537
B19: 30 | C19: Sistema | D19: 370 | F19: 27 | G19: Riber | H19: 278.93 | J19: 21 | K19: Diniz(Thales) | L19: 697.1 | N19: 22 | O19: MEC 3 | P19: 1486.94
B20: 30 | C20: Tráfego pago | D20: 600 | F20: 27 | G20: MEC 3 | H20: 1734.28 | J20: 25 | K20: MEC 3 | L20: 1734.8 | N20: 22 | O20: Riber | P20: 428.45
B21: 30 | C21: Polar | D21: 211.23 | F21: 28 | G21: Riber | H21: 1029.4 | J21: 25 | K21: Riber | L21: 1812.08 | N21: 23 | O21: Polar | P21: 136.51
B22: 30 | C22: Polar | D22: 416.99 | F22: 28 | G22: Diniz | H22: 326.1 | J22: 25 | K22: Polar | L22: 134.99 | N22: 29 | O22: Unigra | P22: 4817.19
B23: 31 | C23: Riber | D23: 308.15 | F23: 29 | G23: Ecila | H23: 1370 | J23: 25 | K23: Polar | L23: 222.34 | N23: 29 | O23: Riber | P23: 428.45
B24: 31 | C24: Riber | D24: 2664 | F24: 30 | G24: ICMS | H24: 389.48 | J24: 25 | K24: MEC 3 | L24: 1486.49 | N24: 29 | O24: Andaluz | P24: 1443.71
B25: 20 | C25: FGTS | D25: 767.67 | F25: 30 | G25: Unigra | H25: 4817.04 | J25: 26 | K25: Riber | L25: 477.68 | N25: 30 | O25: Polar | P25: 136.51
B26: 20 | C26: Simples | D26: 7323.66 | J26: 26 | K26: Diniz | L26: 182.54 | N26: 30 | O26: Diniz | P26: 225.27
J27: 27 | K27: Ecila | L27: 1400
J28: 28 | K28: Diniz(Thales) | L28: 697.1
J29: 30 | K29: Unigra | L29: 4817.04
B50: TOTAL | D50: =SUM(D3:D49) -> 25968.65 | F50: TOTAL | H50: =SUM(H3:H49) -> 28077.18 | J50: TOTAL | L50: =SUM(L3:L49) -> 25759.74 | N50: TOTAL | P50: =SUM(P3:P49) -> 18652.94 | R50: TOTAL | T50: =SUM(T3:T49) -> 19582.91 | V50: TOTAL | X50: =SUM(X3:X49) -> 17350.52 | Z50: TOTAL | AB50: =SUM(AB3:AB49) -> 13185 | AD50: TOTAL | AF50: =SUM(AF3:AF49) -> 13185 | AH50: TOTAL | AJ50: =SUM(AJ3:AJ49) -> 8185 | AL50: TOTAL | AN50: =SUM(AN3:AN49) -> 0 | AP50: TOTAL | AR50: =SUM(AR3:AR49) -> 0

Sheet NOV_25
K1: 0
A2: 45962 | B2: Venda de produto | C2: Entrada | D2: Vendas | E2: Banco Principal | G2: 7834 | J2: 2025-11 | K2: 7834
A3: 45962 | B3: IFood | C3: Entrada | D3: Vendas iFood | E3: Banco Principal | G3: 370 | J3: 2025-11 | K3: 8204
A4: 45962 | B4: Motoboy | C4: Saída | D4: iFood | E4: Banco Principal | F4: Pix | G4: 53 | J4: 2025-11 | K4: 8151
A5: 45963 | B5: Venda de produto | C5: Entrada | D5: Vendas | E5: Banco Principal | G5: 3000 | J5: 2025-11 | K5: 11151
A6: 45963 | B6: IFood | C6: Entrada | D6: Vendas iFood | E6: Banco Principal | G6: 441 | J6: 2025-11 | K6: 11592
A7: 45963 | B7: Motoboy | C7: Saída | D7: iFood | E7: Banco Principal | F7: Pix | G7: 54 | J7: 2025-11 | K7: 11538
A8: 45963 | B8: Boleto Unigra | C8: Saída | D8: Matéria Prima | E8: Banco Principal | G8: 772.79 | J8: 2025-11 | K8: 10765.21
A9: 45964 | B9: Luz e água mês 10 | C9: Saída | D9: CustoFixo | E9: Caixa | F9: Dinheiro | G9: 1670 | I9: Inteirar luz e água mês 10 | J9: 2025-11 | K9: 9095.21
A10: 45964 | B10: Venda de produtos | C10: Entrada | D10: Vendas | E10: Banco Principal | G10: 1708 | J10: 2025-11 | K10: 10803.21
A11: 45965 | B11: Boleto | C11: Saída | D11: Matéria Prima | E11: Banco Principal | G11: 953.18 | J11: 2025-11 | K11: 9850.03
A12: 45965 | B12: Boleto | C12: Saída | D12: Matéria Prima | E12: Banco Principal | G12: 22.12 | J12: 2025-11 | K12: 9827.91
A13: 45965 | B13: Boleto | C13: Saída | D13: Matéria Prima | E13: Banco Principal | G13: 1445.77 | J13: 2025-11 | K13: 8382.14
A14: 45965 | B14: Vale alimentação | C14: Saída | D14: Salário | E14: Banco Principal | G14: 400 | J14: 2025-11 | K14: 7982.14
A15: 45965 | B15: Impressão PAPELARIA | C15: Saída | D15: Papelaria | E15: Banco Principal | F15: Pix | G15: 3.5 | I15: Impressão Holerite | J15: 2025-11 | K15: 7978.64
A16: 45965 | B16: Leite | C16: Saída | D16: Matéria Prima | E16: Caixa | F16: Dinheiro | G16: 94 | J16: 2025-11 | K16: 7884.64
A17: 45965 | B17: Motoboy | C17: Saída | D17: iFood | E17: Banco Principal | F17: Pix | G17: 9 | J17: 2025-11 | K17: 7875.64
A18: 45965 | B18: Vendas | C18: Entrada | D18: Vendas | E18: Banco Principal | G18: 1499 | J18: 2025-11 | K18: 9374.64
A19: 45965 | B19: IFood | C19: Entrada | D19: Vendas iFood | E19: Banco Principal | G19: 78 | J19: 2025-11 | K19: 9452.64
A20: 45966 | B20: Boleto alarme | C20: Saída | D20: CustoFixo | E20: Banco Principal | G20: 100 | J20: 2025-11 | K20: 9352.64
A21: 45966 | B21: Aluguel | C21: Saída | D21: CustoFixo | E21: Banco Principal | G21: 9000 | J21: 2025-11 | K21: 352.64
A22: 45966 | B22: IPTU | C22: Saída | D22: CustoFixo | E22: Banco Principal | G22: 90.85 | J22: 2025-11 | K22: 261.79
A23: 45966 | B23: Boleto fruta congelada | C23: Saída | D23: Matéria Prima | E23: Banco Principal | G23: 278 | J23: 2025-11 | K23: -16.21
A24: 45966 | B24: Exame demissional | C24: Saída | D24: Contabilidade | E24: Banco Principal | F24: Pix | G24: 45 | I24: Exame demissional Adriana | J24: 2025-11 | K24: -61.21
A25: 45966 | B25: Leite | C25: Saída | D25: Matéria Prima | E25: Caixa | F25: Dinheiro | G25: 94 | J25: 2025-11 | K25: -155.21
A26: 45966 | B26: Carrão de crédito | C26: Saída | D26: Cartao de Credito | E26: Banco Principal | G26: 4478.19 | I26: Tudo que compro no crédito | J26: 2025-11 | K26: -4633.4
A27: 45966 | B27: Tráfego pago | C27: Saída | D27: Marketing | E27: Banco Principal | G27: 2000 | I27: Estava no cartão de crédito | J27: 2025-11 | K27: -6633.4
A28: 45966 | B28: Motoboy | C28: Saída | D28: iFood | E28: Banco Principal | F28: Pix | G28: 27 | J28: 2025-11 | K28: -6660.4
A29: 45966 | B29: Vendas do dia | C29: Entrada | D29: Vendas | G29: 1225 | J29: 2025-11 | K29: -5435.4
A30: 45966 | B30: IFood vendas | C30: Entrada | D30: Vendas iFood | E30: Banco Principal | G30: 185.2 | J30: 2025-11 | K30: -5250.2
A31: 45967 | B31: Leite | C31: Saída | D31: Matéria Prima | E31: Caixa | F31: Dinheiro | G31: 235 | J31: 2025-11 | K31: -5485.2
A32: 45967 | B32: Cubas | C32: Saída | D32: Salário | E32: Caixa | F32: Dinheiro | G32: 190 | I32: Paguei a Cubas | J32: 2025-11 | K32: -5675.2
A33: 45967 | B33: Vendas do dia | C33: Entrada | D33: Vendas | G33: 2605 | J33: 2025-11 | K33: -3070.2
A34: 45967 | B34: IFood vendas | C34: Entrada | D34: Vendas iFood | E34: Banco Principal | G34: 58.4 | J34: 2025-11 | K34: -3011.8
A35: 45967 | B35: Motoboy | C35: Saída | D35: iFood | E35: Banco Principal | F35: Pix | G35: 9 | J35: 2025-11 | K35: -3020.8
A36: 45968 | B36: Salários | C36: Saída | D36: Salário | E36: Banco Principal | F36: Pix | G36: 9642.93 | J36: 2025-11 | K36: -12663.73
A37: 45968 | B37: Leite | C37: Saída | D37: Matéria Prima | E37: Caixa | F37: Dinheiro | G37: 376 | J37: 2025-11 | K37: -13039.73
A38: 45968 | B38: Motoboy | C38: Saída | D38: iFood | E38: Banco Principal | F38: Pix | G38: 35 | J38: 2025-11 | K38: -13074.73
A39: 45968 | B39: Vendas do dia | C39: Entrada | D39: Vendas | G39: 3432.3 | J39: 2025-11 | K39: -9642.43
A40: 45968 | B40: Vendas iFood | C40: Entrada | D40: Vendas iFood | E40: Banco Principal | G40: 302.5 | J40: 2025-11 | K40: -9339.93
A41: 45969 | B41: freelancer | C41: Saída | D41: Freelancer | E41: Caixa | F41: Dinheiro | G41: 120 | J41: 2025-11 | K41: -9459.93
A42: 45969 | B42: Motoboy | C42: Saída | D42: iFood | E42: Banco Principal | F42: Pix | G42: 26 | J42: 2025-11 | K42: -9485.93
A43: 45969 | B43: Vendas do dia | C43: Entrada | D43: Vendas | G43: 4737.2 | J43: 2025-11 | K43: -4748.73
A44: 45969 | B44: IFood vendas | C44: Entrada | D44: Vendas iFood | E44: Banco Principal | G44: 346.5 | J44: 2025-11 | K44: -4402.23
A45: 45970 | B45: Motoboy | C45: Saída | D45: iFood | E45: Banco Principal | F45: Pix | G45: 69 | J45: 2025-11 | K45: -4471.23
A46: 45970 | B46: Vendas do dia | C46: Entrada | D46: Vendas | G46: 9025 | J46: 2025-11 | K46: 4553.77
A47: 45970 | B47: Vendas iFood | C47: Entrada | D47: Vendas iFood | E47: Banco Principal | G47: 352.9 | J47: 2025-11 | K47: 4906.67
A48: 45970 | B48: Freelance | C48: Saída | D48: Freelancer | E48: Caixa | F48: Dinheiro | G48: 120 | J48: 2025-11 | K48: 4786.67
A49: 45971 | B49: Royalt + marketing | C49: Saída | D49: Royalt | E49: Banco Principal | F49: Pix | G49: 7726.31 | J49: 2025-11 | K49: -2939.64
A50: 45971 | B50: Moça Faxina | C50: Saída | D50: Salário | E50: Banco Principal | F50: Pix | G50: 900 | J50: 2025-11 | K50: -3839.64
A51: 45971 | B51: Salário Tais | C51: Saída | D51: Salário | E51: Banco Principal | F51: Pix | G51: 3500 | I51: Ainda falta 1.5000 | J51: 2025-11 | K51: -7339.64
A52: 45971 | B52: Contabilidade | C52: Saída | D52: Contabilidade | E52: Banco Principal | G52: 685 | J52: 2025-11 | K52: -8024.64
A53: 45971 | B53: Boleto Polar | C53: Saída | D53: Matéria Prima | E53: Banco Principal | G53: 400.22 | J53: 2025-11 | K53: -8424.86
A54: 45971 | B54: Boleto Polar | C54: Saída | D54: Matéria Prima | E54: Banco Principal | G54: 444.67 | J54: 2025-11 | K54: -8869.53
A55: 45971 | B55: Plano saúde boleto | C55: Saída | D55: Salário | E55: Banco Principal | G55: 60 | J55: 2025-11 | K55: -8929.53
A56: 45971 | B56: Leite | C56: Saída | D56: Matéria Prima | E56: Caixa | F56: Dinheiro | G56: 0 | J56: 2025-11 | K56: -8929.53
A57: 45971 | B57: Vendas do dia | C57: Entrada | D57: Vendas | G57: 1745 | J57: 2025-11 | K57: -7184.53
A58: 45971 | B58: Vendas iFood | C58: Entrada | D58: Vendas iFood | E58: Banco Principal | G58: 97.4 | J58: 2025-11 | K58: -7087.13
A59: 45971 | B59: Motoboy | C59: Saída | D59: iFood | E59: Banco Principal | F59: Pix | G59: 17 | J59: 2025-11 | K59: -7104.13
A60: 45972 | B60: leite | C60: Saída | D60: Matéria Prima | E60: Caixa | F60: Dinheiro | G60: 300 | J60: 2025-11 | K60: -7404.13
A61: 45972 | B61: Leite | C61: Saída | D61: Matéria Prima | E61: Caixa | F61: Dinheiro | G61: 47 | J61: 2025-11 | K61: -7451.13
A62: 45972 | B62: Vendas do dia | C62: Entrada | D62: Vendas | G62: 1866 | J62: 2025-11 | K62: -5585.13
A63: 45972 | B63: Vendas iFood | C63: Entrada | D63: Vendas iFood | E63: Banco Principal | G63: 78 | J63: 2025-11 | K63: -5507.13
A64: 45972 | B64: Boleto Unigra | C64: Saída | D64: Matéria Prima | E64: Banco Principal | G64: 3280.83 | J64: 2025-11 | K64: -8787.96
A65: 45972 | B65: Motoboy | C65: Saída | D65: iFood | E65: Banco Principal | F65: Pix | G65: 9 | J65: 2025-11 | K65: -8796.96
A66: 45973 | B66: leite | C66: Saída | D66: Matéria Prima | E66: Caixa | F66: Dinheiro | G66: 300 | J66: 2025-11 | K66: -9096.96
A67: 45973 | B67: Vendas do dia | C67: Entrada | D67: Vendas | G67: 2167.5 | J67: 2025-11 | K67: -6929.46
A68: 45973 | B68: Vendas iFood | C68: Entrada | D68: Vendas iFood | E68: Banco Principal | G68: 0 | J68: 2025-11 | K68: -6929.46
A69: 45973 | B69: Leite | C69: Saída | D69: Matéria Prima | E69: Caixa | F69: Dinheiro | G69: 135 | J69: 2025-11 | K69: -7064.46
A70: 45973 | B70: Motoboy | C70: Saída | D70: iFood | E70: Banco Principal | F70: Pix | G70: 0 | J70: 2025-11 | K70: -7064.46
A71: 45973 | B71: Boleto Unigra | C71: Saída | D71: Matéria Prima | E71: Banco Principal | G71: 518.42 | J71: 2025-11 | K71: -7582.88
A72: 45973 | B72: Boleto Ecila | C72: Saída | D72: Matéria Prima | E72: Banco Principal | G72: 77.98 | J72: 2025-11 | K72: -7660.86
A73: 45973 | B73: Boleto Mec 3 | C73: Saída | D73: Matéria Prima | E73: Banco Principal | G73: 1019.29 | J73: 2025-11 | K73: -8680.15
A74: 45973 | B74: Boleto Riber | C74: Saída | D74: Matéria Prima | E74: Banco Principal | G74: 1450.11 | J74: 2025-11 | K74: -10130.26
A75: 45974 | B75: Boleto Andaluz | C75: Saída | D75: Matéria Prima | E75: Banco Principal | G75: 935.43 | J75: 2025-11 | K75: -11065.69
A76: 45974 | B76: Boleto Diniz | C76: Saída | D76: Matéria Prima | E76: Banco Principal | G76: 513.36 | J76: 2025-11 | K76: -11579.05
A77: 45973 | B77: Leite | C77: Saída | D77: Matéria Prima | E77: Caixa | F77: Dinheiro | G77: 235 | J77: 2025-11 | K77: -11814.05
A78: 45974 | B78: Vendas do dia | C78: Entrada | D78: Vendas | G78: 2643 | J78: 2025-11 | K78: -9171.05
A79: 45974 | B79: Vendas IFood | C79: Entrada | D79: Vendas iFood | E79: Banco Principal | G79: 214.4 | J79: 2025-11 | K79: -8956.65
A80: 45974 | B80: Motoboy | C80: Saída | D80: iFood | E80: Banco Principal | F80: Pix | G80: 27 | J80: 2025-11 | K80: -8983.65
A81: 45975 | B81: Boleto Unigra | C81: Saída | D81: Matéria Prima | E81: Banco Principal | G81: 237.61 | J81: 2025-11 | K81: -9221.26
A82: 45975 | B82: Boleto Unigra | C82: Saída | D82: Matéria Prima | E82: Banco Principal | G82: 514.82 | J82: 2025-11 | K82: -9736.08
A83: 45975 | B83: FGTS | C83: Saída | D83: Impostos | E83: Banco Principal | G83: 842.05 | J83: 2025-11 | K83: -10578.13
A84: 45975 | B84: Leite | C84: Saída | D84: Matéria Prima | E84: Caixa | F84: Dinheiro | G84: 329 | J84: 2025-11 | K84: -10907.13
A85: 45975 | B85: Motoboy | C85: Saída | D85: iFood | E85: Banco Principal | F85: Pix | G85: 27 | J85: 2025-11 | K85: -10934.13
A86: 45975 | B86: Vendas do dia | C86: Entrada | D86: Vendas | G86: 3044 | J86: 2025-11 | K86: -7890.13
A87: 45975 | B87: Venda iFood | C87: Entrada | D87: Vendas iFood | E87: Banco Principal | G87: 146.2 | J87: 2025-11 | K87: -7743.93
A88: 45975 | B88: Maracujá | C88: Saída | D88: Matéria Prima | E88: Banco Principal | F88: Pix | G88: 224 | J88: 2025-11 | K88: -7967.93
A89: 45976 | B89: Canequinha para pazinhas | C89: Saída | D89: Mat Consumo | E89: Caixa | F89: Dinheiro | G89: 5 | J89: 2025-11 | K89: -7972.93
A90: 45976 | B90: Motoboy | C90: Saída | D90: iFood | E90: Banco Principal | F90: Pix | G90: 44 | J90: 2025-11 | K90: -8016.93
A91: 45976 | B91: Vendas do dia | C91: Entrada | D91: Vendas | G91: 8091 | J91: 2025-11 | K91: 74.07
A92: 45976 | B92: Vendas iFood | C92: Entrada | D92: Vendas | E92: Banco Principal | G92: 274.3 | J92: 2025-11 | K92: 348.37
A93: 45976 | B93: Freelancer | C93: Saída | D93: Freelancer | E93: Caixa | F93: Dinheiro | G93: 120 | J93: 2025-11 | K93: 228.37
A94: 45977 | B94: freelancer | C94: Saída | D94: Freelancer | E94: Caixa | F94: Dinheiro | G94: 120 | J94: 2025-11 | K94: 108.37
A95: 45977 | B95: motoboy | C95: Saída | D95: iFood | E95: Banco Principal | F95: Pix | G95: 97 | J95: 2025-11 | K95: 11.37
A96: 45977 | B96: vendas | C96: Entrada | D96: Vendas | G96: 5696 | J96: 2025-11 | K96: 5707.37
A97: 45977 | B97: vendasifood | C97: Entrada | D97: Vendas iFood | E97: Banco Principal | G97: 528.8 | J97: 2025-11 | K97: 6236.17
A98: 45977 | B98: Praline | C98: Saída | D98: Matéria Prima | E98: Banco Principal | F98: Pix | G98: 305.6 | J98: 2025-11 | K98: 5930.57
A99: 45978 | B99: Restante salário Tais | C99: Saída | D99: Salário | E99: Banco Principal | F99: Pix | G99: 1500 | J99: 2025-11 | K99: 4430.57
A100: 45978 | B100: Copinhos | C100: Saída | D100: Mat Consumo | E100: Banco Principal | F100: Pix | G100: 2254 | J100: 2025-11 | K100: 2176.57
...

Sheet DEZ_25
A2: 45992 | B2: Caixa_Novembro_25 | C2: Entrada | D2: Caixa_mes_anterior | G2: 30968.84 | I2: Caixa_mes_anterior | J2: 2025-12 | K2: 30968.84
A3: 45992 | B3: Vale alimentação | C3: Saída | D3: Salário | E3: Banco Principal | G3: 2400 | J3: 2025-12 | K3: 28568.84
A4: 45992 | B4: Boleto sistema | C4: Saída | D4: CustoFixo | E4: Banco Principal | G4: 370 | J4: 2025-12 | K4: 28198.84
A5: 45992 | B5: Leite | C5: Saída | D5: Matéria Prima | E5: Caixa | F5: Dinheiro | G5: 235 | J5: 2025-12 | K5: 27963.84
A6: 45992 | B6: Peça da máquina produtora | C6: Saída | D6: Mat Consumo | E6: Banco Principal | F6: Pix | G6: 160 | J6: 2025-12 | K6: 27803.84
A7: 45992 | B7: Água | C7: Saída | D7: Matéria Prima | E7: Banco Principal | F7: Pix | G7: 203.5 | J7: 2025-12 | K7: 27600.34
A8: 45992 | B8: Tráfego Pago | C8: Saída | D8: Marketing | E8: Banco Principal | F8: Pix | G8: 600 | J8: 2025-12 | K8: 27000.34
A9: 45992 | B9: Tortelli | C9: Saída | D9: Tortelli | E9: Banco Principal | G9: 13185 | J9: 2025-12 | K9: 13815.34
A10: 45992 | B10: Vendas do dia | C10: Entrada | D10: Vendas | G10: 1824 | J10: 2025-12 | K10: 15639.34
A11: 45992 | B11: Motoboy | C11: Saída | D11: iFood | E11: Banco Principal | F11: Pix | G11: 19 | J11: 2025-12 | K11: 15620.34
A12: 45993 | B12: Boleto Ecila | C12: Saída | D12: Matéria Prima | E12: Banco Principal | G12: 767.37 | J12: 2025-12 | K12: 14852.97
A13: 45993 | B13: Boleto Mec 3 | C13: Saída | D13: Matéria Prima | E13: Banco Principal | G13: 1341.23 | J13: 2025-12 | K13: 13511.74
A14: 45993 | B14: Creme de Leite | C14: Saída | D14: Matéria Prima | E14: Banco Principal | F14: Pix | G14: 698 | J14: 2025-12 | K14: 12813.74
A15: 45993 | B15: Boleto Riber | C15: Saída | D15: Matéria Prima | E15: Banco Principal | G15: 399.94 | J15: 2025-12 | K15: 12413.8
A16: 45993 | B16: Supermercado | C16: Saída | D16: Matéria Prima | E16: Banco Principal | F16: Pix | G16: 100 | J16: 2025-12 | K16: 12313.8
A17: 45993 | B17: Vendas do dia | C17: Entrada | D17: Vendas | G17: 952 | J17: 2025-12 | K17: 13265.8
A18: 45993 | B18: Vendas iFood | C18: Entrada | D18: Vendas iFood | E18: Banco Principal | G18: 200.39 | J18: 2025-12 | K18: 13466.19
A19: 45993 | B19: Motoboy | C19: Saída | D19: iFood | E19: Banco Principal | F19: Pix | G19: 25 | J19: 2025-12 | K19: 13441.19
A20: 45994 | B20: Leite | C20: Saída | D20: Matéria Prima | E20: Caixa | F20: Dinheiro | G20: 0 | J20: 2025-12 | K20: 13441.19
A21: 45994 | B21: Boleto Unigra | C21: Saída | D21: Matéria Prima | E21: Banco Principal | G21: 772.82 | J21: 2025-12 | K21: 12668.37
A22: 45994 | B22: Impressão holerite | C22: Saída | D22: Salário | E22: Banco Principal | F22: Pix | G22: 3 | J22: 2025-12 | K22: 12665.37
A23: 45994 | B23: Vendas do dia | C23: Entrada | D23: Vendas | G23: 1599 | J23: 2025-12 | K23: 14264.37
A24: 45994 | B24: Vendas iFood | C24: Entrada | D24: Vendas iFood | E24: Banco Principal | G24: 117 | J24: 2025-12 | K24: 14381.37
A25: 45995 | B25: Boleto Mec 3 | C25: Saída | D25: Matéria Prima | E25: Banco Principal | G25: 1360.97 | J25: 2025-12 | K25: 13020.4
A26: 45995 | B26: Boleto Alarme | C26: Saída | D26: CustoFixo | E26: Banco Principal | G26: 100 | J26: 2025-12 | K26: 12920.4
A27: 45995 | B27: Leite | C27: Saída | D27: Matéria Prima | E27: Caixa | F27: Dinheiro | G27: 282 | J27: 2025-12 | K27: 12638.4
A28: 45995 | B28: Vendas do dia | C28: Entrada | D28: Vendas | G28: 1795 | J28: 2025-12 | K28: 14433.4
A29: 45995 | B29: Venda Ifood | C29: Entrada | D29: Vendas iFood | E29: Banco Principal | G29: 0 | J29: 2025-12 | K29: 14433.4
A30: 45996 | B30: Salario Pessoal | C30: Saída | D30: Salário | E30: Banco Principal | G30: 9432.18 | J30: 2025-12 | K30: 5001.22
A31: 45996 | B31: Aluguel | C31: Saída | D31: CustoFixo | E31: Banco Principal | G31: 9000 | J31: 2025-12 | K31: -3998.78
A32: 45996 | B32: IPTU | C32: Saída | D32: CustoFixo | E32: Banco Principal | G32: 90.85 | J32: 2025-12 | K32: -4089.63
A33: 45996 | B33: Cartão de credito | C33: Saída | D33: Cartao de Credito | E33: Banco Principal | G33: 3898.85 | J33: 2025-12 | K33: -7988.48
A34: 45996 | B34: Vendas do dia | C34: Entrada | D34: Vendas | G34: 3862 | J34: 2025-12 | K34: -4126.48
A35: 45996 | B35: Vendas iFood | C35: Entrada | D35: Vendas iFood | E35: Banco Principal | G35: 185.12 | J35: 2025-12 | K35: -3941.36
A36: 45996 | B36: Leite | C36: Saída | D36: Matéria Prima | E36: Caixa | F36: Dinheiro | G36: 376 | J36: 2025-12 | K36: -4317.36
A37: 45996 | B37: Moça Faxina | C37: Saída | D37: Salário | E37: Banco Principal | F37: Pix | G37: 824 | J37: 2025-12 | K37: -5141.36
A38: 45996 | B38: Restante cubas | C38: Saída | D38: Salário | E38: Caixa | F38: Dinheiro | G38: 150 | J38: 2025-12 | K38: -5291.36
A39: 45996 | B39: Motoboy | C39: Saída | D39: iFood | E39: Banco Principal | F39: Pix | G39: 27 | J39: 2025-12 | K39: -5318.36
A40: 45997 | B40: Vendas do dia | C40: Entrada | D40: Vendas | G40: 8793 | J40: 2025-12 | K40: 3474.64
A41: 45997 | B41: Vendas iFood | C41: Entrada | D41: Vendas iFood | E41: Banco Principal | G41: 400.7 | J41: 2025-12 | K41: 3875.34
A42: 45997 | B42: Motoboy | C42: Saída | D42: iFood | E42: Banco Principal | F42: Pix | G42: 54 | J42: 2025-12 | K42: 3821.34
A43: 45997 | B43: Freelancer | C43: Saída | D43: Freelancer | E43: Caixa | F43: Dinheiro | G43: 120 | J43: 2025-12 | K43: 3701.34
A44: 45998 | B44: Freelancer | C44: Saída | D44: Freelancer | E44: Caixa | F44: Dinheiro | G44: 120 | J44: 2025-12 | K44: 3581.34
A45: 45998 | B45: Vendas do dia | C45: Entrada | D45: Vendas | G45: 8012 | J45: 2025-12 | K45: 11593.34
A46: 45998 | B46: Vendas iFood | C46: Entrada | D46: Vendas iFood | E46: Banco Principal | G46: 516.91 | J46: 2025-12 | K46: 12110.25
A47: 45998 | B47: Motoboy | C47: Saída | D47: iFood | E47: Banco Principal | F47: Pix | G47: 81 | J47: 2025-12 | K47: 12029.25
A48: 45998 | B48: Leite | C48: Saída | D48: Matéria Prima | E48: Caixa | F48: Dinheiro | G48: 235 | J48: 2025-12 | K48: 11794.25
A49: 45999 | B49: Frutas | C49: Saída | D49: Matéria Prima | E49: Banco Principal | F49: Pix | G49: 260 | J49: 2025-12 | K49: 11534.25
A50: 45999 | B50: Tráfego pago cartão de crédito | C50: Saída | D50: Marketing | E50: Banco Principal | G50: 1000 | J50: 2025-12 | K50: 10534.25
A51: 45999 | B51: Luz e água | C51: Saída | D51: CustoFixo | E51: Caixa | F51: Dinheiro | G51: 2473.41 | J51: 2025-12 | K51: 8060.84
A52: 45999 | B52: Boleto Unigra | C52: Saída | D52: Matéria Prima | E52: Banco Principal | G52: 3208.12 | J52: 2025-12 | K52: 4852.72
A53: 45999 | B53: Boleto pregel | C53: Saída | D53: Matéria Prima | E53: Banco Principal | G53: 1028.14 | J53: 2025-12 | K53: 3824.58
A54: 45999 | B54: Boleto andaluz | C54: Saída | D54: Matéria Prima | E54: Banco Principal | G54: 1020.55 | J54: 2025-12 | K54: 2804.03
A55: 45999 | B55: Salário Tais | C55: Saída | D55: Salário | E55: Banco Principal | F55: Pix | G55: 3000 | J55: 2025-12 | K55: -195.97
A56: 45999 | B56: Vendas do dia | C56: Entrada | D56: Vendas | G56: 3078 | J56: 2025-12 | K56: 2882.03
A57: 46000 | B57: Vendas do dia | C57: Entrada | D57: Vendas | G57: 758 | J57: 2025-12 | K57: 3640.03
A58: 45993 | B58: Vendas IFood | C58: Entrada | D58: Vendas iFood | E58: Banco Principal | G58: 24.3 | J58: 2025-12 | K58: 3664.33
A59: 46000 | B59: Motoboy | C59: Saída | D59: iFood | E59: Banco Principal | F59: Pix | G59: 9 | J59: 2025-12 | K59: 3655.33
A60: 46001 | B60: Vendas do dia | C60: Entrada | D60: Vendas | G60: 1246 | J60: 2025-12 | K60: 4901.33
A61: 46001 | B61: Vendas IFood | C61: Entrada | D61: Vendas iFood | E61: Banco Principal | G61: 34.3 | J61: 2025-12 | K61: 4935.63
A62: 46002 | B62: Águas | C62: Saída | D62: Matéria Prima | E62: Banco Principal | F62: Pix | G62: 378.5 | J62: 2025-12 | K62: 4557.13
A63: 46002 | B63: Royalty | C63: Saída | D63: Royalt | E63: Banco Principal | F63: Pix | G63: 8013.92 | J63: 2025-12 | K63: -3456.79
A64: 46002 | B64: Marketing | C64: Saída | D64: Marketing | E64: Banco Principal | F64: Pix | G64: 450 | J64: 2025-12 | K64: -3906.79
A65: 46002 | B65: Conserto liquidificador | C65: Saída | D65: Matéria Prima | E65: Banco Principal | G65: 80 | J65: 2025-12 | K65: -3986.79
A66: 46002 | B66: COnserto liquidificador | C66: Saída | D66: Matéria Prima | E66: Caixa | F66: Dinheiro | G66: 200 | J66: 2025-12 | K66: -4186.79
A67: 46002 | B67: Leite | C67: Saída | D67: Matéria Prima | E67: Caixa | F67: Dinheiro | G67: 150 | J67: 2025-12 | K67: -4336.79
A68: 46002 | B68: Vendas do dia | C68: Entrada | D68: Vendas | G68: 2280 | J68: 2025-12 | K68: -2056.79
A69: 46002 | B69: Vendas IFood | C69: Entrada | D69: Vendas iFood | E69: Banco Principal | G69: 49 | J69: 2025-12 | K69: -2007.79
A70: 46002 | B70: Motoboy | C70: Saída | D70: iFood | E70: Banco Principal | F70: Pix | G70: 26 | J70: 2025-12 | K70: -2033.79
A71: 46003 | B71: Vendas do dia | C71: Entrada | D71: Vendas | G71: 4609 | J71: 2025-12 | K71: 2575.21
A72: 46003 | B72: Vendas do Ifood | C72: Entrada | D72: Vendas iFood | E72: Banco Principal | G72: 137.57 | J72: 2025-12 | K72: 2712.78
A73: 46003 | B73: Motoboy | C73: Saída | D73: iFood | E73: Banco Principal | F73: Pix | G73: 36 | J73: 2025-12 | K73: 2676.78
A74: 46003 | B74: Leite | C74: Saída | D74: Matéria Prima | E74: Caixa | F74: Dinheiro | G74: 508 | J74: 2025-12 | K74: 2168.78
A75: 46004 | B75: Vendas do dia | C75: Entrada | D75: Vendas | G75: 6263.5 | J75: 2025-12 | K75: 8432.28
A76: 46004 | B76: Vendas IFood | C76: Entrada | D76: Vendas iFood | E76: Banco Principal | G76: 309.3 | J76: 2025-12 | K76: 8741.58
A77: 46004 | B77: Motoboy | C77: Saída | D77: iFood | E77: Banco Principal | F77: Pix | G77: 44 | J77: 2025-12 | K77: 8697.58
A78: 46005 | B78: Vendas do dia | C78: Entrada | D78: Vendas | G78: 7458 | J78: 2025-12 | K78: 16155.58
A79: 46005 | B79: Vendas IFood | C79: Entrada | D79: Vendas iFood | E79: Banco Principal | G79: 271.34 | J79: 2025-12 | K79: 16426.92
A80: 46005 | B80: Motoboy | C80: Saída | D80: iFood | E80: Banco Principal | F80: Pix | G80: 53 | J80: 2025-12 | K80: 16373.92
A81: 46005 | B81: Vale Luany | C81: Saída | D81: Salário | E81: Caixa | F81: Dinheiro | G81: 20 | J81: 2025-12 | K81: 16353.92
A82: 46006 | B82: Restante salario Tais | C82: Saída | D82: Salário | E82: Banco Principal | F82: Pix | G82: 2000 | J82: 2025-12 | K82: 14353.92
A83: 46006 | B83: Boleto Riber | C83: Saída | D83: Matéria Prima | E83: Banco Principal | G83: 1482.05 | J83: 2025-12 | K83: 12871.87
A84: 46006 | B84: Boleto Riber | C84: Saída | D84: Matéria Prima | E84: Banco Principal | G84: 584.39 | J84: 2025-12 | K84: 12287.48
A85: 46006 | B85: Boleto Unigra | C85: Saída | D85: Matéria Prima | E85: Banco Principal | G85: 2146.66 | J85: 2025-12 | K85: 10140.82
A86: 46006 | B86: Seguro de Vida | C86: Saída | D86: Salário | E86: Banco Principal | G86: 84.34 | J86: 2025-12 | K86: 10056.48
A87: 46006 | B87: Contabilidade | C87: Saída | D87: Contabilidade | E87: Banco Principal | G87: 1166.74 | J87: 2025-12 | K87: 8889.74
A88: 46006 | B88: Boleto Polar | C88: Saída | D88: Matéria Prima | E88: Banco Principal | G88: 447.66 | J88: 2025-12 | K88: 8442.08
A89: 46006 | B89: Boleto Polar | C89: Saída | D89: Matéria Prima | E89: Banco Principal | G89: 419.75 | J89: 2025-12 | K89: 8022.33
A90: 46006 | B90: Boleto Unigra | C90: Saída | D90: Matéria Prima | E90: Banco Principal | G90: 237.61 | J90: 2025-12 | K90: 7784.72
A91: 46006 | B91: Boleto Unigra | C91: Saída | D91: Matéria Prima | E91: Banco Principal | G91: 514.82 | J91: 2025-12 | K91: 7269.9
A92: 46006 | B92: Internet | C92: Saída | D92: CustoFixo | E92: Banco Principal | G92: 99.9 | J92: 2025-12 | K92: 7170
A93: 46006 | B93: Plano odontológico | C93: Saída | D93: Salário | E93: Banco Principal | G93: 236.6 | J93: 2025-12 | K93: 6933.4
A94: 46006 | B94: Boleto Riber | C94: Saída | D94: Matéria Prima | E94: Banco Principal | G94: 3040.57 | J94: 2025-12 | K94: 3892.83
A95: 46006 | B95: Creme de Leite | C95: Saída | D95: Matéria Prima | E95: Banco Principal | F95: Pix | G95: 666 | J95: 2025-12 | K95: 3226.83
A96: 46006 | B96: Leite | C96: Saída | D96: Matéria Prima | E96: Caixa | F96: Dinheiro | G96: 94 | J96: 2025-12 | K96: 3132.83
A97: 46006 | B97: Vendas do dia | C97: Entrada | D97: Vendas | G97: 2306 | J97: 2025-12 | K97: 5438.83
A98: 46007 | B98: Boleto Diniz | C98: Saída | D98: Matéria Prima | E98: Banco Principal | G98: 672.56 | J98: 2025-12 | K98: 4766.27
A99: 46007 | B99: Leite | C99: Saída | D99: Matéria Prima | E99: Caixa | F99: Dinheiro | G99: 94 | J99: 2025-12 | K99: 4672.27
A100: 46007 | B100: Vendas IFood | C100: Entrada | D100: Vendas iFood | E100: Banco Principal | G100: 68.6 | J100: 2025-12 | K100: 4740.87
A101: 46007 | B101: Vendas do dia | C101: Entrada | D101: Vendas | G101: 2812 | J101: 2025-12 | K101: 7552.87
...

Sheet JAN_26
A2: Data | B2: Descrição | C2: Tipo | D2: Categoria | E2: Conta | F2: Forma de pagamento | G2: Valor | I2: Obs | J2: Mês | K2: Saldo acumulado
A3: 46024 | B3: Tortelli | C3: Saída | D3: Tortelli | E3: Banco Principal | G3: 13185 | J3: 2026-01 | K3: -13185
A4: 46024 | B4: Vendas | C4: Entrada | D4: Vendas | G4: 10749 | J4: 2026-01 | K4: -2436
A5: 46024 | B5: Vendas Ifood | C5: Entrada | D5: Vendas iFood | G5: 228.9 | J5: 2026-01 | K5: -2207.1
A6: 46024 | B6: Motoboy | C6: Saída | D6: iFood | E6: Banco Principal | F6: Pix | G6: 35 | J6: 2026-01 | K6: -2242.1
A7: 46024 | B7: Leite | C7: Saída | D7: Matéria Prima | E7: Caixa | F7: Dinheiro | G7: 188 | J7: 2026-01 | K7: -2430.1
A8: 46024 | B8: Água | C8: Saída | D8: Matéria Prima | E8: Banco Principal | F8: Pix | G8: 203.5 | J8: 2026-01 | K8: -2633.6
A9: 46024 | B9: Celso Boleto | C9: Saída | D9: Celso | E9: Banco Principal | G9: 5091.58 | J9: 2026-01 | K9: -7725.18
A10: 46024 | B10: Celso Pix | C10: Saída | D10: Celso | E10: Banco Principal | F10: Pix | G10: 8462.74 | J10: 2026-01 | K10: -16187.92
A11: 46025 | B11: Leite | C11: Saída | D11: Matéria Prima | E11: Caixa | F11: Dinheiro | G11: 300 | J11: 2026-01 | K11: -16487.92
A12: 46025 | B12: Freelancer | C12: Saída | D12: Freelancer | E12: Caixa | F12: Dinheiro | G12: 150 | J12: 2026-01 | K12: -16637.92
A13: 46025 | B13: Vendas | C13: Entrada | D13: Vendas | G13: 12622 | J13: 2026-01 | K13: -4015.92
A14: 46025 | B14: Vendas Ifood | C14: Entrada | D14: Vendas iFood | E14: Banco Principal | G14: 183.15 | J14: 2026-01 | K14: -3832.77
A15: 46025 | B15: Motoboy | C15: Saída | D15: iFood | E15: Banco Principal | F15: Pix | G15: 44 | J15: 2026-01 | K15: -3876.77
A16: 46026 | B16: Leite | C16: Saída | D16: Matéria Prima | E16: Caixa | F16: Dinheiro | G16: 235 | J16: 2026-01 | K16: -4111.77
A17: 46026 | B17: Freelancer | C17: Saída | D17: Freelancer | E17: Caixa | F17: Dinheiro | G17: 270 | J17: 2026-01 | K17: -4381.77
A18: 46026 | B18: Vendas | C18: Entrada | D18: Vendas | G18: 12260 | J18: 2026-01 | K18: 7878.23
A19: 46026 | B19: Vendas Ifood | C19: Entrada | D19: Vendas iFood | E19: Banco Principal | G19: 798.02 | J19: 2026-01 | K19: 8676.25
A20: 46026 | B20: Motoboy | C20: Saída | D20: iFood | E20: Banco Principal | F20: Pix | G20: 95 | J20: 2026-01 | K20: 8581.25
A21: 46027 | B21: Boleto Potes Delivery | C21: Saída | D21: Mat Consumo | E21: Banco Principal | G21: 929.88 | J21: 2026-01 | K21: 7651.37
A22: 46027 | B22: Boleto Polar | C22: Saída | D22: Matéria Prima | E22: Banco Principal | G22: 1115.22 | J22: 2026-01 | K22: 6536.15
A23: 46027 | B23: Boleto Polar | C23: Saída | D23: Matéria Prima | E23: Banco Principal | G23: 833.98 | J23: 2026-01 | K23: 5702.17
A24: 46027 | B24: Frutas Congeladas | C24: Saída | D24: Matéria Prima | E24: Banco Principal | G24: 315 | J24: 2026-01 | K24: 5387.17
A25: 46027 | B25: Creme de Leite | C25: Saída | D25: Matéria Prima | E25: Banco Principal | G25: 646 | J25: 2026-01 | K25: 4741.17
A26: 46027 | B26: Aluguel | C26: Saída | D26: CustoFixo | E26: Banco Principal | G26: 9000 | J26: 2026-01 | K26: -4258.83
A27: 46027 | B27: Leite | C27: Saída | D27: Matéria Prima | E27: Caixa | G27: 141 | J27: 2026-01 | K27: -4399.83
A28: 46027 | B28: Vendas | C28: Entrada | D28: Vendas | G28: 4473 | J28: 2026-01 | K28: 73.17
A29: 46027 | B29: Vendas Ifood | C29: Entrada | D29: Vendas iFood | E29: Banco Principal | G29: 96.29 | J29: 2026-01 | K29: 169.46
A30: 46027 | B30: Motoboy | C30: Saída | D30: iFood | E30: Banco Principal | G30: 8 | J30: 2026-01 | K30: 161.46
A31: 46027 | B31: Cartao de Credito | C31: Saída | D31: Cartao de Credito | E31: Banco Principal | G31: 5371.8 | J31: 2026-01 | K31: -5210.34
A32: 46027 | B32: Trafego Pago | C32: Saída | D32: Marketing | E32: Banco Principal | G32: 1000 | J32: 2026-01 | K32: -6210.34
A33: 46028 | B33: Pano de Prato | C33: Saída | D33: Mat Consumo | E33: Caixa | F33: Dinheiro | G33: 20 | J33: 2026-01 | K33: -6230.34
A34: 46028 | B34: Vendas | C34: Entrada | D34: Vendas | G34: 4131 | J34: 2026-01 | K34: -2099.34
A35: 46028 | B35: Vendas Ifood | C35: Entrada | D35: Vendas iFood | E35: Banco Principal | G35: 19.6 | J35: 2026-01 | K35: -2079.74
A36: 46028 | B36: Motoboy | C36: Saída | D36: iFood | E36: Banco Principal | G36: 0 | J36: 2026-01 | K36: -2079.74
A37: 46028 | B37: Frutas Congeladas | C37: Saída | D37: Matéria Prima | E37: Banco Principal | F37: Pix | G37: 290 | J37: 2026-01 | K37: -2369.74
A38: 46028 | B38: Boleto Unigra | C38: Saída | D38: Matéria Prima | E38: Banco Principal | G38: 3208.22 | J38: 2026-01 | K38: -5577.96
A39: 46028 | B39: Boleto Guardanapo | C39: Saída | D39: Mat Consumo | E39: Banco Principal | G39: 476.59 | J39: 2026-01 | K39: -6054.55
A40: 46028 | B40: Boleto Riber | C40: Saída | D40: Matéria Prima | E40: Banco Principal | G40: 3409.49 | J40: 2026-01 | K40: -9464.04
A41: 46028 | B41: Boleto Mec3 | C41: Saída | D41: Matéria Prima | E41: Banco Principal | G41: 2269.26 | J41: 2026-01 | K41: -11733.3
A42: 46028 | B42: Boleto Riber | C42: Saída | D42: Matéria Prima | E42: Banco Principal | G42: 2707.7 | J42: 2026-01 | K42: -14441
A43: 46028 | B43: Boleto Alarme | C43: Saída | D43: CustoFixo | E43: Banco Principal | G43: 102.2 | J43: 2026-01 | K43: -14543.2
A44: 46028 | B44: Boleto Pregel | C44: Saída | D44: Matéria Prima | E44: Banco Principal | G44: 1028.12 | J44: 2026-01 | K44: -15571.32
A45: 46028 | B45: Leite | C45: Saída | D45: Matéria Prima | E45: Caixa | F45: Dinheiro | G45: 47 | J45: 2026-01 | K45: -15618.32
A46: 46029 | B46: Frete guardanapos | C46: Saída | D46: Frete | E46: Banco Principal | G46: 342.77 | J46: 2026-01 | K46: -15961.09
A47: 46029 | B47: Salarios | C47: Saída | D47: Salário | E47: Banco Principal | F47: Pix | G47: 8362.66 | J47: 2026-01 | K47: -24323.75
A48: 46029 | B48: Salario Tais | C48: Saída | D48: Salário | E48: Banco Principal | F48: Pix | G48: 4000 | J48: 2026-01 | K48: -28323.75
A49: 46029 | B49: Vendas | C49: Entrada | D49: Vendas | G49: 3146 | J49: 2026-01 | K49: -25177.75
A50: 46029 | B50: Vendas ifood | C50: Entrada | D50: Vendas iFood | E50: Banco Principal | G50: 0 | J50: 2026-01 | K50: -25177.75
A51: 46029 | B51: Motoboy | C51: Saída | D51: iFood | E51: Banco Principal | F51: Pix | G51: 0 | J51: 2026-01 | K51: -25177.75
A52: 46029 | B52: Leite | C52: Saída | D52: Matéria Prima | E52: Caixa | F52: Dinheiro | G52: 244 | J52: 2026-01 | K52: -25421.75
A53: 46030 | B53: Boleto Pazotti | C53: Saída | D53: Matéria Prima | E53: Banco Principal | G53: 156.08 | J53: 2026-01 | K53: -25577.83
A54: 46030 | B54: Leite | C54: Saída | D54: Matéria Prima | E54: Caixa | F54: Dinheiro | G54: 470 | J54: 2026-01 | K54: -26047.83
A55: 46030 | B55: Vendas | C55: Entrada | D55: Vendas | G55: 5211 | J55: 2026-01 | K55: -20836.83
A56: 46030 | B56: Venda iFood | C56: Entrada | D56: Vendas iFood | E56: Banco Principal | G56: 0 | J56: 2026-01 | K56: -20836.83
A57: 46030 | B57: Motoboy | C57: Saída | D57: iFood | E57: Banco Principal | F57: Pix | G57: 0 | J57: 2026-01 | K57: -20836.83
A58: 46030 | B58: Fabi faxina | C58: Saída | D58: Freelancer | E58: Banco Principal | F58: Pix | G58: 112 | J58: 2026-01 | K58: -20948.83
A59: 46030 | B59: Patrícia Faxina | C59: Saída | D59: Salário | E59: Banco Principal | F59: Pix | G59: 900 | J59: 2026-01 | K59: -21848.83
A60: 46031 | B60: Boleto Unigra | C60: Saída | D60: Matéria Prima | E60: Banco Principal | G60: 2097.72 | J60: 2026-01 | K60: -23946.55
A61: 46031 | B61: Leite | C61: Saída | D61: Matéria Prima | E61: Caixa | F61: Dinheiro | G61: 329 | J61: 2026-01 | K61: -24275.55
A62: 46031 | B62: Vendas | C62: Entrada | D62: Vendas | G62: 8220 | J62: 2026-01 | K62: -16055.55
A63: 46031 | B63: Vendas iFood | C63: Entrada | D63: Vendas iFood | E63: Banco Principal | G63: 58.01 | J63: 2026-01 | K63: -15997.54
A64: 46031 | B64: Motoboy | C64: Saída | D64: iFood | E64: Banco Principal | F64: Pix | G64: 17 | J64: 2026-01 | K64: -16014.54
A65: 46031 | B65: Água | C65: Saída | D65: Matéria Prima | E65: Banco Principal | F65: Pix | G65: 378.5 | J65: 2026-01 | K65: -16393.04
A66: 46032 | B66: Marketing | C66: Saída | D66: Marketing | E66: Banco Principal | F66: Pix | G66: 450 | J66: 2026-01 | K66: -16843.04
A67: 46032 | B67: Royalt | C67: Saída | D67: Royalt | E67: Banco Principal | F67: Pix | G67: 9629.05 | J67: 2026-01 | K67: -26472.09
A68: 46032 | B68: Seguro de vida | C68: Saída | D68: Salário | E68: Banco Principal | G68: 72 | J68: 2026-01 | K68: -26544.09
A69: 46032 | B69: Vendas | C69: Entrada | D69: Vendas | G69: 11002 | J69: 2026-01 | K69: -15542.09
A70: 46032 | B70: Vendas Ifood | C70: Entrada | D70: Vendas iFood | E70: Banco Principal | G70: 259.87 | J70: 2026-01 | K70: -15282.22
A71: 46032 | B71: Motoboy | C71: Saída | D71: iFood | E71: Banco Principal | F71: Pix | G71: 43 | J71: 2026-01 | K71: -15325.22
A72: 46032 | B72: Freelancer | C72: Saída | D72: Freelancer | E72: Caixa | F72: Dinheiro | G72: 150 | J72: 2026-01 | K72: -15475.22
A73: 46032 | B73: Contabilidade | C73: Saída | D73: CustoFixo | E73: Banco Principal | G73: 685 | J73: 2026-01 | K73: -16160.22
A74: 46032 | B74: Frutas Congeladas | C74: Saída | D74: Matéria Prima | E74: Banco Principal | F74: Pix | G74: 110 | J74: 2026-01 | K74: -16270.22
A75: 46033 | B75: Vendas | C75: Entrada | D75: Vendas | G75: 11570 | J75: 2026-01 | K75: -4700.22
A76: 46033 | B76: Vendas iFood | C76: Entrada | D76: Vendas iFood | E76: Banco Principal | G76: 643.9 | J76: 2026-01 | K76: -4056.32
A77: 46033 | B77: Motoboy | C77: Saída | D77: iFood | E77: Banco Principal | F77: Pix | G77: 89 | J77: 2026-01 | K77: -4145.32
A78: 46033 | B78: Leite | C78: Saída | D78: Matéria Prima | E78: Caixa | F78: Dinheiro | G78: 94 | J78: 2026-01 | K78: -4239.32
A79: 46033 | B79: Freelancer | C79: Saída | D79: Freelancer | E79: Caixa | F79: Dinheiro | G79: 300 | J79: 2026-01 | K79: -4539.32
A80: 46034 | B80: Exame demissional | C80: Saída | D80: Demissão | E80: Banco Principal | F80: Pix | G80: 45 | J80: 2026-01 | K80: -4584.32
A81: 46034 | B81: Boleto Riber | C81: Saída | D81: Matéria Prima | E81: Banco Principal | G81: 557.34 | J81: 2026-01 | K81: -5141.66
A82: 46034 | B82: Liquidificador | C82: Saída | D82: Mat Consumo | E82: Banco Principal | F82: Pix | G82: 2078.71 | J82: 2026-01 | K82: -7220.37
A83: 46034 | B83: Vendas | C83: Entrada | D83: Vendas | G83: 4081 | J83: 2026-01 | K83: -3139.37
A84: 46034 | B84: Vendas iFood | C84: Entrada | D84: Vendas iFood | E84: Banco Principal | G84: 157.56 | J84: 2026-01 | K84: -2981.81
A85: 46034 | B85: Motoboy | C85: Saída | D85: iFood | E85: Banco Principal | F85: Pix | G85: 18 | J85: 2026-01 | K85: -2999.81
A86: 46034 | B86: Leite | C86: Saída | D86: Matéria Prima | E86: Caixa | F86: Dinheiro | G86: 141 | J86: 2026-01 | K86: -3140.81
A87: 46034 | B87: Creme de leite e lâmpada | C87: Saída | D87: Matéria Prima | E87: Caixa | F87: Dinheiro | G87: 35 | J87: 2026-01 | K87: -3175.81
A88: 46035 | B88: Boleto Unigra | C88: Saída | D88: Matéria Prima | E88: Banco Principal | G88: 514.83 | J88: 2026-01 | K88: -3690.64
A89: 46035 | B89: Boleto Riber | C89: Saída | D89: Matéria Prima | E89: Banco Principal | G89: 3409.49 | J89: 2026-01 | K89: -7100.13
A90: 46035 | B90: Boleto potes delivery | C90: Saída | D90: Mat Consumo | E90: Banco Principal | G90: 754 | J90: 2026-01 | K90: -7854.13
A91: 46035 | B91: Café | C91: Saída | D91: Mat Consumo | E91: Banco Principal | F91: Pix | G91: 600 | J91: 2026-01 | K91: -8454.13
A92: 46035 | B92: Vendas | C92: Entrada | D92: Vendas | G92: 3341 | J92: 2026-01 | K92: -5113.13
A93: 46035 | B93: Vendas Ifood | C93: Entrada | D93: Vendas iFood | E93: Banco Principal | G93: 0 | J93: 2026-01 | K93: -5113.13
A94: 46035 | B94: Motoboy | C94: Saída | D94: iFood | E94: Banco Principal | F94: Pix | G94: 0 | J94: 2026-01 | K94: -5113.13
A95: 46035 | B95: Leite | C95: Saída | D95: Matéria Prima | E95: Caixa | F95: Dinheiro | G95: 94 | J95: 2026-01 | K95: -5207.13
A96: 46035 | B96: Freelancer Luany | C96: Saída | D96: Freelancer | E96: Caixa | F96: Dinheiro | G96: 200 | J96: 2026-01 | K96: -5407.13
A97: 46036 | B97: Vendas | C97: Entrada | D97: Vendas | G97: 3528 | J97: 2026-01 | K97: -1879.13
A98: 46036 | B98: Vendas Ifoood | C98: Entrada | D98: Vendas iFood | E98: Banco Principal | G98: 0 | J98: 2026-01 | K98: -1879.13
A99: 46036 | B99: Motoboy | C99: Saída | D99: iFood | E99: Banco Principal | F99: Pix | G99: 0 | J99: 2026-01 | K99: -1879.13
A100: 46036 | B100: Leite | C100: Saída | D100: Matéria Prima | E100: Caixa | F100: Dinheiro | G100: 94 | J100: 2026-01 | K100: -1973.13
A101: 46036 | B101: Papel Higienico | C101: Saída | D101: Mat Consumo | E101: Caixa | F101: Dinheiro | G101: 72 | J101: 2026-01 | K101: -2045.13
...

Sheet FEV_25
A1: Data | B1: Descrição | C1: Tipo | D1: Categoria | E1: Conta | F1: Forma de pagamento | G1: Valor | I1: Obs | J1: Mês | K1: Saldo acumulado
A2: 46054 | B2: Dias Amanda teste | C2: Saída | D2: Freelancer | E2: Banco Principal | F2: Pix | G2: 390 | J2: 2026-02 | K2: -390
A3: 46054 | B3: Vendas | C3: Entrada | D3: Vendas | G3: 5836 | J3: 2026-02 | K3: 5446
A4: 46054 | B4: Vendas Ifood | C4: Entrada | D4: Vendas iFood | E4: Banco Principal | G4: 387.11 | J4: 2026-02 | K4: 5833.11
A5: 46054 | B5: Motoboy | C5: Saída | D5: iFood | E5: Banco Principal | F5: Pix | G5: 54 | J5: 2026-02 | K5: 5779.11
A6: 46055 | B6: Boleto Diniz | C6: Saída | D6: Matéria Prima | E6: Banco Principal | G6: 464.11 | J6: 2026-02 | K6: 5315
A7: 46055 | B7: ICMS | C7: Saída | D7: Impostos | E7: Banco Principal | G7: 263.86 | J7: 2026-02 | K7: 5051.14
A8: 46055 | B8: Vendas | C8: Entrada | D8: Vendas | G8: 1657 | J8: 2026-02 | K8: 6708.14
A9: 46055 | B9: Vendas iFood | C9: Entrada | D9: Vendas iFood | E9: Banco Principal | G9: 0 | J9: 2026-02 | K9: 6708.14
A10: 46055 | B10: Motoboy | C10: Saída | D10: iFood | E10: Banco Principal | F10: Pix | G10: 0 | J10: 2026-02 | K10: 6708.14
A11: 46055 | B11: Leite | C11: Saída | D11: Matéria Prima | E11: Caixa | F11: Dinheiro | G11: 0 | J11: 2026-02 | K11: 6708.14
A12: 46055 | B12: Exame adimissional | C12: Saída | D12: Contabilidade | E12: Banco Principal | F12: Pix | G12: 45 | J12: 2026-02 | K12: 6663.14
A13: 46055 | B13: Plaquinha e adesivo | C13: Saída | D13: Marketing | E13: Banco Principal | F13: Pix | G13: 45 | J13: 2026-02 | K13: 6618.14
A14: 46056 | B14: Vendas | C14: Entrada | D14: Vendas | G14: 1296 | J14: 2026-02 | K14: 7914.14
A15: 46056 | B15: Vendas Ifood | C15: Entrada | D15: Vendas iFood | E15: Banco Principal | G15: 151.79 | J15: 2026-02 | K15: 8065.93
A16: 46056 | B16: Motoboy | C16: Saída | D16: iFood | E16: Banco Principal | F16: Pix | G16: 36 | J16: 2026-02 | K16: 8029.93
A17: 46056 | B17: Leite | C17: Saída | D17: Matéria Prima | E17: Caixa | F17: Dinheiro | G17: 0 | J17: 2026-02 | K17: 8029.93
A18: 46056 | B18: Frutas | C18: Saída | D18: Matéria Prima | E18: Banco Principal | F18: Pix | G18: 455 | J18: 2026-02 | K18: 7574.93
A19: 46056 | B19: Agua | C19: Saída | D19: Matéria Prima | E19: Banco Principal | F19: Pix | G19: 203.5 | J19: 2026-02 | K19: 7371.43
A20: 46056 | B20: Boleto Ecila | C20: Saída | D20: Matéria Prima | E20: Banco Principal | G20: 708.88 | J20: 2026-02 | K20: 6662.55
A21: 46056 | B21: Boleto riber | C21: Saída | D21: Matéria Prima | E21: Banco Principal | G21: 1106.8 | J21: 2026-02 | K21: 5555.75
A22: 46056 | B22: Boleto riber | C22: Saída | D22: Matéria Prima | E22: Banco Principal | G22: 2822 | J22: 2026-02 | K22: 2733.75
A23: 46056 | B23: Boleto mec 3 | C23: Saída | D23: Matéria Prima | E23: Banco Principal | G23: 2269.94 | J23: 2026-02 | K23: 463.81
A24: 46056 | B24: Paçoca | C24: Saída | D24: Matéria Prima | E24: Caixa | F24: Dinheiro | G24: 53 | J24: 2026-02 | K24: 410.81
A25: 46057 | B25: Vendas | C25: Entrada | D25: Vendas | G25: 1846 | J25: 2026-02 | K25: 2256.81
A26: 46057 | B26: Vendas Ifood | C26: Entrada | D26: Vendas iFood | E26: Banco Principal | G26: 226.89 | J26: 2026-02 | K26: 2483.7
A27: 46057 | B27: Motoboy | C27: Saída | D27: iFood | E27: Banco Principal | F27: Pix | G27: 27 | J27: 2026-02 | K27: 2456.7
A28: 46057 | B28: Leite | C28: Saída | D28: Matéria Prima | E28: Caixa | F28: Dinheiro | G28: 235 | J28: 2026-02 | K28: 2221.7
A29: 46057 | B29: Salarios | C29: Saída | D29: Salário | E29: Banco Principal | F29: Pix | G29: 6269.02 | J29: 2026-02 | K29: -4047.32
A30: 46057 | B30: Salrio Tais | C30: Saída | D30: Salário | E30: Banco Principal | F30: Pix | G30: 4500 | J30: 2026-02 | K30: -8547.32
A31: 46058 | B31: Cartão | C31: Saída | D31: Cartao de Credito | E31: Banco Principal | G31: 4243.39 | J31: 2026-02 | K31: -12790.71
A32: 46058 | B32: Tráfego pago | C32: Saída | D32: Marketing | E32: Banco Principal | G32: 1000 | J32: 2026-02 | K32: -13790.71
A33: 46058 | B33: Aluguel | C33: Saída | D33: CustoFixo | E33: Banco Principal | G33: 9000 | J33: 2026-02 | K33: -22790.71
A34: 46058 | B34: Alarme | C34: Saída | D34: CustoFixo | E34: Banco Principal | G34: 100 | J34: 2026-02 | K34: -22890.71
A35: 46058 | B35: Leite | C35: Saída | D35: Matéria Prima | E35: Caixa | F35: Dinheiro | G35: 0 | J35: 2026-02 | K35: -22890.71
A36: 46058 | B36: Vendas | C36: Entrada | D36: Vendas | G36: 1824 | J36: 2026-02 | K36: -21066.71
A37: 46058 | B37: Venda iFood | C37: Entrada | D37: Vendas iFood | E37: Banco Principal | G37: 0 | J37: 2026-02 | K37: -21066.71
A38: 46058 | B38: Motoboy | C38: Saída | D38: iFood | E38: Banco Principal | F38: Pix | G38: 0 | J38: 2026-02 | K38: -21066.71
A39: 46058 | B39: Creme de leite | C39: Saída | D39: Matéria Prima | E39: Banco Principal | F39: Pix | G39: 594.5 | J39: 2026-02 | K39: -21661.21
A40: 46059 | B40: Leite | C40: Saída | D40: Matéria Prima | E40: Caixa | F40: Dinheiro | G40: 329 | J40: 2026-02 | K40: -21990.21
A41: 46059 | B41: Vendas | C41: Entrada | D41: Vendas | G41: 1840 | J41: 2026-02 | K41: -20150.21
A42: 46059 | B42: Vendas Ifood | C42: Entrada | D42: Vendas iFood | E42: Banco Principal | G42: 157.84 | J42: 2026-02 | K42: -19992.37
A43: 46059 | B43: Motoboy | C43: Saída | D43: iFood | E43: Banco Principal | F43: Pix | G43: 44 | J43: 2026-02 | K43: -20036.37
A44: 46060 | B44: Vendas | C44: Entrada | D44: Vendas | G44: 4623 | J44: 2026-02 | K44: -15413.37
A45: 46060 | B45: Vendas Ifood | C45: Entrada | D45: Vendas iFood | E45: Banco Principal | G45: 108.95 | J45: 2026-02 | K45: -15304.42
A46: 46060 | B46: Motoboy | C46: Saída | D46: iFood | E46: Banco Principal | F46: Pix | G46: 17 | J46: 2026-02 | K46: -15321.42
A47: 46060 | B47: Amanda teste | C47: Saída | D47: Freelancer | E47: Banco Principal | F47: Pix | G47: 330 | J47: 2026-02 | K47: -15651.42
A48: 46060 | B48: Conserto ar condicionado | C48: Saída | D48: Manutenção | E48: Banco Principal | F48: Pix | G48: 350 | J48: 2026-02 | K48: -16001.42
A49: 46060 | B49: Baldes 50 litros | C49: Saída | D49: Mat Consumo | E49: Caixa | F49: Dinheiro | G49: 50 | J49: 2026-02 | K49: -16051.42
A50: 46061 | B50: Vendas | C50: Entrada | D50: Vendas | G50: 5426 | J50: 2026-02 | K50: -10625.42
A51: 46061 | B51: Vendas Ifood | C51: Entrada | D51: Vendas iFood | E51: Banco Principal | G51: 191.32 | J51: 2026-02 | K51: -10434.1
A52: 46061 | B52: Motoboy | C52: Saída | D52: iFood | E52: Banco Principal | F52: Pix | G52: 17 | J52: 2026-02 | K52: -10451.1
A53: 46061 | B53: Pano de Prato | C53: Saída | D53: Mat Consumo | E53: Caixa | F53: Dinheiro | G53: 20 | J53: 2026-02 | K53: -10471.1
A54: 46062 | B54: Boleto Unigra | C54: Saída | D54: Matéria Prima | E54: Banco Principal | G54: 2097.77 | J54: 2026-02 | K54: -12568.87
A55: 46062 | B55: Águas | C55: Saída | D55: Matéria Prima | E55: Banco Principal | G55: 382.5 | J55: 2026-02 | K55: -12951.37
A56: 46062 | B56: Vendas | C56: Entrada | D56: Vendas | G56: 569 | J56: 2026-02 | K56: -12382.37
A57: 46062 | B57: Vendas iFood | C57: Entrada | D57: Vendas iFood | E57: Banco Principal | G57: 10.9 | J57: 2026-02 | K57: -12371.47
A58: 46062 | B58: Motoboy | C58: Saída | D58: iFood | E58: Banco Principal | F58: Pix | G58: 9 | J58: 2026-02 | K58: -12380.47
A59: 46063 | B59: Royalt | C59: Saída | D59: Royalt | E59: Banco Principal | F59: Pix | G59: 10172.6 | J59: 2026-02 | K59: -22553.07
A60: 46063 | B60: Marketing | C60: Saída | D60: Marketing | E60: Banco Principal | F60: Pix | G60: 450 | J60: 2026-02 | K60: -23003.07
A61: 46063 | B61: Boleto Seguro de vida | C61: Saída | D61: Salário | E61: Banco Principal | G61: 60 | J61: 2026-02 | K61: -23063.07
A62: 46063 | B62: Contabilidade | C62: Saída | D62: Contabilidade | E62: Banco Principal | G62: 732 | J62: 2026-02 | K62: -23795.07
A63: 46063 | B63: Vendas | C63: Entrada | D63: Vendas | G63: 1826 | J63: 2026-02 | K63: -21969.07
A64: 46063 | B64: Venda iFood | C64: Entrada | D64: Vendas iFood | E64: Banco Principal | G64: 57.9 | J64: 2026-02 | K64: -21911.17
A65: 46063 | B65: Motoboy | C65: Saída | D65: iFood | E65: Banco Principal | F65: Pix | G65: 9 | J65: 2026-02 | K65: -21920.17
A66: 46063 | B66: Boleto Riber | C66: Saída | D66: Matéria Prima | E66: Banco Principal | G66: 1105.4 | J66: 2026-02 | K66: -23025.57
A67: 46063 | B67: Boleto Riber | C67: Saída | D67: Matéria Prima | E67: Banco Principal | G67: 1107.6 | J67: 2026-02 | K67: -24133.17
A68: 46063 | B68: Frutas | C68: Saída | D68: Matéria Prima | E68: Banco Principal | F68: Pix | G68: 156 | J68: 2026-02 | K68: -24289.17
A69: 46063 | B69: Banner | C69: Saída | D69: Marketing | E69: Banco Principal | F69: Pix | G69: 500 | J69: 2026-02 | K69: -24789.17
A70: 46063 | B70: Pazinhas Thales | C70: Saída | D70: Mat Consumo | E70: Caixa | F70: Dinheiro | G70: 1533.4 | J70: 2026-02 | K70: -26322.57
A71: 46064 | B71: Boleto. Andaluz | C71: Saída | D71: Matéria Prima | E71: Banco Principal | G71: 882.66 | J71: 2026-02 | K71: -27205.23
A72: 46064 | B72: Boleto Ecila | C72: Saída | D72: Matéria Prima | E72: Banco Principal | G72: 116.97 | J72: 2026-02 | K72: -27322.2
A73: 46064 | B73: Boleto Mec 3 | C73: Saída | D73: Matéria Prima | E73: Banco Principal | G73: 1831.59 | J73: 2026-02 | K73: -29153.79
A74: 46064 | B74: Leite | C74: Saída | D74: Matéria Prima | E74: Caixa | F74: Dinheiro | G74: 0 | J74: 2026-02 | K74: -29153.79
A75: 46064 | B75: Vendas | C75: Entrada | D75: Vendas | G75: 1154.6 | J75: 2026-02 | K75: -27999.19
A76: 46064 | B76: Vendas iFood | C76: Entrada | D76: Vendas iFood | E76: Banco Principal | G76: 24.3 | J76: 2026-02 | K76: -27974.89
A77: 46064 | B77: Motoboy | C77: Saída | D77: iFood | E77: Banco Principal | F77: Pix | G77: 9 | J77: 2026-02 | K77: -27983.89
A78: 46064 | B78: Uniformes | C78: Saída | D78: Manutenção | E78: Banco Principal | F78: Pix | G78: 1105 | J78: 2026-02 | K78: -29088.89
A79: 46065 | B79: Boleto Unigra | C79: Saída | D79: Matéria Prima | E79: Banco Principal | G79: 5156.3 | J79: 2026-02 | K79: -34245.19
A80: 46065 | B80: Leite | C80: Saída | D80: Matéria Prima | E80: Caixa | F80: Dinheiro | G80: 576 | J80: 2026-02 | K80: -34821.19
A81: 46065 | B81: Vendas | C81: Entrada | D81: Vendas | G81: 2113 | J81: 2026-02 | K81: -32708.19
A82: 46065 | B82: Vendas iFood | C82: Entrada | D82: Vendas iFood | E82: Banco Principal | G82: 74.39 | J82: 2026-02 | K82: -32633.8
A83: 46065 | B83: Motoboy | C83: Saída | D83: iFood | E83: Banco Principal | F83: Pix | G83: 18 | J83: 2026-02 | K83: -32651.8
A84: 46065 | B84: Luanny | C84: Saída | D84: Freelancer | E84: Banco Principal | F84: Pix | G84: 150 | J84: 2026-02 | K84: -32801.8
A85: 46066 | B85: Leite | C85: Saída | D85: Matéria Prima | E85: Caixa | F85: Dinheiro | G85: 670 | J85: 2026-02 | K85: -33471.8
A86: 46066 | B86: Vendas | C86: Entrada | D86: Vendas | G86: 5289 | J86: 2026-02 | K86: -28182.8
A87: 46066 | B87: Vendas Ifood | C87: Entrada | D87: Vendas iFood | E87: Banco Principal | G87: 99.78 | J87: 2026-02 | K87: -28083.02
A88: 46066 | B88: Motoboy | C88: Saída | D88: iFood | E88: Banco Principal | F88: Pix | G88: 36 | J88: 2026-02 | K88: -28119.02
A89: 46067 | B89: Cachaça | C89: Saída | D89: Matéria Prima | E89: Caixa | F89: Dinheiro | G89: 50 | J89: 2026-02 | K89: -28169.02
A90: 46067 | B90: Vendas | C90: Entrada | D90: Vendas | G90: 12357 | J90: 2026-02 | K90: -15812.02
A91: 46067 | B91: Vendas Ifood | C91: Entrada | D91: Vendas iFood | E91: Banco Principal | G91: 509.16 | J91: 2026-02 | K91: -15302.86
A92: 46067 | B92: Motoboy | C92: Saída | D92: iFood | E92: Banco Principal | F92: Pix | G92: 79 | J92: 2026-02 | K92: -15381.86
A93: 46067 | B93: Freelancer | C93: Saída | D93: Freelancer | E93: Caixa | F93: Dinheiro | G93: 150 | J93: 2026-02 | K93: -15531.86
A94: 46067 | B94: Farmacia bandaid e curativo | C94: Saída | D94: Papelaria | E94: Caixa | F94: Dinheiro | G94: 33 | J94: 2026-02 | K94: -15564.86
A95: 46068 | B95: Freelancer | C95: Saída | D95: Freelancer | E95: Caixa | F95: Dinheiro | G95: 280 | J95: 2026-02 | K95: -15844.86
A96: 46068 | B96: Leite | C96: Saída | D96: Matéria Prima | E96: Caixa | F96: Dinheiro | G96: 482 | J96: 2026-02 | K96: -16326.86
A97: 46068 | B97: Vendas | C97: Entrada | D97: Vendas | G97: 15317 | J97: 2026-02 | K97: -1009.86
A98: 46068 | B98: Vendas Ifood | C98: Entrada | D98: Vendas iFood | E98: Banco Principal | G98: 661.44 | J98: 2026-02 | K98: -348.42
A99: 46068 | B99: Motoboy | C99: Saída | D99: iFood | E99: Banco Principal | F99: Pix | G99: 107 | J99: 2026-02 | K99: -455.42
A100: 46069 | B100: Agua | C100: Saída | D100: Matéria Prima | E100: Banco Principal | F100: Pix | G100: 203.5 | J100: 2026-02 | K100: -658.92
...

Sheet MAR_26
A1: Data | B1: Descrição | C1: Tipo | D1: Categoria | E1: Conta | F1: Forma de pagamento | G1: Valor | I1: Obs | J1: Mês | K1: Saldo acumulado
A2: 46082 | B2: Vendas | C2: Entrada | D2: Vendas | G2: 6466 | J2: 2026-03 | K2: 6466
A3: 46082 | B3: Vendas Ifood | C3: Entrada | D3: Vendas iFood | E3: Banco Principal | G3: 349.8 | J3: 2026-03 | K3: 6815.8
A4: 46082 | B4: Motoboy | C4: Saída | D4: iFood | E4: Banco Principal | F4: Pix | G4: 70 | J4: 2026-03 | K4: 6745.8
A5: 46083 | B5: Faxina | C5: Saída | D5: Salário | E5: Banco Principal | F5: Pix | G5: 1100 | J5: 2026-03 | K5: 5645.8
A6: 46083 | B6: Boleto polar (Thales) | C6: Saída | D6: Matéria Prima | E6: Banco Principal | G6: 822.66 | J6: 2026-03 | K6: 4823.14
A7: 46083 | B7: Vendas | C7: Entrada | D7: Vendas | G7: 961 | J7: 2026-03 | K7: 5784.14
A8: 46083 | B8: Vendas iFood | C8: Entrada | D8: Vendas iFood | E8: Banco Principal | G8: 84.7 | J8: 2026-03 | K8: 5868.84
A9: 46083 | B9: Motoboy | C9: Saída | D9: iFood | E9: Banco Principal | F9: Pix | G9: 18 | J9: 2026-03 | K9: 5850.84
A10: 46084 | B10: Vendas | C10: Entrada | D10: Vendas | G10: 1606 | J10: 2026-03 | K10: 7456.84
A11: 46084 | B11: Vendas Ifood | C11: Entrada | D11: Vendas iFood | E11: Banco Principal | G11: 187.8 | J11: 2026-03 | K11: 7644.64
A12: 46084 | B12: Motoboy | C12: Saída | D12: iFood | E12: Banco Principal | F12: Pix | G12: 19 | J12: 2026-03 | K12: 7625.64
A13: 46084 | B13: Leite | C13: Saída | D13: Matéria Prima | E13: Caixa | F13: Dinheiro | G13: 0 | J13: 2026-03 | K13: 7625.64
A14: 46084 | B14: Luz + água | C14: Saída | D14: CustoFixo | E14: Caixa | F14: Dinheiro | G14: 3435.1 | J14: 2026-03 | K14: 4190.54
A15: 46084 | B15: Boleto riber | C15: Saída | D15: Matéria Prima | E15: Banco Principal | G15: 4143.2 | J15: 2026-03 | K15: 47.34
A16: 46084 | B16: Adesivo | C16: Saída | D16: Marketing | E16: Caixa | F16: Dinheiro | G16: 15 | J16: 2026-03 | K16: 32.34
A17: 46085 | B17: Vendas | C17: Entrada | D17: Vendas | G17: 2354 | J17: 2026-03 | K17: 2386.34
A18: 46085 | B18: Vendas iFood | C18: Entrada | D18: Vendas iFood | E18: Banco Principal | G18: 68.1 | J18: 2026-03 | K18: 2454.44
A19: 46085 | B19: Motoboy | C19: Saída | D19: iFood | E19: Banco Principal | F19: Pix | G19: 18 | J19: 2026-03 | K19: 2436.44
A20: 46085 | B20: Leite | C20: Saída | D20: Matéria Prima | E20: Caixa | F20: Dinheiro | G20: 235 | J20: 2026-03 | K20: 2201.44
A21: 46085 | B21: Adesivos | C21: Saída | D21: CustoFixo | E21: Banco Principal | F21: Pix | G21: 200 | J21: 2026-03 | K21: 2001.44
A22: 46086 | B22: Aluguel | C22: Saída | D22: CustoFixo | E22: Banco Principal | G22: 8918.64 | J22: 2026-03 | K22: -6917.2
A23: 46086 | B23: IPTU | C23: Saída | D23: CustoFixo | E23: Banco Principal | F23: Pix | G23: 94.9 | J23: 2026-03 | K23: -7012.1
A24: 46086 | B24: Alarme | C24: Saída | D24: CustoFixo | E24: Banco Principal | G24: 100 | J24: 2026-03 | K24: -7112.1
A25: 46086 | B25: Cartão de crédito restante | C25: Saída | D25: Cartao de Credito | E25: Banco Principal | G25: 566.91 | J25: 2026-03 | K25: -7679.01
A26: 46086 | B26: Salários | C26: Saída | D26: Salário | E26: Banco Principal | F26: Pix | G26: 7720.45 | J26: 2026-03 | K26: -15399.46
A27: 46086 | B27: Vendas | C27: Entrada | D27: Vendas | G27: 2009 | J27: 2026-03 | K27: -13390.46
A28: 46086 | B28: Vendas iFood | C28: Entrada | D28: Vendas iFood | E28: Banco Principal | G28: 203.2 | J28: 2026-03 | K28: -13187.26
A29: 46086 | B29: Motoboy | C29: Saída | D29: iFood | E29: Banco Principal | F29: Pix | G29: 27 | J29: 2026-03 | K29: -13214.26
A30: 46086 | B30: Leite | C30: Saída | D30: Matéria Prima | E30: Caixa | F30: Dinheiro | G30: 141 | J30: 2026-03 | K30: -13355.26
A31: 46086 | B31: Salário Tais | C31: Saída | D31: Salário | E31: Banco Principal | F31: Pix | G31: 5000 | J31: 2026-03 | K31: -18355.26
A32: 46086 | B32: Restante dias Amanda | C32: Saída | D32: Salário | E32: Banco Principal | F32: Pix | G32: 162 | J32: 2026-03 | K32: -18517.26
A33: 46087 | B33: Vendas | C33: Entrada | D33: Vendas | G33: 4333 | J33: 2026-03 | K33: -14184.26
A34: 46087 | B34: Vendas Ifood | C34: Entrada | D34: Vendas iFood | E34: Banco Principal | G34: 457.8 | J34: 2026-03 | K34: -13726.46
A35: 46087 | B35: Motoboy | C35: Saída | D35: iFood | E35: Banco Principal | F35: Pix | G35: 65 | J35: 2026-03 | K35: -13791.46
A36: 46087 | B36: Leite | C36: Saída | D36: Matéria Prima | E36: Caixa | F36: Dinheiro | G36: 423 | J36: 2026-03 | K36: -14214.46
A37: 46088 | B37: Vendas | C37: Entrada | D37: Vendas | G37: 6927 | J37: 2026-03 | K37: -7287.46
A38: 46088 | B38: Vendas Ifood | C38: Entrada | D38: Vendas iFood | E38: Banco Principal | G38: 393.5 | J38: 2026-03 | K38: -6893.96
A39: 46088 | B39: Motoboy | C39: Saída | D39: iFood | E39: Banco Principal | F39: Pix | G39: 72 | J39: 2026-03 | K39: -6965.96
A40: 46089 | B40: Vendas | C40: Entrada | D40: Vendas | G40: 8788 | J40: 2026-03 | K40: 1822.04
A41: 46089 | B41: Vendas iFood | C41: Entrada | D41: Vendas iFood | E41: Banco Principal | G41: 412.6 | J41: 2026-03 | K41: 2234.64
A42: 46089 | B42: Motoboy | C42: Saída | D42: iFood | E42: Banco Principal | F42: Pix | G42: 81 | J42: 2026-03 | K42: 2153.64
A43: 46090 | B43: Boleto mec 3 | C43: Saída | D43: Matéria Prima | E43: Banco Principal | G43: 1736.83 | J43: 2026-03 | K43: 416.81
A44: 46090 | B44: Vendas | C44: Entrada | D44: Vendas | G44: 1332 | J44: 2026-03 | K44: 1748.81
A45: 46090 | B45: Vendas iFood | C45: Entrada | D45: Vendas iFood | E45: Banco Principal | G45: 39 | J45: 2026-03 | K45: 1787.81
A46: 46090 | B46: Motoboy | C46: Saída | D46: iFood | E46: Banco Principal | F46: Pix | G46: 0 | J46: 2026-03 | K46: 1787.81
A47: 46090 | B47: Leite | C47: Saída | D47: Matéria Prima | E47: Caixa | F47: Dinheiro | G47: 0 | J47: 2026-03 | K47: 1787.81
A48: 46091 | B48: Contabilidade | C48: Saída | D48: Contabilidade | E48: Banco Principal | G48: 732 | J48: 2026-03 | K48: 1055.81
A49: 46091 | B49: Royalt | C49: Saída | D49: Royalt | E49: Banco Principal | F49: Pix | G49: 7563.28 | J49: 2026-03 | K49: -6507.47
A50: 46091 | B50: Marketing | C50: Saída | D50: Marketing | E50: Banco Principal | F50: Pix | G50: 450 | J50: 2026-03 | K50: -6957.47
A51: 46091 | B51: Boleto Diniz | C51: Saída | D51: Matéria Prima | E51: Banco Principal | G51: 400.39 | J51: 2026-03 | K51: -7357.86
A52: 46091 | B52: Frete Mec 3 | C52: Saída | D52: Frete | E52: Banco Principal | G52: 432.89 | J52: 2026-03 | K52: -7790.75
A53: 46091 | B53: Vendas | C53: Entrada | D53: Vendas | G53: 1319 | J53: 2026-03 | K53: -6471.75
A54: 46091 | B54: Vendas iFood | C54: Entrada | D54: Vendas iFood | E54: Banco Principal | G54: 92.6 | J54: 2026-03 | K54: -6379.15
A55: 46091 | B55: Motoboy | C55: Saída | D55: iFood | E55: Banco Principal | F55: Pix | G55: 26 | J55: 2026-03 | K55: -6405.15
A56: 46091 | B56: Creme de leite | C56: Saída | D56: Matéria Prima | E56: Banco Principal | F56: Pix | G56: 672.88 | J56: 2026-03 | K56: -7078.03
A57: 46091 | B57: Simples do mês de fevereiro | C57: Saída | D57: Impostos | E57: Banco Principal | G57: 10491.39 | J57: 2026-03 | K57: -17569.42
A58: 46091 | B58: Leite | C58: Saída | D58: Matéria Prima | E58: Caixa | F58: Dinheiro | G58: 0 | J58: 2026-03 | K58: -17569.42
A59: 46091 | B59: Aguas | C59: Saída | D59: Matéria Prima | E59: Banco Principal | F59: Pix | G59: 382.5 | J59: 2026-03 | K59: -17951.92
A60: 46092 | B60: Vendas | C60: Entrada | D60: Vendas | G60: 430 | J60: 2026-03 | K60: -17521.92
A61: 46092 | B61: Vendas iFood | C61: Entrada | D61: Vendas iFood | E61: Banco Principal | G61: 0 | J61: 2026-03 | K61: -17521.92
A62: 46092 | B62: Motoboy | C62: Saída | D62: iFood | E62: Banco Principal | F62: Pix | G62: 0 | J62: 2026-03 | K62: -17521.92
A63: 46092 | B63: Leite | C63: Saída | D63: Matéria Prima | E63: Caixa | F63: Dinheiro | G63: 188 | J63: 2026-03 | K63: -17709.92
A64: 46093 | B64: Plaquinhas | C64: Saída | D64: Mat Consumo | E64: Banco Principal | F64: Pix | G64: 45 | J64: 2026-03 | K64: -17754.92
A65: 46094 | B65: Vendas | C65: Entrada | D65: Vendas | G65: 1029 | J65: 2026-03 | K65: -16680.92
A66: 46093 | B66: Vendas Ifood | C66: Entrada | D66: Vendas iFood | E66: Banco Principal | G66: 101.5 | J66: 2026-03 | K66: -16579.42
A67: 46093 | B67: Motoboy | C67: Saída | D67: iFood | E67: Banco Principal | F67: Pix | G67: 25 | J67: 2026-03 | K67: -16604.42
A68: 46093 | B68: Leite | C68: Saída | D68: Matéria Prima | E68: Caixa | F68: Dinheiro | G68: 0 | J68: 2026-03 | K68: -16604.42
A69: 46093 | B69: Boleto Unigra | C69: Saída | D69: Matéria Prima | E69: Banco Principal | G69: 1022.5 | J69: 2026-03 | K69: -17626.92
A70: 46093 | B70: Boleto Seguro de vida | C70: Saída | D70: Salário | E70: Banco Principal | G70: 72 | J70: 2026-03 | K70: -17698.92
A71: 46094 | B71: Vendas | C71: Entrada | D71: Vendas | G71: 1413 | J71: 2026-03 | K71: -16285.92
A72: 46066 | B72: Vendas Ifood | C72: Entrada | D72: Vendas iFood | E72: Banco Principal | G72: 39 | J72: 2026-02 | K72: -16246.92
A73: 46094 | B73: Motoboy | C73: Saída | D73: iFood | E73: Banco Principal | F73: Pix | G73: 18 | J73: 2026-03 | K73: -16264.92
A74: 46094 | B74: Leite | C74: Saída | D74: Matéria Prima | E74: Caixa | F74: Dinheiro | G74: 329 | J74: 2026-03 | K74: -16593.92
A75: 46095 | B75: Vendas | C75: Entrada | D75: Vendas | G75: 7378 | J75: 2026-03 | K75: -9215.92
A76: 46095 | B76: Vendas Ifood | C76: Entrada | D76: Vendas iFood | E76: Banco Principal | G76: 308.4 | J76: 2026-03 | K76: -8907.52
A77: 46095 | B77: Motoboy | C77: Saída | D77: iFood | E77: Banco Principal | F77: Pix | G77: 35 | J77: 2026-03 | K77: -8942.52
A78: 46096 | B78: Vendas | C78: Entrada | D78: Vendas | G78: 7131 | J78: 2026-03 | K78: -1811.52
A79: 46096 | B79: Vendas ifood | C79: Entrada | D79: Vendas iFood | E79: Banco Principal | G79: 507.5 | J79: 2026-03 | K79: -1304.02
A80: 46096 | B80: Motoboy | C80: Saída | D80: iFood | E80: Banco Principal | F80: Pix | G80: 89 | J80: 2026-03 | K80: -1393.02
A81: 46096 | B81: Leite | C81: Saída | D81: Matéria Prima | E81: Caixa | F81: Dinheiro | G81: 94 | J81: 2026-03 | K81: -1487.02
A82: 46097 | B82: Boleto Unigra | C82: Saída | D82: Matéria Prima | E82: Banco Principal | G82: 5051.91 | J82: 2026-03 | K82: -6538.93
A83: 46097 | B83: Boleto Odontológico | C83: Saída | D83: Salário | E83: Banco Principal | G83: 202.8 | J83: 2026-03 | K83: -6741.73
A84: 46097 | B84: Internet | C84: Saída | D84: CustoFixo | E84: Banco Principal | F84: Pix | G84: 99.9 | J84: 2026-03 | K84: -6841.63
A85: 46097 | B85: Leite | C85: Saída | D85: Matéria Prima | E85: Caixa | F85: Dinheiro | G85: 194 | J85: 2026-03 | K85: -7035.63
A86: 46097 | B86: Vendas | C86: Entrada | D86: Vendas | G86: 1352 | J86: 2026-03 | K86: -5683.63
A87: 46097 | B87: Vendas iFood | C87: Entrada | D87: Vendas iFood | E87: Banco Principal | G87: 114.3 | J87: 2026-03 | K87: -5569.33
A88: 46097 | B88: Motoboy | C88: Saída | D88: iFood | E88: Banco Principal | F88: Pix | G88: 27 | J88: 2026-03 | K88: -5596.33
A89: 46097 | B89: Arfrye | C89: Saída | D89: Mat Consumo | E89: Banco Principal | F89: Pix | G89: 189.91 | J89: 2026-03 | K89: -5786.24
A90: 46098 | B90: Vendas | C90: Entrada | D90: Vendas | G90: 2049 | J90: 2026-03 | K90: -3737.24
A91: 46098 | B91: Vendas Ifood | C91: Entrada | D91: Vendas iFood | E91: Banco Principal | G91: 73.1 | J91: 2026-03 | K91: -3664.14
A92: 46098 | B92: Motoboy | C92: Saída | D92: iFood | E92: Banco Principal | F92: Pix | G92: 25 | J92: 2026-03 | K92: -3689.14
A93: 46098 | B93: Leite | C93: Saída | D93: Matéria Prima | E93: Caixa | F93: Dinheiro | G93: 94 | J93: 2026-03 | K93: -3783.14
A94: 46098 | B94: Boleto Unigra | C94: Saída | D94: Matéria Prima | E94: Banco Principal | G94: 883.32 | J94: 2026-03 | K94: -4666.46
A95: 46098 | B95: Boleto Riber | C95: Saída | D95: Matéria Prima | E95: Banco Principal | G95: 2521.74 | J95: 2026-03 | K95: -7188.2
A96: 46098 | B96: Filtro água | C96: Saída | D96: Manutenção | E96: Banco Principal | F96: Pix | G96: 50 | J96: 2026-03 | K96: -7238.2
A97: 46099 | B97: Boleto Ecila | C97: Saída | D97: Matéria Prima | E97: Banco Principal | G97: 650 | J97: 2026-03 | K97: -7888.2
A98: 46099 | B98: Boleto Morangos | C98: Saída | D98: Matéria Prima | E98: Banco Principal | G98: 278 | J98: 2026-03 | K98: -8166.2
A99: 46099 | B99: Leite | C99: Saída | D99: Matéria Prima | E99: Caixa | F99: Dinheiro | G99: 141 | J99: 2026-03 | K99: -8307.2
A100: 46099 | B100: Vendas | C100: Entrada | D100: Vendas | G100: 1267 | J100: 2026-03 | K100: -7040.2
...

Sheet ABR_26
A1: Data | B1: Descrição | C1: Tipo | D1: Categoria | E1: Conta | F1: Forma de pagamento | G1: Valor | I1: Obs | J1: Mês | K1: Saldo acumulado
A2: 46113 | B2: Vendas | C2: Entrada | D2: Vendas | G2: 3280 | J2: 2026-04 | K2: 3280
A3: 46113 | B3: Vendas Ifood | C3: Entrada | D3: Vendas iFood | E3: Banco Principal | G3: 173.6 | J3: 2026-04 | K3: 3453.6
A4: 46113 | B4: Motoboy | C4: Saída | D4: iFood | E4: Banco Principal | F4: Pix | G4: 35 | J4: 2026-04 | K4: 3418.6
A5: 46113 | B5: Leite | C5: Saída | D5: Matéria Prima | E5: Caixa | F5: Dinheiro | G5: 188 | J5: 2026-04 | K5: 3230.6
A6: 46113 | B6: Hora extra Luany | C6: Saída | D6: Freelancer | E6: Caixa | F6: Dinheiro | G6: 15 | J6: 2026-04 | K6: 3215.6
A7: 46114 | B7: Boleto Diniz | C7: Saída | D7: Matéria Prima | E7: Banco Principal | G7: 484.05 | J7: 2026-04 | K7: 2731.55
A8: 46114 | B8: Vendas | C8: Entrada | D8: Vendas | G8: 5110 | J8: 2026-04 | K8: 7841.55
A9: 46114 | B9: Vendas Ifood | C9: Entrada | D9: Vendas iFood | E9: Banco Principal | G9: 97.5 | J9: 2026-04 | K9: 7939.05
A10: 46114 | B10: Motoboy | C10: Saída | D10: iFood | E10: Banco Principal | F10: Pix | G10: 27 | J10: 2026-04 | K10: 7912.05
A11: 46114 | B11: Leite | C11: Saída | D11: Matéria Prima | E11: Caixa | F11: Dinheiro | G11: 0 | J11: 2026-04 | K11: 7912.05
A12: 46115 | B12: Vendas | C12: Entrada | D12: Vendas | G12: 7846 | J12: 2026-04 | K12: 15758.05
A13: 46115 | B13: Vendas Ifood | C13: Entrada | D13: Vendas iFood | E13: Banco Principal | G13: 219.1 | J13: 2026-04 | K13: 15977.15
A14: 46115 | B14: Motoboy | C14: Saída | D14: iFood | E14: Banco Principal | F14: Pix | G14: 36 | J14: 2026-04 | K14: 15941.15
A15: 46115 | B15: Leite | C15: Saída | D15: Matéria Prima | E15: Caixa | F15: Dinheiro | G15: 376 | J15: 2026-04 | K15: 15565.15
A16: 46116 | B16: Vendas | C16: Entrada | D16: Vendas | G16: 9776 | J16: 2026-04 | K16: 25341.15
A17: 46117 | B17: Vendas Ifood | C17: Entrada | D17: Vendas iFood | E17: Banco Principal | G17: 58.5 | J17: 2026-04 | K17: 25399.65
A18: 46118 | B18: Motoboy | C18: Saída | D18: iFood | E18: Banco Principal | F18: Pix | G18: 9 | J18: 2026-04 | K18: 25390.65
A19: 46119 | B19: Ovinhos meninas | C19: Saída | D19: Mat Consumo | E19: Caixa | F19: Dinheiro | G19: 132 | J19: 2026-04 | K19: 25258.65
A20: 46117 | B20: Vendas | C20: Entrada | D20: Vendas | G20: 5201 | J20: 2026-04 | K20: 30459.65
A21: 46117 | B21: Vendas Ifood | C21: Entrada | D21: Vendas iFood | E21: Banco Principal | G21: 123.3 | J21: 2026-04 | K21: 30582.95
A22: 46117 | B22: Motoboy | C22: Saída | D22: iFood | E22: Banco Principal | F22: Pix | G22: 27 | J22: 2026-04 | K22: 30555.95
A23: 46117 | B23: Leite | C23: Saída | D23: Matéria Prima | E23: Caixa | F23: Dinheiro | G23: 94 | J23: 2026-04 | K23: 30461.95
A24: 46118 | B24: Vendas | C24: Entrada | D24: Vendas | G24: 1472 | J24: 2026-04 | K24: 31933.95
A25: 46118 | B25: Vendas Ifood | C25: Entrada | D25: Vendas iFood | E25: Banco Principal | G25: 0 | J25: 2026-04 | K25: 31933.95
A26: 46118 | B26: Motoboy | C26: Saída | D26: iFood | E26: Banco Principal | F26: Pix | G26: 0 | J26: 2026-04 | K26: 31933.95
A27: 46118 | B27: Leite | C27: Saída | D27: Matéria Prima | E27: Caixa | F27: Dinheiro | G27: 0 | J27: 2026-04 | K27: 31933.95
A28: 46118 | B28: Aluguel | C28: Saída | D28: CustoFixo | E28: Banco Principal | G28: 8918.64 | J28: 2026-04 | K28: 23015.31
A29: 46118 | B29: IPTU | C29: Saída | D29: CustoFixo | E29: Banco Principal | F29: Pix | G29: 94.6 | J29: 2026-04 | K29: 22920.71
A30: 46118 | B30: Alarme | C30: Saída | D30: CustoFixo | E30: Banco Principal | G30: 100 | J30: 2026-04 | K30: 22820.71
A31: 46118 | B31: Pagamento Tais | C31: Saída | D31: Salário | E31: Banco Principal | F31: Pix | G31: 4000 | J31: 2026-04 | K31: 18820.71
A32: 46118 | B32: Boleto Riber | C32: Saída | D32: Matéria Prima | E32: Banco Principal | G32: 1074 | J32: 2026-04 | K32: 17746.71
A33: 46118 | B33: Boleto Riber | C33: Saída | D33: Matéria Prima | E33: Banco Principal | G33: 1708.78 | J33: 2026-04 | K33: 16037.93
A34: 46118 | B34: Boleto Diniz | C34: Saída | D34: Matéria Prima | E34: Banco Principal | G34: 399.72 | J34: 2026-04 | K34: 15638.21
A35: 46118 | B35: Boleto guardanapos | C35: Saída | D35: Mat Consumo | E35: Banco Principal | G35: 537 | J35: 2026-04 | K35: 15101.21
A36: 46118 | B36: Pagamentos funcionários | C36: Saída | D36: Salário | E36: Banco Principal | F36: Pix | G36: 7577.16 | J36: 2026-04 | K36: 7524.05
A37: 46119 | B37: Vendas | C37: Entrada | D37: Vendas | G37: 1634 | J37: 2026-04 | K37: 9158.05
A38: 46119 | B38: Vendas ifood | C38: Entrada | D38: Vendas iFood | E38: Banco Principal | G38: 0 | J38: 2026-04 | K38: 9158.05
A39: 46119 | B39: Motoboy | C39: Saída | D39: iFood | E39: Banco Principal | F39: Pix | G39: 0 | J39: 2026-04 | K39: 9158.05
A40: 46120 | B40: Castanhas promo | C40: Saída | D40: Matéria Prima | E40: Banco Principal | F40: Pix | G40: 689.25 | J40: 2026-04 | K40: 8468.8
A41: 46120 | B41: Boleto Ecila | C41: Saída | D41: Matéria Prima | E41: Banco Principal | G41: 755 | J41: 2026-04 | K41: 7713.8
A42: 46120 | B42: Vendas | C42: Entrada | D42: Vendas | G42: 901 | J42: 2026-04 | K42: 8614.8
A43: 46120 | B43: Vendas ifood | C43: Entrada | D43: Vendas iFood | E43: Banco Principal | G43: 66.6 | J43: 2026-04 | K43: 8681.4
A44: 46120 | B44: Motoboy | C44: Saída | D44: iFood | E44: Banco Principal | F44: Pix | G44: 9 | J44: 2026-04 | K44: 8672.4
A45: 46120 | B45: Leite | C45: Saída | D45: Matéria Prima | E45: Caixa | F45: Dinheiro | G45: 0 | J45: 2026-04 | K45: 8672.4
A46: 46121 | B46: Exame Demissional | C46: Saída | D46: Demissão | E46: Banco Principal | F46: Pix | G46: 45 | J46: 2026-04 | K46: 8627.4
A47: 46121 | B47: Vendas | C47: Entrada | D47: Vendas | G47: 1609 | J47: 2026-04 | K47: 10236.4
A48: 46121 | B48: Vendas ifood | C48: Entrada | D48: Vendas iFood | E48: Banco Principal | G48: 56.6 | J48: 2026-04 | K48: 10293
A49: 46121 | B49: Motoboy | C49: Saída | D49: iFood | E49: Banco Principal | F49: Pix | G49: 17 | J49: 2026-04 | K49: 10276
A50: 46121 | B50: Leite | C50: Saída | D50: Matéria Prima | E50: Caixa | F50: Dinheiro | G50: 188 | J50: 2026-04 | K50: 10088
A51: 46121 | B51: Mel | C51: Saída | D51: Matéria Prima | E51: Banco Principal | F51: Pix | G51: 76.5 | J51: 2026-04 | K51: 10011.5
A52: 46122 | B52: Royalt | C52: Saída | D52: Royalt | E52: Banco Principal | F52: Pix | G52: 6853.92 | J52: 2026-04 | K52: 3157.58
A53: 46122 | B53: Marketing | C53: Saída | D53: Marketing | E53: Banco Principal | F53: Pix | G53: 450 | J53: 2026-04 | K53: 2707.58
A54: 46122 | B54: Vendas | C54: Entrada | D54: Vendas | G54: 2047 | J54: 2026-04 | K54: 4754.58
A55: 46122 | B55: Vendas ifood | C55: Entrada | D55: Vendas iFood | E55: Banco Principal | G55: 0 | J55: 2026-04 | K55: 4754.58
A56: 46122 | B56: Motoboy | C56: Saída | D56: iFood | E56: Banco Principal | F56: Pix | G56: 0 | J56: 2026-04 | K56: 4754.58
A57: 46122 | B57: Leite | C57: Saída | D57: Matéria Prima | E57: Banco Principal | F57: Dinheiro | G57: 376 | J57: 2026-04 | K57: 4378.58
A58: 46121 | B58: Café | C58: Saída | D58: Matéria Prima | E58: Banco Principal | F58: Pix | G58: 700 | J58: 2026-04 | K58: 3678.58
A59: 46122 | B59: Boleto Seguro de vida | C59: Saída | D59: Salário | E59: Banco Principal | G59: 72 | J59: 2026-04 | K59: 3606.58
A60: 46123 | B60: Vendas | C60: Entrada | D60: Vendas | G60: 7406 | J60: 2026-04 | K60: 11012.58
A61: 46123 | B61: Vendas iFood | C61: Entrada | D61: Vendas iFood | E61: Banco Principal | G61: 230.6 | J61: 2026-04 | K61: 11243.18
A62: 46123 | B62: Motoboy | C62: Saída | D62: iFood | E62: Banco Principal | F62: Pix | G62: 0 | J62: 2026-04 | K62: 11243.18
A63: 46124 | B63: Vendas | C63: Entrada | D63: Vendas | G63: 6658 | J63: 2026-04 | K63: 17901.18
A64: 46124 | B64: Vendas iFood | C64: Entrada | D64: Vendas iFood | E64: Banco Principal | G64: 143.4 | J64: 2026-04 | K64: 18044.58
A65: 46124 | B65: Motoboy | C65: Saída | D65: iFood | E65: Banco Principal | F65: Pix | G65: 18 | J65: 2026-04 | K65: 18026.58
A66: 46125 | B66: Vendas | C66: Entrada | D66: Vendas | G66: 1315 | J66: 2026-04 | K66: 19341.58
A67: 46125 | B67: Vendas iFood | C67: Entrada | D67: Vendas iFood | E67: Banco Principal | G67: 19.5 | J67: 2026-04 | K67: 19361.08
A68: 46125 | B68: Motoboy | C68: Saída | D68: iFood | E68: Banco Principal | F68: Pix | G68: 0 | J68: 2026-04 | K68: 19361.08
A69: 46125 | B69: Boleto Unigra | C69: Saída | D69: Matéria Prima | E69: Banco Principal | G69: 1022.5 | J69: 2026-04 | K69: 18338.58
A70: 46125 | B70: Boleto Unigra | C70: Saída | D70: Matéria Prima | E70: Banco Principal | G70: 5052.07 | J70: 2026-04 | K70: 13286.51
A71: 46125 | B71: Creme de leite de caixinha | C71: Saída | D71: Matéria Prima | E71: Banco Principal | F71: Pix | G71: 213.84 | J71: 2026-04 | K71: 13072.67
A72: 46125 | B72: Boleto castanhas | C72: Saída | D72: Matéria Prima | E72: Banco Principal | G72: 850.5 | J72: 2026-04 | K72: 12222.17
A73: 46125 | B73: Bodevan | C73: Saída | D73: Mat Consumo | E73: Banco Principal | F73: Pix | G73: 183.87 | J73: 2026-04 | K73: 12038.3
A74: 46126 | B74: Copinhos | C74: Saída | D74: Mat Consumo | E74: Banco Principal | F74: Pix | G74: 1800 | J74: 2026-04 | K74: 10238.3
A75: 46126 | B75: Boleto Riber | C75: Saída | D75: Matéria Prima | E75: Banco Principal | G75: 1708.19 | J75: 2026-04 | K75: 8530.11
A76: 46126 | B76: Vendas | C76: Entrada | D76: Vendas | G76: 1926 | J76: 2026-04 | K76: 10456.11
A77: 46126 | B77: Vendas iFood | C77: Entrada | D77: Vendas iFood | E77: Banco Principal | G77: 39 | J77: 2026-04 | K77: 10495.11
A78: 46126 | B78: Motoboy | C78: Saída | D78: iFood | E78: Banco Principal | F78: Pix | G78: 8 | J78: 2026-04 | K78: 10487.11
A79: 46126 | B79: Leite | C79: Entrada | D79: Matéria Prima | E79: Caixa | F79: Dinheiro | G79: 0 | J79: 2026-04 | K79: 10487.11
A80: 46127 | B80: Boleto Odonto | C80: Saída | D80: Salário | E80: Banco Principal | G80: 216 | J80: 2026-04 | K80: 10271.11
A81: 46127 | B81: Contabilidade | C81: Saída | D81: Contabilidade | E81: Banco Principal | G81: 800 | J81: 2026-04 | K81: 9471.11
A82: 46127 | B82: Boleto Diniz | C82: Saída | D82: Matéria Prima | E82: Banco Principal | G82: 255.67 | J82: 2026-04 | K82: 9215.44
A83: 46127 | B83: Vendas | C83: Entrada | D83: Vendas | G83: 1863 | J83: 2026-04 | K83: 11078.44
A84: 46127 | B84: Vendas iFood | C84: Entrada | D84: Vendas iFood | E84: Banco Principal | G84: 0 | J84: 2026-04 | K84: 11078.44
A85: 46127 | B85: Motoboy | C85: Saída | D85: iFood | E85: Banco Principal | F85: Pix | G85: 0 | J85: 2026-04 | K85: 11078.44
A86: 46127 | B86: Leite | C86: Saída | D86: Matéria Prima | E86: Caixa | F86: Dinheiro | G86: 188 | J86: 2026-04 | K86: 10890.44
A87: 46127 | B87: Paçoca zero açúcar | C87: Saída | D87: Matéria Prima | E87: Banco Principal | F87: Pix | G87: 64.8 | J87: 2026-04 | K87: 10825.64
A88: 46128 | B88: Vendas | C88: Entrada | D88: Vendas | G88: 1863 | J88: 2026-04 | K88: 12688.64
A89: 46128 | B89: Vendas iFood | C89: Entrada | D89: Vendas iFood | E89: Banco Principal | G89: 0 | J89: 2026-04 | K89: 12688.64
A90: 46128 | B90: Motoboy | C90: Saída | D90: iFood | E90: Banco Principal | F90: Pix | G90: 0 | J90: 2026-04 | K90: 12688.64
A91: 46128 | B91: Leite | C91: Saída | D91: Matéria Prima | E91: Caixa | F91: Dinheiro | G91: 235 | J91: 2026-04 | K91: 12453.64
A92: 46128 | B92: Internet | C92: Saída | D92: CustoFixo | E92: Banco Principal | F92: Pix | G92: 99.9 | J92: 2026-04 | K92: 12353.74
A93: 46128 | B93: Demissão Rafaela | C93: Saída | D93: Demissão | E93: Banco Principal | F93: Pix | G93: 1140.28 | J93: 2026-04 | K93: 11213.46
A94: 46128 | B94: Água | C94: Saída | D94: Matéria Prima | E94: Banco Principal | F94: Pix | G94: 382.5 | J94: 2026-04 | K94: 10830.96
A95: 46128 | B95: Frete copinhos | C95: Saída | D95: Frete | E95: Banco Principal | F95: Pix | G95: 218.41 | J95: 2026-04 | K95: 10612.55
A96: 46128 | B96: FOLGA LUANY | C96: Saída | D96: Freelancer | E96: Banco Principal | F96: Pix | G96: 150 | J96: 2026-04 | K96: 10462.55
A97: 46129 | B97: Vendas | C97: Entrada | D97: Vendas | G97: 3477 | J97: 2026-04 | K97: 13939.55
A98: 46129 | B98: Vendas iFood | C98: Entrada | D98: Vendas iFood | E98: Banco Principal | G98: 48.6 | J98: 2026-04 | K98: 13988.15
A99: 46129 | B99: Motoboy | C99: Saída | D99: iFood | E99: Banco Principal | F99: Pix | G99: 0 | J99: 2026-04 | K99: 13988.15
A100: 46129 | B100: Leite | C100: Saída | D100: Matéria Prima | E100: Caixa | F100: Dinheiro | G100: 376 | J100: 2026-04 | K100: 13612.15
...

Sheet MAIO_26
A2: 46143 | B2: Leite | C2: Saída | D2: Matéria Prima | E2: Caixa | F2: Dinheiro | G2: 476 | J2: 2026-05 | K2: 476
A3: 46143 | B3: Vendas | C3: Entrada | D3: Vendas | G3: 9578 | J3: 2026-05 | K3: 10054
A4: 46143 | B4: Vendas Ifood | C4: Entrada | D4: Vendas iFood | E4: Banco Principal | G4: 574 | J4: 2026-05 | K4: 10628
A5: 46143 | B5: Motoboy | C5: Saída | D5: iFood | E5: Banco Principal | F5: Pix | G5: 53 | J5: 2026-05 | K5: 10575
A6: 46144 | B6: Freelancer | C6: Saída | D6: Freelancer | E6: Caixa | F6: Dinheiro | G6: 150 | J6: 2026-05 | K6: 10425
A7: 46144 | B7: VEndas | C7: Entrada | D7: Vendas | G7: 10116 | J7: 2026-05 | K7: 20541
A8: 46144 | B8: Vendas Ifood | C8: Entrada | D8: Vendas iFood | E8: Banco Principal | G8: 55 | J8: 2026-05 | K8: 20596
A9: 46144 | B9: Motoboy | C9: Saída | D9: iFood | E9: Banco Principal | F9: Pix | G9: 9 | J9: 2026-05 | K9: 20587
A10: 46145 | B10: Freelancer | C10: Saída | D10: Freelancer | E10: Caixa | F10: Dinheiro | G10: 150 | J10: 2026-05 | K10: 20437
A11: 46145 | B11: Vendas | C11: Entrada | D11: Vendas | G11: 6795 | J11: 2026-05 | K11: 27232
A12: 46145 | B12: Vendas Ifood | C12: Entrada | D12: Vendas iFood | E12: Banco Principal | G12: 354 | J12: 2026-05 | K12: 27586
A13: 46145 | B13: Motoboy | C13: Saída | D13: iFood | E13: Banco Principal | F13: Pix | G13: 41 | J13: 2026-05 | K13: 27545
A14: 46144 | B14: Diferenca caixa | C14: Saída | D14: Manutenção | E14: Caixa | F14: Dinheiro | G14: 102 | J14: 2026-05 | K14: 27443
A15: 46146 | B15: Creme de leite | C15: Saída | D15: Matéria Prima | E15: Banco Principal | F15: Pix | G15: 709.75 | J15: 2026-05 | K15: 26733.25
A16: 46146 | B16: Riber | C16: Saída | D16: Matéria Prima | E16: Banco Principal | G16: 1029.4 | J16: 2026-05 | K16: 25703.85
A17: 46146 | B17: Riber | C17: Saída | D17: Matéria Prima | E17: Banco Principal | G17: 156.7 | J17: 2026-05 | K17: 25547.15
A18: 46146 | B18: Riber | C18: Saída | D18: Matéria Prima | E18: Banco Principal | G18: 564.36 | J18: 2026-05 | K18: 24982.79
A19: 46146 | B19: Aluguel | C19: Saída | D19: CustoFixo | E19: Banco Principal | G19: 8918.64 | J19: 2026-05 | K19: 16064.15
A20: 46146 | B20: IPTU | C20: Saída | D20: CustoFixo | E20: Banco Principal | F20: Pix | G20: 94.9 | J20: 2026-05 | K20: 15969.25
A21: 46146 | B21: Alarme | C21: Saída | D21: CustoFixo | E21: Banco Principal | G21: 100 | J21: 2026-05 | K21: 15869.25
A22: 46146 | B22: Luz e água mês março | C22: Saída | D22: CustoFixo | E22: Caixa | F22: Dinheiro | G22: 2836.54 | J22: 2026-05 | K22: 13032.71
A23: 46146 | B23: Morango | C23: Saída | D23: Matéria Prima | E23: Banco Principal | G23: 278 | J23: 2026-05 | K23: 12754.71
A24: 46146 | B24: Vendas | C24: Entrada | D24: Vendas | G24: 1145 | J24: 2026-05 | K24: 13899.71
A25: 46146 | B25: Vendas iFood | C25: Entrada | D25: Vendas iFood | E25: Banco Principal | G25: 0 | J25: 2026-05 | K25: 13899.71
A26: 46146 | B26: Motoboy | C26: Saída | D26: iFood | E26: Banco Principal | F26: Pix | G26: 0 | J26: 2026-05 | K26: 13899.71
A27: 46146 | B27: Leite | C27: Saída | D27: Matéria Prima | E27: Caixa | F27: Dinheiro | G27: 0 | J27: 2026-05 | K27: 13899.71
A28: 46147 | B28: Dedetização | C28: Saída | D28: CustoFixo | E28: Banco Principal | F28: Pix | G28: 150 | J28: 2026-05 | K28: 13749.71
A29: 46147 | B29: Impressos | C29: Saída | D29: Mat Consumo | E29: Banco Principal | F29: Pix | G29: 210 | J29: 2026-05 | K29: 13539.71
A30: 46147 | B30: Vendas | C30: Entrada | D30: Vendas | G30: 1471 | J30: 2026-05 | K30: 15010.71
A31: 46147 | B31: Vendas Ifood | C31: Entrada | D31: Vendas iFood | E31: Banco Principal | G31: 84 | J31: 2026-05 | K31: 15094.71
A32: 46147 | B32: Motoboy | C32: Entrada | D32: iFood | E32: Banco Principal | F32: Pix | G32: 27 | J32: 2026-05 | K32: 15121.71
A33: 46147 | B33: Chocolate Blend | C33: Saída | D33: Matéria Prima | E33: Banco Principal | F33: Pix | G33: 3357.6 | J33: 2026-05 | K33: 11764.11
A34: 46148 | B34: Salários | C34: Saída | D34: Salário | E34: Banco Principal | F34: Pix | G34: 9846.01 | J34: 2026-05 | K34: 1918.1
A35: 46148 | B35: 1/3 férias Tais | C35: Saída | D35: Salário | E35: Banco Principal | F35: Pix | G35: 1666.67 | J35: 2026-05 | K35: 251.43
A36: 46148 | B36: Vendas | C36: Entrada | D36: Vendas | G36: 1514 | J36: 2026-05 | K36: 1765.43
A37: 46148 | B37: Vendas iFood | C37: Entrada | D37: Vendas iFood | E37: Banco Principal | G37: 0 | J37: 2026-05 | K37: 1765.43
A38: 46148 | B38: Motoboy | C38: Saída | D38: iFood | E38: Banco Principal | F38: Pix | G38: 0 | J38: 2026-05 | K38: 1765.43
A39: 46148 | B39: Leite | C39: Saída | D39: Matéria Prima | E39: Caixa | F39: Dinheiro | G39: 235 | J39: 2026-05 | K39: 1530.43
A40: 46148 | B40: Salário Tais | C40: Saída | D40: Salário | E40: Banco Principal | F40: Pix | G40: 2000 | J40: 2026-05 | K40: -469.57
A41: 46148 | B41: Cubas | C41: Saída | D41: Salário | E41: Banco Principal | F41: Pix | G41: 279 | J41: 2026-05 | K41: -748.57
A42: 46149 | B42: Vendas | C42: Entrada | D42: Vendas | G42: 1466 | J42: 2026-05 | K42: 717.43
A43: 46149 | B43: VEndas Ifood | C43: Entrada | D43: Vendas iFood | E43: Banco Principal | G43: 0 | J43: 2026-05 | K43: 717.43
A44: 46149 | B44: Motoboy | C44: Saída | D44: iFood | E44: Banco Principal | F44: Pix | G44: 0 | J44: 2026-05 | K44: 717.43
A45: 46149 | B45: Leite | C45: Saída | D45: Matéria Prima | E45: Caixa | F45: Dinheiro | G45: 235 | J45: 2026-05 | K45: 482.43
A46: 46149 | B46: Boleto Diniz | C46: Saída | D46: Matéria Prima | E46: Banco Principal | G46: 600.69 | J46: 2026-05 | K46: -118.26
A47: 46149 | B47: Plano odontológico mês 02 | C47: Saída | D47: Salário | E47: Banco Principal | F47: Pix | G47: 176.94 | J47: 2026-05 | K47: -295.2
A48: 46150 | B48: Vendas | C48: Entrada | D48: Vendas | G48: 3340 | J48: 2026-05 | K48: 3044.8
A49: 46150 | B49: VEndas Ifood | C49: Entrada | D49: Vendas iFood | E49: Banco Principal | G49: 345 | J49: 2026-05 | K49: 3389.8
A50: 46150 | B50: Motoboy | C50: Saída | D50: iFood | E50: Banco Principal | F50: Pix | G50: 45 | J50: 2026-05 | K50: 3344.8
A51: 46150 | B51: Leite | C51: Saída | D51: Matéria Prima | E51: Caixa | F51: Dinheiro | G51: 376 | J51: 2026-05 | K51: 2968.8
A52: 46151 | B52: Vendas | C52: Entrada | D52: Vendas | G52: 8628 | J52: 2026-05 | K52: 11596.8
A53: 46151 | B53: Vendas iFood | C53: Entrada | D53: Vendas iFood | E53: Banco Principal | G53: 382 | J53: 2026-05 | K53: 11978.8
A54: 46151 | B54: Motoboy | C54: Saída | D54: iFood | E54: Banco Principal | F54: Pix | G54: 46 | J54: 2026-05 | K54: 11932.8
A55: 46152 | B55: Vendas | C55: Entrada | D55: Vendas | G55: 11713 | J55: 2026-05 | K55: 23645.8
A56: 46152 | B56: Vendas iFood | C56: Entrada | D56: Vendas iFood | E56: Banco Principal | G56: 301 | J56: 2026-05 | K56: 23946.8
A57: 46152 | B57: Motoboy | C57: Saída | D57: iFood | E57: Banco Principal | F57: Pix | G57: 45 | J57: 2026-05 | K57: 23901.8
A58: 46152 | B58: Leite | C58: Saída | D58: Matéria Prima | E58: Caixa | F58: Dinheiro | G58: 188 | J58: 2026-05 | K58: 23713.8
A59: 46153 | B59: Vendas | C59: Entrada | D59: Vendas | G59: 1024 | J59: 2026-05 | K59: 24737.8
A60: 46153 | B60: Vendas iFood | C60: Entrada | D60: Vendas iFood | E60: Banco Principal | G60: 42 | J60: 2026-05 | K60: 24779.8
A61: 46153 | B61: Motoboy | C61: Saída | D61: iFood | E61: Banco Principal | F61: Pix | G61: 17 | J61: 2026-05 | K61: 24762.8
A62: 46153 | B62: Leite | C62: Saída | D62: Matéria Prima | E62: Caixa | F62: Dinheiro | G62: 0 | J62: 2026-05 | K62: 24762.8
A63: 46153 | B63: Royalt | C63: Saída | D63: Royalt | E63: Banco Principal | F63: Pix | G63: 7834.23 | J63: 2026-05 | K63: 16928.57
A64: 46153 | B64: Marketing | C64: Saída | D64: Marketing | E64: Banco Principal | F64: Pix | G64: 450 | J64: 2026-05 | K64: 16478.57
A65: 46153 | B65: Seguro de vida | C65: Saída | D65: Salário | E65: Banco Principal | G65: 72 | J65: 2026-05 | K65: 16406.57
A66: 46153 | B66: Boleto Unigra | C66: Saída | D66: Matéria Prima | E66: Banco Principal | G66: 1022.53 | J66: 2026-05 | K66: 15384.04
A67: 46153 | B67: Boleto mec 3 | C67: Saída | D67: Matéria Prima | E67: Banco Principal | G67: 1734.28 | J67: 2026-05 | K67: 13649.76
A68: 46153 | B68: Boleto polar | C68: Saída | D68: Matéria Prima | E68: Banco Principal | G68: 211.23 | J68: 2026-05 | K68: 13438.53
A69: 46153 | B69: Boleto polar | C69: Saída | D69: Matéria Prima | E69: Banco Principal | G69: 66.73 | J69: 2026-05 | K69: 13371.8
A70: 46153 | B70: Recisao Rafaela | C70: Saída | D70: Demissão | E70: Banco Principal | F70: Pix | G70: 467.25 | J70: 2026-05 | K70: 12904.55
A71: 46154 | B71: Vendas | C71: Entrada | D71: Vendas | G71: 1036 | J71: 2026-05 | K71: 13940.55
A72: 46154 | B72: Vendas Ifood | C72: Entrada | D72: Vendas iFood | E72: Banco Principal | G72: 40 | J72: 2026-05 | K72: 13980.55
A73: 46154 | B73: Motoboy | C73: Saída | D73: iFood | E73: Banco Principal | F73: Pix | G73: 9 | J73: 2026-05 | K73: 13971.55
A74: 46154 | B74: Leite | C74: Saída | D74: Matéria Prima | E74: Caixa | F74: Dinheiro | G74: 141 | J74: 2026-05 | K74: 13830.55
A75: 46154 | B75: Boleto Riber | C75: Saída | D75: Matéria Prima | E75: Banco Principal | G75: 564.37 | J75: 2026-05 | K75: 13266.18
A76: 46154 | B76: Boleto Riber | C76: Saída | D76: Matéria Prima | E76: Banco Principal | G76: 156.7 | J76: 2026-05 | K76: 13109.48
A77: 46154 | B77: Boleto Diniz | C77: Saída | D77: Matéria Prima | E77: Banco Principal | G77: 1977.87 | J77: 2026-05 | K77: 11131.61
A78: 46154 | B78: Plaquinha sabor | C78: Saída | D78: Mat Consumo | E78: Banco Principal | F78: Pix | G78: 15 | J78: 2026-05 | K78: 11116.61
A79: 46154 | B79: Frete Guardanapos | C79: Saída | D79: Frete | E79: Banco Principal | F79: Pix | G79: 438.4 | J79: 2026-05 | K79: 10678.21
A80: 46155 | B80: Vendas | C80: Entrada | D80: Vendas | G80: 1271 | J80: 2026-05 | K80: 11949.21
A81: 46155 | B81: Vendas Ifood | C81: Entrada | D81: Vendas iFood | E81: Banco Principal | G81: 0 | J81: 2026-05 | K81: 11949.21
A82: 46155 | B82: Motoboy | C82: Saída | D82: iFood | E82: Banco Principal | F82: Pix | G82: 0 | J82: 2026-05 | K82: 11949.21
A83: 46155 | B83: Leite | C83: Saída | D83: Matéria Prima | E83: Caixa | F83: Dinheiro | G83: 188 | J83: 2026-05 | K83: 11761.21
A84: 46155 | B84: Carrossel | C84: Saída | D84: Mat Consumo | E84: Banco Principal | F84: Pix | G84: 71.96 | J84: 2026-05 | K84: 11689.25
A85: 46156 | B85: Vendas | C85: Entrada | D85: Vendas | G85: 1558 | J85: 2026-05 | K85: 13247.25
A86: 46156 | B86: Venda Ifood | C86: Entrada | D86: Vendas iFood | E86: Banco Principal | G86: 0 | J86: 2026-05 | K86: 13247.25
A87: 46156 | B87: Motoboy | C87: Saída | D87: iFood | E87: Banco Principal | F87: Pix | G87: 0 | J87: 2026-05 | K87: 13247.25
A88: 46156 | B88: Leite | C88: Saída | D88: Matéria Prima | E88: Caixa | F88: Dinheiro | G88: 235 | J88: 2026-05 | K88: 13012.25
A89: 46156 | B89: Boleto Andaluz | C89: Saída | D89: Matéria Prima | E89: Banco Principal | G89: 1132.95 | J89: 2026-05 | K89: 11879.3
A90: 46156 | B90: Boleto Amoras | C90: Saída | D90: Matéria Prima | E90: Banco Principal | G90: 254.8 | J90: 2026-05 | K90: 11624.5
A91: 46156 | B91: Boleto Diniz | C91: Saída | D91: Matéria Prima | E91: Banco Principal | G91: 697.1 | J91: 2026-05 | K91: 10927.4
A92: 46156 | B92: Internet | C92: Saída | D92: CustoFixo | E92: Banco Principal | F92: Pix | G92: 99.9 | J92: 2026-05 | K92: 10827.5
A93: 46156 | B93: ICMS | C93: Saída | D93: Impostos | E93: Banco Principal | G93: 1046.2 | J93: 2026-05 | K93: 9781.3
A94: 46156 | B94: Odonto | C94: Saída | D94: Salário | E94: Banco Principal | G94: 216 | J94: 2026-05 | K94: 9565.3
A95: 46156 | B95: Contabilidade | C95: Saída | D95: Contabilidade | E95: Banco Principal | G95: 800 | J95: 2026-05 | K95: 8765.3
A96: 46157 | B96: Vendas | C96: Entrada | D96: Vendas | G96: 3419 | J96: 2026-05 | K96: 12184.3
A97: 46157 | B97: Vendas Ifood | C97: Entrada | D97: Vendas iFood | E97: Banco Principal | G97: 42 | J97: 2026-05 | K97: 12226.3
A98: 46157 | B98: Motoboy | C98: Saída | D98: iFood | E98: Banco Principal | F98: Pix | G98: 9 | J98: 2026-05 | K98: 12217.3
A99: 46157 | B99: Maracuja | C99: Saída | D99: Matéria Prima | E99: Banco Principal | F99: Pix | G99: 166 | J99: 2026-05 | K99: 12051.3
A100: 46157 | B100: Leite | C100: Saída | D100: Matéria Prima | E100: Caixa | F100: Dinheiro | G100: 329 | J100: 2026-05 | K100: 11722.3
A101: 46158 | B101: Vendas | C101: Entrada | D101: Vendas | G101: 9113 | J101: 2026-05 | K101: 20835.3
...

Sheet JUN_26
A1: Data | B1: Descrição | C1: Tipo | D1: Categoria | E1: Conta | F1: Forma de pagamento | G1: Valor | I1: Obs | J1: Mês | K1: Saldo acumulado
A2: 46174 | B2: Leite | C2: Saída | D2: Matéria Prima | E2: Caixa | F2: Dinheiro | G2: 235 | J2: 2026-06 | K2: =G2 -> 235
A3: 46174 | B3: Tortelli | C3: Saída | D3: Tortelli | E3: Banco Principal | G3: 13185 | J3: 2026-06 | K3: =K2 + IF(C3="Entrada", G3, -G3) -> -12950
A4: 46174 | B4: Unigra | C4: Saída | D4: Matéria Prima | E4: Banco Principal | G4: 4817.04 | J4: 2026-06 | K4: =K3 + IF(C4="Entrada", G4, -G4) -> -17767.04
A5: 46174 | B5: Sistema | C5: Saída | D5: CustoFixo | E5: Banco Principal | G5: 370 | J5: 2026-06 | K5: =K4 + IF(C5="Entrada", G5, -G5) -> -18137.04
A6: 46174 | B6: Tráfego pago | C6: Saída | D6: Marketing | E6: Banco Principal | F6: Pix | G6: 600 | J6: 2026-06 | K6: =K5 + IF(C6="Entrada", G6, -G6) -> -18737.04
A7: 46174 | B7: Vendas | C7: Entrada | D7: Vendas | G7: 454 | J7: 2026-06 | K7: =K6 + IF(C7="Entrada", G7, -G7) -> -18283.04
A8: 46174 | B8: Vendas iFood | C8: Entrada | D8: Vendas iFood | E8: Banco Principal | G8: 32 | J8: 2026-06 | K8: =K7 + IF(C8="Entrada", G8, -G8) -> -18251.04
A9: 46174 | B9: Motoboy | C9: Saída | D9: iFood | E9: Banco Principal | F9: Pix | G9: 13 | J9: 2026-06 | K9: =K8 + IF(C9="Entrada", G9, -G9) -> -18264.04
A10: 46175 | B10: Vendas | C10: Entrada | D10: Vendas | G10: 1001 | J10: 2026-06 | K10: =K9 + IF(C10="Entrada", G10, -G10) -> -17263.04
A11: 46175 | B11: Vendas Ifood | C11: Entrada | D11: Vendas iFood | E11: Banco Principal | G11: 0 | J11: 2026-06 | K11: =K10 + IF(C11="Entrada", G11, -G11) -> -17263.04
A12: 46175 | B12: Motoboy | C12: Saída | D12: iFood | E12: Banco Principal | F12: Pix | G12: 0 | J12: 2026-06 | K12: =K11 + IF(C12="Entrada", G12, -G12) -> -17263.04
A13: 46175 | B13: Boleto Diniz | C13: Saída | D13: Matéria Prima | E13: Banco Principal | G13: 182.54 | J13: 2026-06 | K13: =K12 + IF(C13="Entrada", G13, -G13) -> -17445.58
A14: 46175 | B14: Boleto Riber | C14: Saída | D14: Matéria Prima | E14: Banco Principal | G14: 477.68 | J14: 2026-06 | K14: =K13 + IF(C14="Entrada", G14, -G14) -> -17923.26
A15: 46175 | B15: Limão | C15: Saída | D15: Matéria Prima | E15: Banco Principal | F15: Pix | G15: 130 | J15: 2026-06 | K15: =K14 + IF(C15="Entrada", G15, -G15) -> -18053.26
A16: 46175 | B16: Paflo, lampada e cola | C16: Saída | D16: Manutenção | E16: Banco Principal | F16: Pix | G16: 50.7 | J16: 2026-06 | K16: =K15 + IF(C16="Entrada", G16, -G16) -> -18103.96
A17: 46175 | B17: Luany domingo adiantado | C17: Saída | D17: Freelancer | E17: Banco Principal | F17: Pix | G17: 150 | J17: 2026-06 | K17: =K16 + IF(C17="Entrada", G17, -G17) -> -18253.96
A18: 46176 | B18: Salário Tais | C18: Saída | D18: Salário | E18: Banco Principal | F18: Pix | G18: 5000 | J18: 2026-06 | K18: =K17 + IF(C18="Entrada", G18, -G18) -> -23253.96
A19: 46176 | B19: Boleto Ecila | C19: Saída | D19: Matéria Prima | E19: Banco Principal | G19: 115.8 | J19: 2026-06 | K19: =K18 + IF(C19="Entrada", G19, -G19) -> -23369.76
A20: 46176 | B20: Vendas | C20: Entrada | D20: Vendas | G20: 1413 | J20: 2026-06 | K20: =K19 + IF(C20="Entrada", G20, -G20) -> -21956.76
A21: 46176 | B21: Vendas iFood | C21: Entrada | D21: Vendas iFood | E21: Banco Principal | G21: 0 | J21: 2026-06 | K21: =K20 + IF(C21="Entrada", G21, -G21) -> -21956.76
A22: 46176 | B22: Motoboy | C22: Saída | D22: iFood | E22: Banco Principal | F22: Pix | G22: 0 | J22: 2026-06 | K22: =K21 + IF(C22="Entrada", G22, -G22) -> -21956.76
A23: 46177 | B23: Vendas | C23: Entrada | D23: Vendas | G23: 5165 | J23: 2026-06 | K23: =K22 + IF(C23="Entrada", G23, -G23) -> -16791.76
A24: 46177 | B24: Vendas Ifood | C24: Entrada | D24: Vendas iFood | E24: Banco Principal | G24: 0 | J24: 2026-06 | K24: =K23 + IF(C24="Entrada", G24, -G24) -> -16791.76
A25: 46177 | B25: Motoboy | C25: Saída | D25: iFood | E25: Banco Principal | F25: Pix | G25: 0 | J25: 2026-06 | K25: =K24 + IF(C25="Entrada", G25, -G25) -> -16791.76
A26: 46177 | B26: Leite | C26: Saída | D26: Matéria Prima | E26: Caixa | F26: Dinheiro | G26: 235 | J26: 2026-06 | K26: =K25 + IF(C26="Entrada", G26, -G26) -> -17026.76
A27: 46178 | B27: Vendas | C27: Entrada | D27: Vendas | G27: 6234 | J27: 2026-06 | K27: =K26 + IF(C27="Entrada", G27, -G27) -> -10792.76
A28: 46178 | B28: Vendas Ifood | C28: Entrada | D28: Vendas iFood | E28: Banco Principal | G28: 168 | J28: 2026-06 | K28: =K27 + IF(C28="Entrada", G28, -G28) -> -10624.76
A29: 46178 | B29: Motoboy | C29: Saída | D29: iFood | E29: Banco Principal | F29: Pix | G29: 35 | J29: 2026-06 | K29: =K28 + IF(C29="Entrada", G29, -G29) -> -10659.76
A30: 46178 | B30: Salarios | C30: Saída | D30: Salário | E30: Banco Principal | F30: Pix | G30: 6890.33 | J30: 2026-06 | K30: =K29 + IF(C30="Entrada", G30, -G30) -> -17550.09
A31: 46178 | B31: Aluguel | C31: Saída | D31: CustoFixo | E31: Banco Principal | G31: 8918.64 | J31: 2026-06 | K31: =K30 + IF(C31="Entrada", G31, -G31) -> -26468.73
A32: 46178 | B32: IPTU | C32: Saída | D32: CustoFixo | E32: Banco Principal | F32: Pix | G32: 94.9 | J32: 2026-06 | K32: =K31 + IF(C32="Entrada", G32, -G32) -> -26563.63
A33: 46178 | B33: Alarme | C33: Saída | D33: CustoFixo | E33: Banco Principal | G33: 100 | J33: 2026-06 | K33: =K32 + IF(C33="Entrada", G33, -G33) -> -26663.63
A34: 46178 | B34: Leite | C34: Saída | D34: Matéria Prima | E34: Caixa | F34: Dinheiro | G34: 329 | J34: 2026-06 | K34: =K33 + IF(C34="Entrada", G34, -G34) -> -26992.63
A35: 46178 | B35: Agua | C35: Saída | D35: Matéria Prima | E35: Banco Principal | F35: Pix | G35: 203.5 | J35: 2026-06 | K35: =K34 + IF(C35="Entrada", G35, -G35) -> -27196.13
A36: 46179 | B36: Vendas | C36: Entrada | D36: Vendas | G36: 6129 | J36: 2026-06 | K36: =K35 + IF(C36="Entrada", G36, -G36) -> -21067.13
A37: 46179 | B37: Vendas Ifood | C37: Entrada | D37: Vendas iFood | E37: Banco Principal | G37: 114 | J37: 2026-06 | K37: =K36 + IF(C37="Entrada", G37, -G37) -> -20953.13
A38: 46179 | B38: Motoboy | C38: Saída | D38: iFood | E38: Banco Principal | F38: Pix | G38: 9 | J38: 2026-06 | K38: =K37 + IF(C38="Entrada", G38, -G38) -> -20962.13
A39: 46179 | B39: Freelancer | C39: Saída | D39: Freelancer | E39: Caixa | F39: Dinheiro | G39: 150 | J39: 2026-06 | K39: =K38 + IF(C39="Entrada", G39, -G39) -> -21112.13
A40: 46180 | B40: Vendas | C40: Entrada | D40: Vendas | G40: 4783 | J40: 2026-06 | K40: =K39 + IF(C40="Entrada", G40, -G40) -> -16329.13
A41: 46180 | B41: Vendas Ifood | C41: Entrada | D41: Vendas iFood | E41: Banco Principal | G41: 99 | J41: 2026-06 | K41: =K40 + IF(C41="Entrada", G41, -G41) -> -16230.13
A42: 46180 | B42: Motoboy | C42: Saída | D42: iFood | E42: Banco Principal | F42: Pix | G42: 17 | J42: 2026-06 | K42: =K41 + IF(C42="Entrada", G42, -G42) -> -16247.13
A43: 46180 | B43: Freelancer | C43: Saída | D43: Freelancer | E43: Caixa | F43: Dinheiro | G43: 150 | J43: 2026-06 | K43: =K42 + IF(C43="Entrada", G43, -G43) -> -16397.13
A44: 46181 | B44: Vendas | C44: Entrada | D44: Vendas | G44: 924 | J44: 2026-06 | K44: =K43 + IF(C44="Entrada", G44, -G44) -> -15473.13
A45: 46181 | B45: Vendas Ifood | C45: Entrada | D45: Vendas iFood | E45: Banco Principal | G45: 0 | J45: 2026-06 | K45: =K44 + IF(C45="Entrada", G45, -G45) -> -15473.13
A46: 46181 | B46: Motoboy | C46: Saída | D46: iFood | E46: Banco Principal | F46: Pix | G46: 0 | J46: 2026-06 | K46: =K45 + IF(C46="Entrada", G46, -G46) -> -15473.13
A47: 46181 | B47: Cartão de credito | C47: Saída | D47: Cartao de Credito | E47: Banco Principal | G47: 2570.76 | J47: 2026-06 | K47: =K46 + IF(C47="Entrada", G47, -G47) -> -18043.89
A48: 46181 | B48: Trafego pago | C48: Saída | D48: Marketing | E48: Banco Principal | G48: 1500 | J48: 2026-06 | K48: =K47 + IF(C48="Entrada", G48, -G48) -> -19543.89
A49: 46181 | B49: Boleto Mec 3 | C49: Saída | D49: Matéria Prima | E49: Banco Principal | G49: 1486.49 | J49: 2026-06 | K49: =K48 + IF(C49="Entrada", G49, -G49) -> -21030.38
A50: 46181 | B50: Boleto Polar | C50: Saída | D50: Matéria Prima | E50: Banco Principal | G50: 772.73 | J50: 2026-06 | K50: =K49 + IF(C50="Entrada", G50, -G50) -> -21803.11
A51: 46181 | B51: Boleto Polar | C51: Saída | D51: Matéria Prima | E51: Banco Principal | G51: 444.67 | J51: 2026-06 | K51: =K50 + IF(C51="Entrada", G51, -G51) -> -22247.78
A52: 46181 | B52: Boleto guardanapos | C52: Saída | D52: Mat Consumo | E52: Banco Principal | G52: 571.9 | J52: 2026-06 | K52: =K51 + IF(C52="Entrada", G52, -G52) -> -22819.68
A53: 46182 | B53: Luz e água | C53: Saída | D53: CustoFixo | E53: Caixa | F53: Dinheiro | G53: 2440.75 | J53: 2026-06 | K53: =K52 + IF(C53="Entrada", G53, -G53) -> -25260.43
A54: 46182 | B54: Boleto Diniz | C54: Saída | D54: Matéria Prima | E54: Banco Principal | G54: 182.55 | J54: 2026-06 | K54: =K53 + IF(C54="Entrada", G54, -G54) -> -25442.98
A55: 46182 | B55: Boleto riber | C55: Saída | D55: Matéria Prima | E55: Banco Principal | G55: 1084.28 | J55: 2026-06 | K55: =K54 + IF(C55="Entrada", G55, -G55) -> -26527.26
A56: 46182 | B56: Boleto riber | C56: Saída | D56: Matéria Prima | E56: Banco Principal | G56: 578 | J56: 2026-06 | K56: =K55 + IF(C56="Entrada", G56, -G56) -> -27105.26
A57: 46182 | B57: Boleto vigilância sanitária | C57: Saída | D57: CustoFixo | E57: Banco Principal | G57: 304.92 | J57: 2026-06 | K57: =K56 + IF(C57="Entrada", G57, -G57) -> -27410.18
A58: 46182 | B58: Vendas | C58: Entrada | D58: Vendas | G58: 1097 | J58: 2026-06 | K58: =K57 + IF(C58="Entrada", G58, -G58) -> -26313.18
A59: 46182 | B59: Vendas iFood | C59: Entrada | D59: Vendas iFood | E59: Banco Principal | G59: 0 | J59: 2026-06 | K59: =K58 + IF(C59="Entrada", G59, -G59) -> -26313.18
A60: 46182 | B60: Motoboy | C60: Saída | D60: iFood | E60: Banco Principal | F60: Pix | G60: 0 | J60: 2026-06 | K60: =K59 + IF(C60="Entrada", G60, -G60) -> -26313.18
A61: 46182 | B61: Dedetizacao | C61: Saída | D61: Manutenção | E61: Banco Principal | F61: Pix | G61: 500 | J61: 2026-06 | K61: =K60 + IF(C61="Entrada", G61, -G61) -> -26813.18
A62: 46183 | B62: Vendas | C62: Entrada | D62: Vendas | G62: 912 | J62: 2026-06 | K62: =K61 + IF(C62="Entrada", G62, -G62) -> -25901.18
A63: 46183 | B63: Vendas Ifood | C63: Entrada | D63: Vendas iFood | E63: Banco Principal | G63: 0 | J63: 2026-06 | K63: =K62 + IF(C63="Entrada", G63, -G63) -> -25901.18
A64: 46183 | B64: Motoboy | C64: Saída | D64: iFood | E64: Banco Principal | F64: Pix | G64: 0 | J64: 2026-06 | K64: =K63 + IF(C64="Entrada", G64, -G64) -> -25901.18
A65: 46183 | B65: Royalty | C65: Saída | D65: Royalt | E65: Banco Principal | F65: Pix | G65: 7228.96 | J65: 2026-06 | K65: =K64 + IF(C65="Entrada", G65, -G65) -> -33130.14
A66: 46183 | B66: Marketing | C66: Saída | D66: Marketing | E66: Banco Principal | F66: Pix | G66: 450 | J66: 2026-06 | K66: =K65 + IF(C66="Entrada", G66, -G66) -> -33580.14
A67: 46183 | B67: Unigra | C67: Saída | D67: Matéria Prima | E67: Banco Principal | G67: 1085.93 | J67: 2026-06 | K67: =K66 + IF(C67="Entrada", G67, -G67) -> -34666.07
A68: 46183 | B68: Seguro de vida | C68: Saída | D68: Salário | E68: Banco Principal | G68: 60 | J68: 2026-06 | K68: =K67 + IF(C68="Entrada", G68, -G68) -> -34726.07
A69: 46183 | B69: Plano de Saude | C69: Saída | D69: Salário | E69: Banco Principal | G69: 204.5 | J69: 2026-06 | K69: =K68 + IF(C69="Entrada", G69, -G69) -> -34930.57
A70: 46184 | B70: Adiantamento Tais | C70: Saída | D70: Salário | E70: Banco Principal | F70: Pix | G70: 0 | J70: 2026-06 | K70: =K69 + IF(C70="Entrada", G70, -G70) -> -34930.57
A71: 46184 | B71: Vendas | C71: Entrada | D71: Vendas | G71: 939 | J71: 2026-06 | K71: =K70 + IF(C71="Entrada", G71, -G71) -> -33991.57
A72: 46184 | B72: Vendas Ifood | C72: Entrada | D72: Vendas iFood | E72: Banco Principal | G72: 54 | J72: 2026-06 | K72: =K71 + IF(C72="Entrada", G72, -G72) -> -33937.57
A73: 46184 | B73: Motoboy | C73: Saída | D73: iFood | E73: Banco Principal | F73: Pix | G73: 9 | J73: 2026-06 | K73: =K72 + IF(C73="Entrada", G73, -G73) -> -33946.57
A74: 46185 | B74: Vendas | C74: Entrada | D74: Vendas | G74: 1802 | J74: 2026-06 | K74: =K73 + IF(C74="Entrada", G74, -G74) -> -32144.57
A75: 46185 | B75: Vendas Ifood | C75: Entrada | D75: Vendas iFood | E75: Banco Principal | G75: 103 | J75: 2026-06 | K75: =K74 + IF(C75="Entrada", G75, -G75) -> -32041.57
A76: 46185 | B76: Motoboy | C76: Saída | D76: iFood | E76: Banco Principal | F76: Pix | G76: 17 | J76: 2026-06 | K76: =K75 + IF(C76="Entrada", G76, -G76) -> -32058.57
A77: 46185 | B77: Leite | C77: Saída | D77: Matéria Prima | E77: Caixa | F77: Dinheiro | G77: 376 | J77: 2026-06 | K77: =K76 + IF(C77="Entrada", G77, -G77) -> -32434.57
A78: 46186 | B78: Vendas | C78: Entrada | D78: Vendas | G78: 3938 | J78: 2026-06 | K78: =K77 + IF(C78="Entrada", G78, -G78) -> -28496.57
A79: 46186 | B79: Vendas Ifood | C79: Entrada | D79: Vendas iFood | E79: Banco Principal | G79: 0 | J79: 2026-06 | K79: =K78 + IF(C79="Entrada", G79, -G79) -> -28496.57
A80: 46186 | B80: Moyoboy | C80: Saída | D80: Vendas iFood | E80: Banco Principal | F80: Pix | G80: 9 | J80: 2026-06 | K80: =K79 + IF(C80="Entrada", G80, -G80) -> -28505.57
A81: 46187 | B81: Vendas | C81: Entrada | D81: Vendas | G81: 4218 | J81: 2026-06 | K81: =K80 + IF(C81="Entrada", G81, -G81) -> -24287.57
A82: 46187 | B82: Vendas Ifood | C82: Entrada | D82: Vendas iFood | E82: Banco Principal | G82: 252 | J82: 2026-06 | K82: =K81 + IF(C82="Entrada", G82, -G82) -> -24035.57
A83: 46187 | B83: Vale Luany | C83: Saída | D83: Salário | E83: Caixa | F83: Dinheiro | G83: 10 | J83: 2026-06 | K83: =K82 + IF(C83="Entrada", G83, -G83) -> -24045.57
A84: 46187 | B84: Motoboy | C84: Saída | D84: iFood | E84: Banco Principal | F84: Pix | G84: 27 | J84: 2026-06 | K84: =K82 + IF(C84="Entrada", G84, -G84) -> -24062.57
A85: 46188 | B85: Vendas | C85: Entrada | D85: Vendas | G85: 764 | J85: 2026-06 | K85: =K84 + IF(C85="Entrada", G85, -G85) -> -23298.57
A86: 46188 | B86: Vendas Ifood | C86: Entrada | D86: Vendas iFood | E86: Banco Principal | G86: 0 | J86: 2026-06 | K86: =K85 + IF(C86="Entrada", G86, -G86) -> -23298.57
A87: 46188 | B87: Motoboy | C87: Saída | D87: iFood | E87: Banco Principal | F87: Pix | G87: 0 | J87: 2026-06 | K87: =K86 + IF(C87="Entrada", G87, -G87) -> -23298.57
A88: 46188 | B88: Boleto odonto | C88: Saída | D88: Salário | E88: Banco Principal | G88: 180 | J88: 2026-06 | K88: =K87 + IF(C88="Entrada", G88, -G88) -> -23478.57
A89: 46188 | B89: Contabilidade | C89: Saída | D89: Contabilidade | E89: Banco Principal | G89: 800 | J89: 2026-06 | K89: =K88 + IF(C89="Entrada", G89, -G89) -> -24278.57
A90: 46188 | B90: Diniz | C90: Saída | D90: Matéria Prima | E90: Banco Principal | G90: 231.55 | J90: 2026-06 | K90: =K89 + IF(C90="Entrada", G90, -G90) -> -24510.12
A91: 46188 | B91: Croiassant | C91: Saída | D91: Matéria Prima | E91: Banco Principal | F91: Pix | G91: 225 | J91: 2026-06 | K91: =K90 + IF(C91="Entrada", G91, -G91) -> -24735.12
A92: 46188 | B92: DAE | C92: Saída | D92: Impostos | E92: Banco Principal | G92: 606.58 | J92: 2026-06 | K92: =K91 + IF(C92="Entrada", G92, -G92) -> -25341.7
A93: 46189 | B93: Vendas | C93: Entrada | D93: Vendas | G93: 1249 | J93: 2026-06 | K93: =K92 + IF(C93="Entrada", G93, -G93) -> -24092.7
A94: 46189 | B94: Vendas Ifood | C94: Entrada | D94: Vendas iFood | E94: Banco Principal | G94: 254 | J94: 2026-06 | K94: =K93 + IF(C94="Entrada", G94, -G94) -> -23838.7
A95: 46189 | B95: Motoboy | C95: Saída | D95: iFood | E95: Banco Principal | F95: Pix | G95: 35 | J95: 2026-06 | K95: =K94 + IF(C95="Entrada", G95, -G95) -> -23873.7
A96: 46189 | B96: Boleto Riber | C96: Saída | D96: Matéria Prima | E96: Banco Principal | G96: 1084.28 | J96: 2026-06 | K96: =K95 + IF(C96="Entrada", G96, -G96) -> -24957.98
A97: 46189 | B97: Boleto Riber | C97: Saída | D97: Matéria Prima | E97: Caixa | G97: 578 | J97: 2026-06 | K97: =K96 + IF(C97="Entrada", G97, -G97) -> -25535.98
A98: 46189 | B98: Boleto Diniz | C98: Saída | D98: Matéria Prima | E98: Banco Principal | G98: 136.51 | J98: 2026-06 | K98: =K97 + IF(C98="Entrada", G98, -G98) -> -25672.49
A99: 46189 | B99: Adesivo + plaquinha | C99: Saída | D99: Marketing | E99: Banco Principal | F99: Pix | G99: 45 | J99: 2026-06 | K99: =K98 + IF(C99="Entrada", G99, -G99) -> -25717.49
A100: 46189 | B100: Papelaria | C100: Saída | D100: Papelaria | E100: Caixa | F100: Dinheiro | G100: 20 | J100: 2026-06 | K100: =K99 + IF(C100="Entrada", G100, -G100) -> -25737.49
...

Sheet Sabores_Receitas
A1: Sabor | B1: Tipo | C1: Ingrediente | D1: Unidade | E1: Quantidade
A2: Abacaxi | B2: Sorbet | C2: Água | D2: Gramas | E2: 1100
A3: Abacaxi | B3: Sorbet | C3: Sacarose | D3: Gramas | E3: 320
A4: Abacaxi | B4: Sorbet | C4: Base Fruta | D4: Gramas | E4: 140
A5: Abacaxi | B5: Sorbet | C5: Açúcar invertido | D5: Gramas | E5: 80
A6: Abacaxi | B6: Sorbet | C6: Abacaxi | D6: Gramas | E6: 2000
A7: Abacaxi | B7: Sorbet | C7: Glucose em pó 38DE | D7: Gramas | E7: 320
A8: Abacaxi | B8: Sorbet | C8: Fibra | D8: Gramas | E8: 40
A9: Abacaxi com hortelã | B9: Sorbet | C9: Água | D9: Gramas | E9: 1085.8835
A10: Abacaxi com hortelã | B10: Sorbet | C10: Sacarose | D10: Gramas | E10: 315.89339
A11: Abacaxi com hortelã | B11: Sorbet | C11: Base Fruta | D11: Gramas | E11: 138.20336
A12: Abacaxi com hortelã | B12: Sorbet | C12: Açúcar invertido | D12: Gramas | E12: 78.973346
A13: Abacaxi com hortelã | B13: Sorbet | C13: Abacaxi | D13: Gramas | E13: 1974.3337
... A1275: Chocolate com Frutas Vermelhas Zero | B1275: Diet | C1275: Frutas Vermelhas Zero J&B | D1275: Gramas | E1275: 405.5

Sheet Valor_Cuba
A1: Sabor | B1: Tipo | C1: Item | D1: Mdd | E1: Qtd | F1: Proporção em % | G1: Valor | K1: Valores da Materia Prima
A2: Pistache | B2: Gelato | C2: Leite Integral Fresco | D2: Gramas | E2: 2736 | F2: 68.4 | G2: 12.8592 | K2: Valor | L2: Peso Prod | M2: 1 kg | P2: Gramas | Q2: Valor
A3: Pistache | B3: Gelato | C3: Creme de Leite 70% | D3: Gramas | E3: 112 | F3: 2.8 | G3: 2.8 | J3: Leite Integral Fresco | K3: 4.7 | L3: 1kg | M3: 4.7 | O3: Copinho Pequeno | P3: 150 | Q3: 21
A4: Pistache | B4: Gelato | C4: Sacarose | D4: Gramas | E4: 360 | F4: 9 | G4: 1.008 | J4: Creme de Leite 70% | K4: 25 | L4: 1kg | M4: 25 | O4: Copinho Médio | P4: 210 | Q4: 25
A5: Pistache | B5: Gelato | C5: Açúcar invertido | D5: Gramas | E5: 80 | F5: 2 | G5: 0.47997139 | J5: Sacarose | K5: 14 | L5: 5kg | M5: 2.8 | O5: Grandissimo | P5: 300 | Q5: 33
A6: Pistache | B6: Gelato | C6: Base 6 MEC 3 | D6: Gramas | E6: 20 | F6: 0.5 | G6: 4.55808 | J6: Açúcar fino | K6: 4.4 | L6: 1kg | M6: 4.4 | O6: Pequeno Viagem | P6: 150 | Q6: 21
A7: Pistache | B7: Gelato | C7: Glucose em pó 38DE | D7: Gramas | E7: 200 | F7: 5 | G7: 1.5999198 | J7: Sal | K7: 2.2 | L7: 1kg | M7: 2.2 | O7: Grande Viagem | P7: 250 | Q7: 33
A8: Pistache | B8: Gelato | C8: Leite em pó desnatado | D8: Gramas | E8: 120 | F8: 3 | G8: 3.12 | J8: Açúcar invertido | K8: 179.98927 | L8: 30kg | M8: 5.9996423 | O8: Cascao 1 Bola | P8: 160 | Q8: 22
A9: Pistache | B9: Gelato | C9: Pistache Califórnia | D9: Gramas | E9: 252 | F9: 6.3 | G9: 80.904197 | J9: Glucose em pó 38DE | K9: 199.98998 | L9: 25kg | M9: 7.9995992 | O9: Cascao 2 Bola | P9: 250 | Q9: 28
A10: Pistache | B10: Gelato | C10: Sal | D10: Gramas | E10: 12 | F10: 0.3 | G10: 0.0264 | J10: Leite em pó desnatado | K10: 650 | L10: 25kg | M10: 26
A11: Pistache | B11: Gelato | C11: Pistache Diamante | D11: Gramas | E11: 108 | F11: 2.7 | G11: 38.478857 | J11: Castanha de caju
A12: Pistache | B12: Gelato | C12: Pistache granel | D12: Gramas | E12: 60 | F12: Mescla | G12: 12.2466 | J12: Cacau em pó Holandês | K12: 2351.02 | L12: 25kg | M12: 94.0408
E13: 4060 | G13: 158.08123 | J13: Avelã | K13: 127.95 | L13: 1kg | M13: 127.95
J14: Pistache granel | K14: 204.11 | L14: 1kg | M14: 204.11
A15: Sabor | B15: Tipo | C15: Item | D15: Mdd | E15: Qtd | F15: Proporção em % | G15: Valor | J15: Base 6 MEC 3 | K15: 569.76 | L15: 2,5kg | M15: 227.904
A16: Kinder Bueno | B16: Gelato | C16: Leite Integral Fresco | D16: Gramas | E16: 2716 | F16: 67.9 | G16: 12.7652 | J16: Pistache Califórnia | K16: 8026.21 | L16: 25kg | M16: 321.0484
A17: Kinder Bueno | B17: Gelato | C17: Creme de Leite 70% | D17: Gramas | E17: 120 | F17: 3 | G17: 3 | J17: Pistache Diamante | K17: 1247 | L17: 3,5kg | M17: 356.28571
A18: Kinder Bueno | B18: Gelato | C18: Sacarose | D18: Gramas | E18: 360 | F18: 9 | G18: 1.008 | J18: Nocciola Pasta | K18: 2645.99 | L18: 25kg | M18: 105.8396
A19: Kinder Bueno | B19: Gelato | C19: Açúcar invertido | D19: Gramas | E19: 160 | F19: 4 | G19: 0.95994277 | J19: Quella | K19: 171.08 | L19: 3kg | M19: 57.026667
A20: Kinder Bueno | B20: Gelato | C20: Base 6 MEC 3 | D20: Gramas | E20: 20 | F20: 0.5 | G20: 4.55808 | J20: Creme Cheese Cake Aromitalia
A21: Kinder Bueno | B21: Gelato | C21: Glucose em pó 38DE | D21: Gramas | E21: 240 | F21: 6 | G21: 1.9199038 | J21: Fior di Bosco
A22: Kinder Bueno | B22: Gelato | C22: Leite em pó desnatado | D22: Gramas | E22: 120 | F22: 3 | G22: 3.12 | J22: Doce de Leite | K22: 211 | L22: 9.8kg | M22: 21.530612
A23: Kinder Bueno | B23: Gelato | C23: Nocciola Pasta | D23: Gramas | E23: 260 | F23: 6.5 | G23: 27.518296 | J23: Chocolate Blend | K23: 151.2 | L23: 2,1kg | M23: 72
A24: Kinder Bueno | B24: Gelato | C24: Sal | D24: Gramas | E24: 8 | F24: 0.2 | G24: 0.0176 | J24: Yogomix | K24: 195.02 | L24: 2kg | M24: 97.51
A25: Kinder Bueno | B25: Gelato | C25: Quella | D25: Gramas | E25: 300 | F25: Mescla | G25: 17.108 | J25: Amarena | K25: 416.99 | L25: 1kg | M25: 416.99
A26: Kinder Bueno | B26: Gelato | C26: Avelã | D26: Gramas | E26: 52 | F26: Mescla | G26: 6.6534 | J26: Nutella | K26: 184 | L26: 3kg | M26: 61.333333
E27: 4356 | G27: 78.628423
J28: AROMITALIA MESCLA STRAC BR STAND | K28: 145.43 | L28: 3,25KG | M28: 44.747692
A29: Sabor | B29: Tipo | C29: Item | D29: Mdd | E29: Qtd | F29: Proporção em % | G29: Valor | J29: LEITE COND AUREA BAG 5KG | K29: 94.07 | L29: 5kg | M29: 18.814
A30: Cheese Cake com Fior di Bosco | B30: Gelato | C30: Leite Integral Fresco | D30: Gramas | E30: 2860 | F30: 71.5 | J30: RECHEIO KIT KAT NESTLE 1,01KG | K30: 89.99 | L30: 1kg | M30: 89.99
A31: Cheese Cake com Fior di Bosco | B31: Gelato | C31: Creme de Leite 70% | D31: Gramas | E31: 152 | F31: 3.8 | J31: AROMITALIA MESCLA TRUFA BRANCA 3,5KG | K31: 143.521 | L31: 3,5kg | M31: 41.006
A32: Cheese Cake com Fior di Bosco | B32: Gelato | C32: Sacarose | D32: Gramas | E32: 380 | F32: 9.5 | J32: CHOC BRANCO KIBBLES CARGILL 25KG | K32: 2175 | L32: 25kg | M32: 87
A33: Cheese Cake com Fior di Bosco | B33: Gelato | C33: Açúcar invertido | D33: Gramas | E33: 116 | F33: 2.9 | J33: PASTA DE AMENDOIM INT BALSAMO 5KG | K33: 120.54 | L33: 5 kg | M33: 24.108
A34: Cheese Cake com Fior di Bosco | B34: Gelato | C34: Base 6 MEC 3 | D34: Gramas | E34: 20 | F34: 0.5
A35: Cheese Cake com Fior di Bosco | B35: Gelato | C35: Glucose em pó 38DE | D35: Gramas | E35: 172 | F35: 4.3
A36: Cheese Cake com Fior di Bosco | B36: Gelato | C36: Leite em pó desnatado | D36: Gramas | E36: 116 | F36: 2.9
A37: Cheese Cake com Fior di Bosco | B37: Gelato | C37: Creme Cheese Cake Aromitalia | D37: Gramas | E37: 188 | F37: 4.7
A38: Cheese Cake com Fior di Bosco | B38: Gelato | C38: Fior di Bosco | D38: Gramas | E38: 300 | F38: Mescla
A39: Cheese Cake com Fior di Bosco | B39: Gelato | C39: Castanha de caju | D39: Gramas | E39: 100 | F39: Mescla
A42: Sabor | B42: Tipo | C42: Item | D42: Mdd | E42: Qtd | F42: Proporção em % | G42: Valor
A43: Doce de Leite | B43: Gelato | C43: Leite Integral Fresco | D43: Gramas | E43: 576 | F43: 14.4
A44: Doce de Leite | B44: Gelato | C44: Creme de Leite 70% | D44: Gramas | E44: 180 | F44: 4.5
A45: Doce de Leite | B45: Gelato | C45: Sacarose | D45: Gramas | E45: 0 | F45: 0
A46: Doce de Leite | B46: Gelato | C46: Açúcar invertido | D46: Gramas | E46: 18 | F46: 0.45
A47: Doce de Leite | B47: Gelato | C47: Glucose em pó 38DE | D47: Gramas | E47: 160 | F47: 4
A48: Doce de Leite | B48: Gelato | C48: Leite em Pó Desnatado | D48: Gramas | E48: 240 | F48: 6
A49: Doce de Leite | B49: Gelato | C49: Base 6 MEC 3 | D49: Gramas | E49: 20 | F49: 0.5
A50: Doce de Leite | B50: Gelato | C50: Doce de Leite | D50: Gramas | E50: 1400 | F50: 35
A51: Doce de Leite | B51: Gelato | C51: Água | D51: Gramas | E51: 1400 | F51: 35
A52: Doce de Leite | B52: Gelato | C52: Sal | D52: Gramas | E52: 6 | F52: 0.15
A53: Doce de Leite | B53: Gelato | C53: Doce de leite | D53: Gramas | E53: 200 | F53: Mescla
A56: Sabor | B56: Tipo | C56: Item | D56: Mdd | E56: Qtd | F56: Proporção em % | G56: Valor
A57: Chocolate Belga | B57: Gelato | C57: Leite Integral Fresco | D57: Gramas | E57: 2620 | F57: 65.5
A58: Chocolate Belga | B58: Gelato | C58: Creme de Leite 70% | D58: Gramas | E58: 80 | F58: 2
A59: Chocolate Belga | B59: Gelato | C59: Sacarose | D59: Gramas | E59: 0 | F59: 0
A60: Chocolate Belga | B60: Gelato | C60: Açúcar invertido | D60: Gramas | E60: 80 | F60: 2
A61: Chocolate Belga | B61: Gelato | C61: Base 6 MEC 3 | D61: Gramas | E61: 20 | F61: 0.5
A62: Chocolate Belga | B62: Gelato | C62: Glucose em pó 38DE | D62: Gramas | E62: 140 | F62: 3.5
A63: Chocolate Belga | B63: Gelato | C63: Leite em pó desnatado | D63: Gramas | E63: 100 | F63: 2.5
A64: Chocolate Belga | B64: Gelato | C64: Chocolate Blend | D64: Gramas | E64: 800 | F64: 20
A65: Chocolate Belga | B65: Gelato | C65: Cacau em pó Holandês | D65: Gramas | E65: 160 | F65: 4
A66: Chocolate Belga | B66: Gelato | C66: Chocolate Blend | D66: Gramas | E66: 40 | F66: Mescla
A68: Sabor | B68: Tipo | C68: Item | D68: Mdd | E68: Qtd | F68: Proporção em % | G68: Valor
A69: Fior di Latte | B69: Gelato | C69: Leite Integral Fresco | D69: Gramas | E69: 2760 | F69: 69
A70: Fior di Latte | B70: Gelato | C70: Creme de Leite 70% | D70: Gramas | E70: 320 | F70: 8
A71: Fior di Latte | B71: Gelato | C71: Sacarose | D71: Gramas | E71: 480 | F71: 12
A72: Fior di Latte | B72: Gelato | C72: Açúcar invertido | D72: Gramas | E72: 120 | F72: 3
A73: Fior di Latte | B73: Gelato | C73: Base 6 MEC 3 | D73: Gramas | E73: 20 | F73: 0.5
A74: Fior di Latte | B74: Gelato | C74: Glucose em pó 38DE | D74: Gramas | E74: 180 | F74: 4.5
A75: Fior di Latte | B75: Gelato | C75: Leite em pó desnatado | D75: Gramas | E75: 120 | F75: 3
A78: Sabor | B78: Tipo | C78: Item | D78: Mdd | E78: Qtd | F78: Proporção em % | G78: Valor
A79: Iogurte com Amarena | B79: Gelato | C79: Leite Integral Fresco | D79: Gramas | E79: 2660 | F79: 66.5
A80: Iogurte com Amarena | B80: Gelato | C80: Creme de Leite 70% | D80: Gramas | E80: 240 | F80: 6
A81: Iogurte com Amarena | B81: Gelato | C81: Sacarose | D81: Gramas | E81: 440 | F81: 11
A82: Iogurte com Amarena | B82: Gelato | C82: Açúcar invertido | D82: Gramas | E82: 200 | F82: 5
A83: Iogurte com Amarena | B83: Gelato | C83: Base 6 MEC 3 | D83: Gramas | E83: 20 | F83: 0.5
A84: Iogurte com Amarena | B84: Gelato | C84: Glucose em pó 38DE | D84: Gramas | E84: 160 | F84: 4
A85: Iogurte com Amarena | B85: Gelato | C85: Leite em pó desnatado | D85: Gramas | E85: 80 | F85: 2
A86: Iogurte com Amarena | B86: Gelato | C86: Yogomix | D86: Gramas | E86: 200 | F86: 5
A87: Iogurte com Amarena | B87: Gelato | C87: Amarena | D87: Gramas | E87: 300 | F87: Mescla
A90: Sabor | B90: Tipo | C90: Item | D90: Mdd | E90: Qtd | F90: Proporção em % | G90: Valor
A91: Nutellina | B91: Gelato | C91: Leite Integral Fresco | D91: Gramas | E91: 2760 | F91: 69
A92: Nutellina | B92: Gelato | C92: Creme de Leite 70% | D92: Gramas | E92: 320 | F92: 8
A93: Nutellina | B93: Gelato | C93: Sacarose | D93: Gramas | E93: 480 | F93: 12
A94: Nutellina | B94: Gelato | C94: Açúcar invertido | D94: Gramas | E94: 120 | F94: 3
A95: Nutellina | B95: Gelato | C95: Base 6 MEC 3 | D95: Gramas | E95: 20 | F95: 0.5
A96: Nutellina | B96: Gelato | C96: Glucose em pó 38DE | D96: Gramas | E96: 180 | F96: 4.5
A97: Nutellina | B97: Gelato | C97: Leite em pó desnatado | D97: Gramas | E97: 120 | F97: 3
A98: Nutellina | B98: Gelato | C98: Nutella | D98: Gramas | E98: 400 | F98: Mescla

Sheet Producao_Cubas
A1: Data | B1: Sabor | C1: Produtor | D1: Quantidade
A2: 45962 | B2: cheese cake | C2: Natalia+Alisson | D2: 11
A3: 45962 | B3: Kinder Bueno | C3: Natalia+Alisson | D3: 11
A4: 45962 | B4: chocolate Nero | C4: Natalia+Alisson | D4: 1
A5: 45963 | B5: Pistache | C5: Natalia+Alisson | D5: 9
A6: 45963 | B6: Iogurte com amarena | C6: Natalia+Alisson | D6: 7
A7: 45963 | B7: nutellina | C7: Natalia+Alisson | D7: 7
A8: 45963 | B8: fior de latte | C8: Natalia+Alisson | D8: 7
A9: 45963 | B9: leite ninho c/ Nutella | C9: Natalia+Alisson | D9: 1
A10: 45963 | B10: doce de leite | C10: Natalia+Alisson | D10: 9
A11: 45963 | B11: abacaxi | C11: Natalia+Alisson | D11: 1
A12: 45963 | B12: limão | C12: Natalia+Alisson | D12: 1
A13: 45967 | B13: sonho de valsa | C13: Natalia+Alisson | D13: 1
... A1122: 46203 | B1122: iogurt com amarena | C1122: Alisson | D1122: 1

Sheet Nutricional
A1: Sabor | B1: Kcal | C1: VD Kcal % | D1: Carboidratos g | E1: VD Carb % | F1: Açúcares Totais g | G1: Açúcares Adicionados g | H1: Gorduras Totais g | I1: VD Gord % | J1: Gorduras Saturadas g | K1: VD Sat % | L1: Proteína g | M1: VD Prot % | N1: Fibra g | O1: VD Fibra % | P1: Sódio mg | Q1: VD Sódio % | R1: Contém Leite | S1: Contém Açúcar
A2: Fior di Latte | B2: 173 | C2: 9 | D2: 24 | E2: 8 | F2: 21 | G2: 16 | H2: 7.1 | I2: 13 | J2: 4.5 | K2: 21 | L2: 3.4 | M2: 5 | N2: 0 | O2: 0 | P2: 54 | Q2: 2 | R2: Sim | S2: Sim
A3: Nutellina | B3: 207 | C3: 10 | D3: 27 | E3: 9 | F3: 24 | G3: 20 | H3: 9.3 | I3: 17 | J3: 5.1 | K3: 23 | L3: 3.7 | M3: 5 | N3: 0 | O3: 1 | P3: 53 | Q3: 2 | R3: Sim | S3: Sim
A4: Cheesecake de Frutas Vermelhas | B4: 185 | C4: 9 | D4: 27 | E4: 9 | F4: 23 | G4: 18 | H4: 6.7 | I4: 12 | J4: 3.3 | K4: 15 | L4: 3.7 | M4: 5 | N4: 0 | O4: 1 | P4: 55 | Q4: 2 | R4: Sim | S4: Sim
A5: Iogurte com Amarena | B5: 180 | C5: 9 | D5: 29 | E5: 10 | F5: 23 | G5: 19 | H5: 5.5 | I5: 10 | J5: 3.5 | K5: 16 | L5: 3.8 | M5: 5 | N5: 0 | O5: 0 | P5: 58 | Q5: 2 | R5: Sim | S5: Sim
A6: Doce de Leite | B6: 190 | C6: 9 | D6: 30 | E6: 10 | F6: 26 | G6: 18 | H6: 5.6 | I6: 10 | J6: 3.5 | K6: 16 | L6: 5.2 | M6: 7 | N6: 0 | O6: 0 | P6: 172 | Q6: 7 | R6: Sim | S6: Sim
A7: Kinder Bueno | B7: 219 | C7: 11 | D7: 25 | E7: 8 | F7: 22 | G7: 17 | H7: 11.1 | I7: 20 | J7: 3.1 | K7: 14 | L7: 4.7 | M7: 6 | N7: 0.8 | O7: 3 | P7: 108 | Q7: 4 | R7: Sim | S7: Sim
A8: Pistache | B8: 186 | C8: 9 | D8: 23 | E8: 8 | F8: 18 | G8: 12 | H8: 8.6 | I8: 16 | J8: 3.1 | K8: 14 | L8: 5.4 | M8: 7 | N8: 1 | O8: 4 | P8: 148 | Q8: 6 | R8: Sim | S8: Sim
A9: Chocolate Belga | B9: 195 | C9: 10 | D9: 25 | E9: 8 | F9: 20 | G9: 14 | H9: 9.4 | I9: 17 | J9: 5.8 | K9: 26 | L9: 4.5 | M9: 6 | N9: 2.1 | O9: 8 | P9: 53 | Q9: 2 | R9: Sim | S9: Sim
A10: Pezzo del Nord | B10: 178 | C10: 9 | D10: 26 | E10: 9 | F10: 18 | G10: 14 | H10: 7.6 | I10: 14 | J10: 3.4 | K10: 16 | L10: 4.9 | M10: 6 | N10: 2.4 | O10: 9 | P10: 40 | Q10: 2 | R10: Sim | S10: Sim
A11: Morango | B11: 111 | C11: 6 | D11: 27 | E11: 9 | F11: 21 | G11: 19 | H11: 0 | I11: 0 | J11: 0 | K11: 0 | L11: 0 | M11: 0 | N11: 1.1 | O11: 4 | P11: 0 | Q11: 0 | R11: Não | S11: Sim
A12: Limão Siciliano | B12: 109 | C12: 5 | D12: 27 | E12: 9 | F12: 20 | G12: 20 | H12: 0 | I12: 0 | J12: 0 | K12: 0 | L12: 0 | M12: 0 | N12: 1.7 | O12: 7 | P12: 6 | Q12: 0 | R12: Não | S12: Sim
A13: Coco | B13: 121 | C13: 6 | D13: 6 | E13: 2 | F13: 5.3 | G13: 0 | H13: 6.5 | I13: 12 | J13: 5.2 | K13: 23 | L13: 3.3 | M13: 4 | N13: 3.4 | O13: 14 | P13: 53 | Q13: 2 | R13: Sim | S13: Não
A14: Gianduia | B14: 123 | C14: 6 | D14: 7.3 | E14: 2 | F14: 5.5 | G14: 0 | H14: 5.9 | I14: 11 | J14: 2 | K14: 9 | L14: 4.6 | M14: 6 | N14: 4.1 | O14: 16 | P14: 99 | Q14: 4 | R14: Sim | S14: Não

Sheet Metas
A1: Indicador | B1: Meta | C1: Obs
A2: Faturamento mensal | B2: 100000 | C2: R$ — ajuste conforme a estação
A3: CMV % | B3: 32 | C3: percentual máximo sobre o faturamento
A4: Folha % | B4: 28 | C4: percentual máximo sobre o faturamento
A5: Marketing % | B5: 5 | C5: percentual máximo sobre o faturamento
A6: Resultado mensal | B6: 15000 | C6: R$ — lucro operacional desejado
